Workbook

Sheet Cover
A6: Scaled CECL Allowance for Losses Estimator (SCALE)
A12: Prepared For:
A13: ='Historical Data'!B2
A16: For Period Ending
A17: ='Calc tab'!AE6
A19: Presented by:
B35: ="© "&YEAR('Historical Data'!AY8)&" TCT Risk Solutions" | E35: ="For Period Ending "&TEXT(Cover!A17,"mm/dd/yyyy")
B36: P.O. Box 2210 | E36: =A13
B37: Eagle, ID 83616
B38: Voice (208) 939-8366 - Fax (208) 938-6276
B39: E-Mail: RThompson@tctrisk.com or Office@tctrisk.com

Sheet Introduction
B2: ='Historical Data'!B2
B3: =Cover!A6
B4: ="For Period Ending "&TEXT(Cover!A17,"mm/dd/yyyy")
B8: Introduction to the Model
C9: This report explains the anticipated loan loss exposure to the credit union using the Scaled CECL Allowance for Losses Estimator (SCALE). A credit union’s allowance account is directly related to the risk of loss resulting from non-performing loans in the portfolio. Because of this relationship, it is critical that a credit union accurately identify risk and allow for that risk in its financial statements.
C11: In a Policy Guidance Statement from 2006 the Office of Comptroller of the Currency stated:
D13: “The ALLL represents one of the most significant estimates in an institution's financial statements and regulatory reports. Because of its significance, each institution has a responsibility for developing, maintaining, and documenting a comprehensive, systematic, and consistently applied process for determining the amounts of the ALLL and the provision for loan and lease losses (PLLL). To fulfill this responsibility, each institution should ensure controls are in place to consistently determine the ALLL in accordance with GAAP, the institution's stated policies and procedures, management's best judgment and relevant supervisory guidance.”
C15: For financial institutions adopting the CECL methodology, an Allowance for Credit Losses (ACL) for loans replaces the former Allowance for Loan and Lease Losses (ALLL) referenced by the OCC. Both methodologies provide for an estimate of uncollectible amounts maintained through a valuation account adjusted through charges to operating income. The measurement framework and conceptual basis supporting an ACL differ, however, from those of the allowance for loan and lease losses.
C17: The SCALE method is one of the two methodologies offered by TCT Risk Solutions for calculating an estimate of uncollectible amounts in the loan portfolio. It was originally introduced by the Federal Reserve as a simplified application for banks. TCT has adapted this model with components of the WARM methodology to create a simple, yet statistically valid method of estimating anticipated loss in the loan portfolio.
C19: Under CECL, ACLs are estimates of the expected credit losses on financial assets measured at amortized cost, which is measured using relevant information about past events, including historical credit loss experience on financial assets with similar risk characteristics, current conditions, and reasonable and supportable forecasts that affect the collectability of the remaining cash flows over the contractual term of the financial assets.
C21: TCT pulls core data from the 5300 to populate the model in order to calculate the ACL. The credit union provides information relative to individually identified loans to include in the model for calculating the ACL. Throughout the process TCT relies on input and guidance from Credit Union management.
B27: =Cover!B35 | L27: Confidential

Sheet Scale Calculation
C2: CECL Allowances for Credit Losses (ACL) Calculation
C3: ="Prepared For "&'Historical Data'!B2
C4: ="Quarter Ended "& TEXT('Calc tab'!AE6,"m/d/yyyy")
C5: ="Charter Number "&'Historical Data'!B3
C8: Portfolio Segment | E8: End of Period Loan Balance | F8: - | G8: Less Loans Assessed on Individual Basis | H8: = | I8: Net Loans Assessed on Pooled Basis | K8: CECL ACL Lifetime Loss Rate | L8: +/- | M8: Mgmt. Adj. | N8: = | O8: Life of Loan Loss Rate | Q8: Base CECL ACL | R8: +/- | S8: Adj. for Qualitative Factors | U8: Final CECL ACL
C9: Unsecured Credit Card Loans | E9: ='Calc tab'!AE7 | G9: =SUMIF(' Impaired Loans ASC 310-10'!$D$27:$D$412,C9,' Impaired Loans ASC 310-10'!$Q$27:$Q$412) | I9: =E9-G9 | K9: ='Calc tab'!AI58 | M9: ='Historical Data'!AY145 | O9: =K9+M9 | Q9: =I9*O9 | S9: ='Env Factor by Pool'!I17 | U9: =Q9+(Q9*S9)
C10: Payday Alternative Loans | E10: ='Calc tab'!AE8 | G10: =SUMIF(' Impaired Loans ASC 310-10'!$D$27:$D$412,C10,' Impaired Loans ASC 310-10'!$Q$27:$Q$412) | I10: =E10-G10 | K10: ='Calc tab'!AI59 | M10: ='Historical Data'!AY146 | O10: =K10+M10 | Q10: =I10*O10 | S10: ='Env Factor by Pool'!I25 | U10: =Q10+(Q10*S10)
C11: Non-Federally Guaranteed Student Loans | E11: ='Calc tab'!AE9 | G11: =SUMIF(' Impaired Loans ASC 310-10'!$D$27:$D$412,C11,' Impaired Loans ASC 310-10'!$Q$27:$Q$412) | I11: =E11-G11 | K11: ='Calc tab'!AI60 | M11: ='Historical Data'!AY147 | O11: =K11+M11 | Q11: =I11*O11 | S11: ='Env Factor by Pool'!I33 | U11: =Q11+(Q11*S11)
C12: All Other Unsecured Loans/Lines of Credit | E12: ='Calc tab'!AE10 | G12: =SUMIF(' Impaired Loans ASC 310-10'!$D$27:$D$412,C12,' Impaired Loans ASC 310-10'!$Q$27:$Q$412) | I12: =E12-G12 | K12: ='Calc tab'!AI61 | M12: ='Historical Data'!AY148 | O12: =K12+M12 | Q12: =I12*O12 | S12: ='Env Factor by Pool'!I41 | U12: =Q12+(Q12*S12)
C13: New Vehicle Loans | E13: ='Calc tab'!AE11 | G13: =SUMIF(' Impaired Loans ASC 310-10'!$D$27:$D$412,C13,' Impaired Loans ASC 310-10'!$Q$27:$Q$412) | I13: =E13-G13 | K13: ='Calc tab'!AI62 | M13: ='Historical Data'!AY149 | O13: =K13+M13 | Q13: =I13*O13 | S13: ='Env Factor by Pool'!I49 | U13: =Q13+(Q13*S13)
C14: Used Vehicle Loans | E14: ='Calc tab'!AE12 | G14: =SUMIF(' Impaired Loans ASC 310-10'!$D$27:$D$412,C14,' Impaired Loans ASC 310-10'!$Q$27:$Q$412) | I14: =E14-G14 | K14: ='Calc tab'!AI63 | M14: ='Historical Data'!AY150 | O14: =K14+M14 | Q14: =I14*O14 | S14: ='Env Factor by Pool'!I57 | U14: =Q14+(Q14*S14)
C15: Leases Receivable | E15: ='Calc tab'!AE13 | G15: =SUMIF(' Impaired Loans ASC 310-10'!$D$27:$D$412,C15,' Impaired Loans ASC 310-10'!$Q$27:$Q$412) | I15: =E15-G15 | K15: ='Calc tab'!AI64 | M15: ='Historical Data'!AY151 | O15: =K15+M15 | Q15: =I15*O15 | S15: ='Env Factor by Pool'!I65 | U15: =Q15+(Q15*S15)
C16: All Other Secured Non-Real Estate Loans/Lines of Credit | E16: ='Calc tab'!AE14 | G16: =SUMIF(' Impaired Loans ASC 310-10'!$D$27:$D$412,C16,' Impaired Loans ASC 310-10'!$Q$27:$Q$412) | I16: =E16-G16 | K16: ='Calc tab'!AI65 | M16: ='Historical Data'!AY152 | O16: =K16+M16 | Q16: =I16*O16 | S16: ='Env Factor by Pool'!I73 | U16: =Q16+(Q16*S16)
C17: Loans/Lines of Credit Secured by a First Lien on a single 1- to 4-Family Residential Property | E17: ='Calc tab'!AE15 | G17: =SUMIF(' Impaired Loans ASC 310-10'!$D$27:$D$412,C17,' Impaired Loans ASC 310-10'!$Q$27:$Q$412) | I17: =E17-G17 | K17: ='Calc tab'!AI66 | M17: ='Historical Data'!AY153 | O17: =K17+M17 | Q17: =I17*O17 | S17: ='Env Factor by Pool'!I81 | U17: =Q17+(Q17*S17)
C18: Loans/Lines of Credit Secured by a Junior Lien on a single 1- to 4-Family Residential Property | E18: ='Calc tab'!AE16 | G18: =SUMIF(' Impaired Loans ASC 310-10'!$D$27:$D$412,C18,' Impaired Loans ASC 310-10'!$Q$27:$Q$412) | I18: =E18-G18 | K18: ='Calc tab'!AI67 | M18: ='Historical Data'!AY154 | O18: =K18+M18 | Q18: =I18*O18 | S18: ='Env Factor by Pool'!I89 | U18: =Q18+(Q18*S18)
C19: All Other (Non-Commercial) Real Estate Loans/Lines of Credit | E19: ='Calc tab'!AE17 | G19: =SUMIF(' Impaired Loans ASC 310-10'!$D$27:$D$412,C19,' Impaired Loans ASC 310-10'!$Q$27:$Q$412) | I19: =E19-G19 | K19: ='Calc tab'!AI68 | M19: ='Historical Data'!AY155 | O19: =K19+M19 | Q19: =I19*O19 | S19: ='Env Factor by Pool'!I97 | U19: =Q19+(Q19*S19)
C20: Commercial Loans/Lines of Credit Real Estate Secured | E20: ='Calc tab'!AE18 | G20: =SUMIF(' Impaired Loans ASC 310-10'!$D$27:$D$412,C20,' Impaired Loans ASC 310-10'!$Q$27:$Q$412) | I20: =E20-G20 | K20: ='Calc tab'!AI69 | M20: ='Historical Data'!AY156 | O20: =K20+M20 | Q20: =I20*O20 | S20: ='Env Factor by Pool'!I145 | U20: =Q20+(Q20*S20)
C21: Commercial Loans/Lines of Credit Not Real Estate Secured | E21: ='Calc tab'!AE19 | G21: =SUMIF(' Impaired Loans ASC 310-10'!$D$27:$D$412,C21,' Impaired Loans ASC 310-10'!$Q$27:$Q$412) | I21: =E21-G21 | K21: ='Calc tab'!AI70 | M21: ='Historical Data'!AY157 | O21: =K21+M21 | Q21: =I21*O21 | S21: ='Env Factor by Pool'!I153 | U21: =Q21+(Q21*S21)
C23: Total | E23: =SUM(E9:E21) | I23: =SUM(I9:I21) | Q23: =SUM(Q9:$Q$21) | U23: =SUM(U9:U21)
Q25: Management Adjustment-Additional Environmental Factor | S25: ='Historical Data'!AY159 | U25: =I23*S25
Q27: Expected Losses on Loans Assessed on Individual Basis | U27: =' Impaired Loans ASC 310-10'!P24
Q29: Total Expected Losses on Loans | U29: =U23+U25+U27
Q30: Current ACL Balance | U30: ='Historical Data'!AY177
Q31: Adjustment | U31: =U29-U30
Q33: ACL/Total Loans | U33: =IF(U29=0,0,U29/E23)
C37: Explanation of ACL Calculation
C39: The calculation of the credit union’s ACL includes multiple components that combine to create a valid estimate of anticipated losses over the remaining life of loans in the portfolio. Those components as shown in the report above.
C41: Portfolio Segment: Loans are presented in groups, or pools, consistent with the presentation on the quarterly NCUA 5300 Call Report in this column.
C43: End of Period Loan Balance: Loan balances for each identified pool as shown in the NCUA 5300 Call reports for the end of the most recent quarter are listed in this column.
C45: Loans Assessed on Individual Basis: Loan that have been identified by credit union management as deteriorated in credit quality are listed by pool in this column.
C47: Loans Assessed on Pooled Basis: Individually assessed loans are subtracted from the End of Period loan balances for each pool and are displayed in this column.
C49: CECL ACL Lifetime Loss Rate: Based on the remaining life of loan for each loan pool, total losses for the period are summed for each pool and then divided by the average balance for the life period to arrive at a loss rate for each pool. These loss rates are shown in this column.
C51: Management Adjustment: Any adjustments to the loss rates for any pool, indicated by management judgement, are shown in this column.
C53: Life of Loan Loss Rate: The Lifetime Loss Rate and the Management Adjustments for each pool are totaled and displayed in this column.
C55: CECL ACL Base: The loss rate is multiplied times the Loans Assessed on Individual Basis to calculate the base ACL for each pool. The dollar amounts are shown in this column.
C57: Adjustment for Qualitative Factors: Two statistically validated Qualitative Factors are included in the model, advanced delinquency, and Environmental Stress Score. These factors are displayed for each pool on page 4. The indicated adjustment percentage for each pool is displayed in this column.
C59: CECL ACL Final: The Adjustment for Qualitative Factors percentage is multiplied by the CECL ALC base the resulting amount is added to the base to arrive at the CECL ACL Final. Dollar amounts for each pool is shown in this column.
... C71: ACL/Total Loans: This cells shows the percentage of total loan portfolio that is indicated in the ACL.
B77: =Cover!B35 | U77: Confidential

Sheet Env Factor by Pool
B1: ='Historical Data'!B2
B2: Environmental Factor for PLL
B3: ="For Period Ending "&TEXT('Historical Data'!AY8,"mm/dd/yyyy")
B5: Economic Stress Index Calculation
B6: State | C6: Unemployment Rate* | D6: Foreclosures per Person** | E6: Bankruptcies*** | F6: Population***
B7: ='Historical Data'!B4 | C7: ='Historical Data'!AY139 | D7: ='Historical Data'!AY140 | E7: ='Historical Data'!AY141 | F7: ='Historical Data'!AY142
B8: County | C8: Unemployment Rate | D8: Bankruptcy Percentage | E8: Foreclosure Percentage | F8: Economic Stress Index
B9: ='Historical Data'!B5 | C9: =C7 | D9: =E7/F7 | E9: =1/D7 | F9: =SUM(C9:E9)
B11: ='Scale Calculation'!C9
B12: Delinquency Variance | E12: Economic Stress
B13: Variance from Average | C13: Score | E13: Actual | F13: Score
B14: ='Calc tab'!AI92 | C14: =IF(B14>='Environmental Factor Ranges'!$J$9,'Environmental Factor Ranges'!$K$9,IF(B14>='Environmental Factor Ranges'!$J$10,'Environmental Factor Ranges'!$K$10,IF(B14>='Environmental Factor Ranges'!$J$11,'Environmental Factor Ranges'!$K$11,IF(B14>='Environmental Factor Ranges'!$J$12,'Environmental Factor Ranges'!$K$12,IF(B14>='Environmental Factor Ranges'!$J$13,'Environmental Factor Ranges'!$K$13,IF(B14>='Environmental Factor Ranges'!$J$14,'Environmental Factor Ranges'!$K$14,IF(B14>='Environmental Factor Ranges'!$J$15,'Environmental Factor Ranges'!$K$15,IF(B14>='Environmental Factor Ranges'!$J$16,'Environmental Factor Ranges'!$K$16,IF(B14>='Environmental Factor Ranges'!$J$17,'Environmental Factor Ranges'!$K$17,IF(B14>='Environmental Factor Ranges'!$J$18,'Environmental Factor Ranges'!$K$18,IF(B14>='Environmental Factor Ranges'!$J$19,'Environmental Factor Ranges'!$K$19,IF(B14>='Environmental Factor Ranges'!$J$20,'Environmental Factor Ranges'!$K$20,IF(B14>='Environmental Factor Ranges'!$J$21,'Environmental Factor Ranges'!$K$21,IF(B14>='Environmental Factor Ranges'!$J$22,'Environmental Factor Ranges'!$K$22,IF(B14>='Environmental Factor Ranges'!$J$23,'Environmental Factor Ranges'!$K$23,IF(B14>='Environmental Factor Ranges'!$J$24,'Environmental Factor Ranges'!$K$24,'Environmental Factor Ranges'!$K$25)))))))))))))))) | E14: =$F$9 | F14: =IF(E14>='Environmental Factor Ranges'!$L$9,'Environmental Factor Ranges'!$F$9,IF(E14>='Environmental Factor Ranges'!$L$10,'Environmental Factor Ranges'!$F$10,IF(E14>='Environmental Factor Ranges'!$L$11,'Environmental Factor Ranges'!$F$11,IF(E14>='Environmental Factor Ranges'!$L$12,'Environmental Factor Ranges'!$F$12,IF(E14>='Environmental Factor Ranges'!$L$13,'Environmental Factor Ranges'!$F$13,IF(E14>='Environmental Factor Ranges'!$L$14,'Environmental Factor Ranges'!$F$14,IF(E14>='Environmental Factor Ranges'!$L$15,'Environmental Factor Ranges'!$F$15,IF(E14>='Environmental Factor Ranges'!$L$16,'Environmental Factor Ranges'!$F$16,IF(E14>='Environmental Factor Ranges'!$L$17,'Environmental Factor Ranges'!$F$17,IF(E14>='Environmental Factor Ranges'!$L$18,'Environmental Factor Ranges'!$F$18,IF(E14>='Environmental Factor Ranges'!$L$19,'Environmental Factor Ranges'!$F$19,IF(E14>='Environmental Factor Ranges'!$L$20,'Environmental Factor Ranges'!$F$20,IF(E14>='Environmental Factor Ranges'!$L$21,'Environmental Factor Ranges'!$F$21,IF(E14>='Environmental Factor Ranges'!$L$22,'Environmental Factor Ranges'!$F$22,IF(E14>='Environmental Factor Ranges'!$L$23,'Environmental Factor Ranges'!$F$23,IF(E14>='Environmental Factor Ranges'!$L$24,'Environmental Factor Ranges'!$F$24,IF(E14>='Environmental Factor Ranges'!$L$25,'Environmental Factor Ranges'!$F$25,'Environmental Factor Ranges'!$F$26)))))))))))))))))
B15: ="Environmental Factor-"&B11
B16: =C14+F14
H17: Environmental Factor | I17: =B16
B19: ='Scale Calculation'!C10
B20: =$B$12 | E20: Economic Stress
B21: =B13 | C21: Score | E21: Actual | F21: Score
B22: ='Calc tab'!AI93 | C22: =IF(B22>='Environmental Factor Ranges'!$J$9,'Environmental Factor Ranges'!$K$9,IF(B22>='Environmental Factor Ranges'!$J$10,'Environmental Factor Ranges'!$K$10,IF(B22>='Environmental Factor Ranges'!$J$11,'Environmental Factor Ranges'!$K$11,IF(B22>='Environmental Factor Ranges'!$J$12,'Environmental Factor Ranges'!$K$12,IF(B22>='Environmental Factor Ranges'!$J$13,'Environmental Factor Ranges'!$K$13,IF(B22>='Environmental Factor Ranges'!$J$14,'Environmental Factor Ranges'!$K$14,IF(B22>='Environmental Factor Ranges'!$J$15,'Environmental Factor Ranges'!$K$15,IF(B22>='Environmental Factor Ranges'!$J$16,'Environmental Factor Ranges'!$K$16,IF(B22>='Environmental Factor Ranges'!$J$17,'Environmental Factor Ranges'!$K$17,IF(B22>='Environmental Factor Ranges'!$J$18,'Environmental Factor Ranges'!$K$18,IF(B22>='Environmental Factor Ranges'!$J$19,'Environmental Factor Ranges'!$K$19,IF(B22>='Environmental Factor Ranges'!$J$20,'Environmental Factor Ranges'!$K$20,IF(B22>='Environmental Factor Ranges'!$J$21,'Environmental Factor Ranges'!$K$21,IF(B22>='Environmental Factor Ranges'!$J$22,'Environmental Factor Ranges'!$K$22,IF(B22>='Environmental Factor Ranges'!$J$23,'Environmental Factor Ranges'!$K$23,IF(B22>='Environmental Factor Ranges'!$J$24,'Environmental Factor Ranges'!$K$24,'Environmental Factor Ranges'!$K$25)))))))))))))))) | E22: =$F$9 | F22: =IF(E22>='Environmental Factor Ranges'!$L$9,'Environmental Factor Ranges'!$F$9,IF(E22>='Environmental Factor Ranges'!$L$10,'Environmental Factor Ranges'!$F$10,IF(E22>='Environmental Factor Ranges'!$L$11,'Environmental Factor Ranges'!$F$11,IF(E22>='Environmental Factor Ranges'!$L$12,'Environmental Factor Ranges'!$F$12,IF(E22>='Environmental Factor Ranges'!$L$13,'Environmental Factor Ranges'!$F$13,IF(E22>='Environmental Factor Ranges'!$L$14,'Environmental Factor Ranges'!$F$14,IF(E22>='Environmental Factor Ranges'!$L$15,'Environmental Factor Ranges'!$F$15,IF(E22>='Environmental Factor Ranges'!$L$16,'Environmental Factor Ranges'!$F$16,IF(E22>='Environmental Factor Ranges'!$L$17,'Environmental Factor Ranges'!$F$17,IF(E22>='Environmental Factor Ranges'!$L$18,'Environmental Factor Ranges'!$F$18,IF(E22>='Environmental Factor Ranges'!$L$19,'Environmental Factor Ranges'!$F$19,IF(E22>='Environmental Factor Ranges'!$L$20,'Environmental Factor Ranges'!$F$20,'Environmental Factor Ranges'!$F$21))))))))))))
B23: ="Environmental Factor-"&B19
B24: =C22+F22
H25: Environmental Factor | I25: =B24
B27: ='Scale Calculation'!C11
B28: =$B$12 | E28: Economic Stress
B29: =B13 | C29: Score | E29: Actual | F29: Score
B30: ='Calc tab'!AI94 | C30: =IF(B30>='Environmental Factor Ranges'!$J$9,'Environmental Factor Ranges'!$K$9,IF(B30>='Environmental Factor Ranges'!$J$10,'Environmental Factor Ranges'!$K$10,IF(B30>='Environmental Factor Ranges'!$J$11,'Environmental Factor Ranges'!$K$11,IF(B30>='Environmental Factor Ranges'!$J$12,'Environmental Factor Ranges'!$K$12,IF(B30>='Environmental Factor Ranges'!$J$13,'Environmental Factor Ranges'!$K$13,IF(B30>='Environmental Factor Ranges'!$J$14,'Environmental Factor Ranges'!$K$14,IF(B30>='Environmental Factor Ranges'!$J$15,'Environmental Factor Ranges'!$K$15,IF(B30>='Environmental Factor Ranges'!$J$16,'Environmental Factor Ranges'!$K$16,IF(B30>='Environmental Factor Ranges'!$J$17,'Environmental Factor Ranges'!$K$17,IF(B30>='Environmental Factor Ranges'!$J$18,'Environmental Factor Ranges'!$K$18,IF(B30>='Environmental Factor Ranges'!$J$19,'Environmental Factor Ranges'!$K$19,IF(B30>='Environmental Factor Ranges'!$J$20,'Environmental Factor Ranges'!$K$20,IF(B30>='Environmental Factor Ranges'!$J$21,'Environmental Factor Ranges'!$K$21,IF(B30>='Environmental Factor Ranges'!$J$22,'Environmental Factor Ranges'!$K$22,IF(B30>='Environmental Factor Ranges'!$J$23,'Environmental Factor Ranges'!$K$23,IF(B30>='Environmental Factor Ranges'!$J$24,'Environmental Factor Ranges'!$K$24,'Environmental Factor Ranges'!$K$25)))))))))))))))) | E30: =$F$9 | F30: =IF(E30>='Environmental Factor Ranges'!$L$9,'Environmental Factor Ranges'!$F$9,IF(E30>='Environmental Factor Ranges'!$L$10,'Environmental Factor Ranges'!$F$10,IF(E30>='Environmental Factor Ranges'!$L$11,'Environmental Factor Ranges'!$F$11,IF(E30>='Environmental Factor Ranges'!$L$12,'Environmental Factor Ranges'!$F$12,IF(E30>='Environmental Factor Ranges'!$L$13,'Environmental Factor Ranges'!$F$13,IF(E30>='Environmental Factor Ranges'!$L$14,'Environmental Factor Ranges'!$F$14,IF(E30>='Environmental Factor Ranges'!$L$15,'Environmental Factor Ranges'!$F$15,IF(E30>='Environmental Factor Ranges'!$L$16,'Environmental Factor Ranges'!$F$16,IF(E30>='Environmental Factor Ranges'!$L$17,'Environmental Factor Ranges'!$F$17,IF(E30>='Environmental Factor Ranges'!$L$18,'Environmental Factor Ranges'!$F$18,IF(E30>='Environmental Factor Ranges'!$L$19,'Environmental Factor Ranges'!$F$19,IF(E30>='Environmental Factor Ranges'!$L$20,'Environmental Factor Ranges'!$F$20,'Environmental Factor Ranges'!$F$21))))))))))))
B31: ="Environmental Factor-"&B27
B32: =C30+F30
H33: Environmental Factor | I33: =B32
B35: ='Scale Calculation'!C12
B36: =$B$12 | E36: Economic Stress
B37: =B21 | C37: Score | E37: Actual | F37: Score
B38: ='Calc tab'!AI95 | C38: =IF(B38>='Environmental Factor Ranges'!$J$9,'Environmental Factor Ranges'!$K$9,IF(B38>='Environmental Factor Ranges'!$J$10,'Environmental Factor Ranges'!$K$10,IF(B38>='Environmental Factor Ranges'!$J$11,'Environmental Factor Ranges'!$K$11,IF(B38>='Environmental Factor Ranges'!$J$12,'Environmental Factor Ranges'!$K$12,IF(B38>='Environmental Factor Ranges'!$J$13,'Environmental Factor Ranges'!$K$13,IF(B38>='Environmental Factor Ranges'!$J$14,'Environmental Factor Ranges'!$K$14,IF(B38>='Environmental Factor Ranges'!$J$15,'Environmental Factor Ranges'!$K$15,IF(B38>='Environmental Factor Ranges'!$J$16,'Environmental Factor Ranges'!$K$16,IF(B38>='Environmental Factor Ranges'!$J$17,'Environmental Factor Ranges'!$K$17,IF(B38>='Environmental Factor Ranges'!$J$18,'Environmental Factor Ranges'!$K$18,IF(B38>='Environmental Factor Ranges'!$J$19,'Environmental Factor Ranges'!$K$19,IF(B38>='Environmental Factor Ranges'!$J$20,'Environmental Factor Ranges'!$K$20,IF(B38>='Environmental Factor Ranges'!$J$21,'Environmental Factor Ranges'!$K$21,IF(B38>='Environmental Factor Ranges'!$J$22,'Environmental Factor Ranges'!$K$22,IF(B38>='Environmental Factor Ranges'!$J$23,'Environmental Factor Ranges'!$K$23,IF(B38>='Environmental Factor Ranges'!$J$24,'Environmental Factor Ranges'!$K$24,'Environmental Factor Ranges'!$K$25)))))))))))))))) | E38: =$F$9 | F38: =IF(E38>='Environmental Factor Ranges'!$L$9,'Environmental Factor Ranges'!$F$9,IF(E38>='Environmental Factor Ranges'!$L$10,'Environmental Factor Ranges'!$F$10,IF(E38>='Environmental Factor Ranges'!$L$11,'Environmental Factor Ranges'!$F$11,IF(E38>='Environmental Factor Ranges'!$L$12,'Environmental Factor Ranges'!$F$12,IF(E38>='Environmental Factor Ranges'!$L$13,'Environmental Factor Ranges'!$F$13,IF(E38>='Environmental Factor Ranges'!$L$14,'Environmental Factor Ranges'!$F$14,IF(E38>='Environmental Factor Ranges'!$L$15,'Environmental Factor Ranges'!$F$15,IF(E38>='Environmental Factor Ranges'!$L$16,'Environmental Factor Ranges'!$F$16,IF(E38>='Environmental Factor Ranges'!$L$17,'Environmental Factor Ranges'!$F$17,IF(E38>='Environmental Factor Ranges'!$L$18,'Environmental Factor Ranges'!$F$18,IF(E38>='Environmental Factor Ranges'!$L$19,'Environmental Factor Ranges'!$F$19,IF(E38>='Environmental Factor Ranges'!$L$20,'Environmental Factor Ranges'!$F$20,'Environmental Factor Ranges'!$F$21))))))))))))
B39: ="Environmental Factor-"&B35
B40: =C38+F38
H41: Environmental Factor | I41: =B40
B43: ='Scale Calculation'!C13
B44: =$B$12 | E44: Economic Stress
B45: =B13 | C45: Score | E45: Actual | F45: Score
B46: ='Calc tab'!AI96 | C46: =IF(B46>='Environmental Factor Ranges'!$J$9,'Environmental Factor Ranges'!$K$9,IF(B46>='Environmental Factor Ranges'!$J$10,'Environmental Factor Ranges'!$K$10,IF(B46>='Environmental Factor Ranges'!$J$11,'Environmental Factor Ranges'!$K$11,IF(B46>='Environmental Factor Ranges'!$J$12,'Environmental Factor Ranges'!$K$12,IF(B46>='Environmental Factor Ranges'!$J$13,'Environmental Factor Ranges'!$K$13,IF(B46>='Environmental Factor Ranges'!$J$14,'Environmental Factor Ranges'!$K$14,IF(B46>='Environmental Factor Ranges'!$J$15,'Environmental Factor Ranges'!$K$15,IF(B46>='Environmental Factor Ranges'!$J$16,'Environmental Factor Ranges'!$K$16,IF(B46>='Environmental Factor Ranges'!$J$17,'Environmental Factor Ranges'!$K$17,IF(B46>='Environmental Factor Ranges'!$J$18,'Environmental Factor Ranges'!$K$18,IF(B46>='Environmental Factor Ranges'!$J$19,'Environmental Factor Ranges'!$K$19,IF(B46>='Environmental Factor Ranges'!$J$20,'Environmental Factor Ranges'!$K$20,IF(B46>='Environmental Factor Ranges'!$J$21,'Environmental Factor Ranges'!$K$21,IF(B46>='Environmental Factor Ranges'!$J$22,'Environmental Factor Ranges'!$K$22,IF(B46>='Environmental Factor Ranges'!$J$23,'Environmental Factor Ranges'!$K$23,IF(B46>='Environmental Factor Ranges'!$J$24,'Environmental Factor Ranges'!$K$24,'Environmental Factor Ranges'!$K$25)))))))))))))))) | E46: =$F$9 | F46: =IF(E46>='Environmental Factor Ranges'!$L$9,'Environmental Factor Ranges'!$F$9,IF(E46>='Environmental Factor Ranges'!$L$10,'Environmental Factor Ranges'!$F$10,IF(E46>='Environmental Factor Ranges'!$L$11,'Environmental Factor Ranges'!$F$11,IF(E46>='Environmental Factor Ranges'!$L$12,'Environmental Factor Ranges'!$F$12,IF(E46>='Environmental Factor Ranges'!$L$13,'Environmental Factor Ranges'!$F$13,IF(E46>='Environmental Factor Ranges'!$L$14,'Environmental Factor Ranges'!$F$14,IF(E46>='Environmental Factor Ranges'!$L$15,'Environmental Factor Ranges'!$F$15,IF(E46>='Environmental Factor Ranges'!$L$16,'Environmental Factor Ranges'!$F$16,IF(E46>='Environmental Factor Ranges'!$L$17,'Environmental Factor Ranges'!$F$17,IF(E46>='Environmental Factor Ranges'!$L$18,'Environmental Factor Ranges'!$F$18,IF(E46>='Environmental Factor Ranges'!$L$19,'Environmental Factor Ranges'!$F$19,IF(E46>='Environmental Factor Ranges'!$L$20,'Environmental Factor Ranges'!$F$20,'Environmental Factor Ranges'!$F$21))))))))))))
B47: ="Environmental Factor-"&B43
B48: =C46+F46
H49: Environmental Factor | I49: =B48
B51: ='Scale Calculation'!C14
B52: =$B$12 | E52: Economic Stress
B53: =B13 | C53: Score | E53: Actual | F53: Score
B54: ='Calc tab'!AI97 | C54: =IF(B54>='Environmental Factor Ranges'!$J$9,'Environmental Factor Ranges'!$K$9,IF(B54>='Environmental Factor Ranges'!$J$10,'Environmental Factor Ranges'!$K$10,IF(B54>='Environmental Factor Ranges'!$J$11,'Environmental Factor Ranges'!$K$11,IF(B54>='Environmental Factor Ranges'!$J$12,'Environmental Factor Ranges'!$K$12,IF(B54>='Environmental Factor Ranges'!$J$13,'Environmental Factor Ranges'!$K$13,IF(B54>='Environmental Factor Ranges'!$J$14,'Environmental Factor Ranges'!$K$14,IF(B54>='Environmental Factor Ranges'!$J$15,'Environmental Factor Ranges'!$K$15,IF(B54>='Environmental Factor Ranges'!$J$16,'Environmental Factor Ranges'!$K$16,IF(B54>='Environmental Factor Ranges'!$J$17,'Environmental Factor Ranges'!$K$17,IF(B54>='Environmental Factor Ranges'!$J$18,'Environmental Factor Ranges'!$K$18,IF(B54>='Environmental Factor Ranges'!$J$19,'Environmental Factor Ranges'!$K$19,IF(B54>='Environmental Factor Ranges'!$J$20,'Environmental Factor Ranges'!$K$20,IF(B54>='Environmental Factor Ranges'!$J$21,'Environmental Factor Ranges'!$K$21,IF(B54>='Environmental Factor Ranges'!$J$22,'Environmental Factor Ranges'!$K$22,IF(B54>='Environmental Factor Ranges'!$J$23,'Environmental Factor Ranges'!$K$23,IF(B54>='Environmental Factor Ranges'!$J$24,'Environmental Factor Ranges'!$K$24,'Environmental Factor Ranges'!$K$25)))))))))))))))) | E54: =$F$9 | F54: =IF(E54>='Environmental Factor Ranges'!$L$9,'Environmental Factor Ranges'!$F$9,IF(E54>='Environmental Factor Ranges'!$L$10,'Environmental Factor Ranges'!$F$10,IF(E54>='Environmental Factor Ranges'!$L$11,'Environmental Factor Ranges'!$F$11,IF(E54>='Environmental Factor Ranges'!$L$12,'Environmental Factor Ranges'!$F$12,IF(E54>='Environmental Factor Ranges'!$L$13,'Environmental Factor Ranges'!$F$13,IF(E54>='Environmental Factor Ranges'!$L$14,'Environmental Factor Ranges'!$F$14,IF(E54>='Environmental Factor Ranges'!$L$15,'Environmental Factor Ranges'!$F$15,IF(E54>='Environmental Factor Ranges'!$L$16,'Environmental Factor Ranges'!$F$16,IF(E54>='Environmental Factor Ranges'!$L$17,'Environmental Factor Ranges'!$F$17,IF(E54>='Environmental Factor Ranges'!$L$18,'Environmental Factor Ranges'!$F$18,IF(E54>='Environmental Factor Ranges'!$L$19,'Environmental Factor Ranges'!$F$19,IF(E54>='Environmental Factor Ranges'!$L$20,'Environmental Factor Ranges'!$F$20,'Environmental Factor Ranges'!$F$21))))))))))))
B55: ="Environmental Factor-"&B51
B56: =C54+F54
H57: Environmental Factor | I57: =B56
B59: ='Scale Calculation'!C15
B60: =$B$12 | E60: Economic Stress
B61: =B13 | C61: Score | E61: Actual | F61: Score
B62: ='Calc tab'!AI98 | C62: =IF(B62>='Environmental Factor Ranges'!$J$9,'Environmental Factor Ranges'!$K$9,IF(B62>='Environmental Factor Ranges'!$J$10,'Environmental Factor Ranges'!$K$10,IF(B62>='Environmental Factor Ranges'!$J$11,'Environmental Factor Ranges'!$K$11,IF(B62>='Environmental Factor Ranges'!$J$12,'Environmental Factor Ranges'!$K$12,IF(B62>='Environmental Factor Ranges'!$J$13,'Environmental Factor Ranges'!$K$13,IF(B62>='Environmental Factor Ranges'!$J$14,'Environmental Factor Ranges'!$K$14,IF(B62>='Environmental Factor Ranges'!$J$15,'Environmental Factor Ranges'!$K$15,IF(B62>='Environmental Factor Ranges'!$J$16,'Environmental Factor Ranges'!$K$16,IF(B62>='Environmental Factor Ranges'!$J$17,'Environmental Factor Ranges'!$K$17,IF(B62>='Environmental Factor Ranges'!$J$18,'Environmental Factor Ranges'!$K$18,IF(B62>='Environmental Factor Ranges'!$J$19,'Environmental Factor Ranges'!$K$19,IF(B62>='Environmental Factor Ranges'!$J$20,'Environmental Factor Ranges'!$K$20,IF(B62>='Environmental Factor Ranges'!$J$21,'Environmental Factor Ranges'!$K$21,IF(B62>='Environmental Factor Ranges'!$J$22,'Environmental Factor Ranges'!$K$22,IF(B62>='Environmental Factor Ranges'!$J$23,'Environmental Factor Ranges'!$K$23,IF(B62>='Environmental Factor Ranges'!$J$24,'Environmental Factor Ranges'!$K$24,'Environmental Factor Ranges'!$K$25)))))))))))))))) | E62: =$F$9 | F62: =IF(E62>='Environmental Factor Ranges'!$L$9,'Environmental Factor Ranges'!$F$9,IF(E62>='Environmental Factor Ranges'!$L$10,'Environmental Factor Ranges'!$F$10,IF(E62>='Environmental Factor Ranges'!$L$11,'Environmental Factor Ranges'!$F$11,IF(E62>='Environmental Factor Ranges'!$L$12,'Environmental Factor Ranges'!$F$12,IF(E62>='Environmental Factor Ranges'!$L$13,'Environmental Factor Ranges'!$F$13,IF(E62>='Environmental Factor Ranges'!$L$14,'Environmental Factor Ranges'!$F$14,IF(E62>='Environmental Factor Ranges'!$L$15,'Environmental Factor Ranges'!$F$15,IF(E62>='Environmental Factor Ranges'!$L$16,'Environmental Factor Ranges'!$F$16,IF(E62>='Environmental Factor Ranges'!$L$17,'Environmental Factor Ranges'!$F$17,IF(E62>='Environmental Factor Ranges'!$L$18,'Environmental Factor Ranges'!$F$18,IF(E62>='Environmental Factor Ranges'!$L$19,'Environmental Factor Ranges'!$F$19,IF(E62>='Environmental Factor Ranges'!$L$20,'Environmental Factor Ranges'!$F$20,'Environmental Factor Ranges'!$F$21))))))))))))
B63: ="Environmental Factor-"&B59
B64: =C62+F62
H65: Environmental Factor | I65: =B64
B67: ='Scale Calculation'!C16
B68: =$B$12 | E68: Economic Stress
B69: =B53 | C69: Score | E69: Actual | F69: Score
B70: ='Calc tab'!AI99 | C70: =IF(B70>='Environmental Factor Ranges'!$J$9,'Environmental Factor Ranges'!$K$9,IF(B70>='Environmental Factor Ranges'!$J$10,'Environmental Factor Ranges'!$K$10,IF(B70>='Environmental Factor Ranges'!$J$11,'Environmental Factor Ranges'!$K$11,IF(B70>='Environmental Factor Ranges'!$J$12,'Environmental Factor Ranges'!$K$12,IF(B70>='Environmental Factor Ranges'!$J$13,'Environmental Factor Ranges'!$K$13,IF(B70>='Environmental Factor Ranges'!$J$14,'Environmental Factor Ranges'!$K$14,IF(B70>='Environmental Factor Ranges'!$J$15,'Environmental Factor Ranges'!$K$15,IF(B70>='Environmental Factor Ranges'!$J$16,'Environmental Factor Ranges'!$K$16,IF(B70>='Environmental Factor Ranges'!$J$17,'Environmental Factor Ranges'!$K$17,IF(B70>='Environmental Factor Ranges'!$J$18,'Environmental Factor Ranges'!$K$18,IF(B70>='Environmental Factor Ranges'!$J$19,'Environmental Factor Ranges'!$K$19,IF(B70>='Environmental Factor Ranges'!$J$20,'Environmental Factor Ranges'!$K$20,IF(B70>='Environmental Factor Ranges'!$J$21,'Environmental Factor Ranges'!$K$21,IF(B70>='Environmental Factor Ranges'!$J$22,'Environmental Factor Ranges'!$K$22,IF(B70>='Environmental Factor Ranges'!$J$23,'Environmental Factor Ranges'!$K$23,IF(B70>='Environmental Factor Ranges'!$J$24,'Environmental Factor Ranges'!$K$24,'Environmental Factor Ranges'!$K$25)))))))))))))))) | E70: =$F$9 | F70: =IF(E70>='Environmental Factor Ranges'!$L$9,'Environmental Factor Ranges'!$F$9,IF(E70>='Environmental Factor Ranges'!$L$10,'Environmental Factor Ranges'!$F$10,IF(E70>='Environmental Factor Ranges'!$L$11,'Environmental Factor Ranges'!$F$11,IF(E70>='Environmental Factor Ranges'!$L$12,'Environmental Factor Ranges'!$F$12,IF(E70>='Environmental Factor Ranges'!$L$13,'Environmental Factor Ranges'!$F$13,IF(E70>='Environmental Factor Ranges'!$L$14,'Environmental Factor Ranges'!$F$14,IF(E70>='Environmental Factor Ranges'!$L$15,'Environmental Factor Ranges'!$F$15,IF(E70>='Environmental Factor Ranges'!$L$16,'Environmental Factor Ranges'!$F$16,IF(E70>='Environmental Factor Ranges'!$L$17,'Environmental Factor Ranges'!$F$17,IF(E70>='Environmental Factor Ranges'!$L$18,'Environmental Factor Ranges'!$F$18,IF(E70>='Environmental Factor Ranges'!$L$19,'Environmental Factor Ranges'!$F$19,IF(E70>='Environmental Factor Ranges'!$L$20,'Environmental Factor Ranges'!$F$20,'Environmental Factor Ranges'!$F$21))))))))))))
B71: ="Environmental Factor-"&B67
B72: =C70+F70
H73: Environmental Factor | I73: =B72
B75: ='Scale Calculation'!C17
B76: =$B$12 | E76: Economic Stress
B77: =B13 | C77: Score | E77: Actual | F77: Score
B78: ='Calc tab'!AI100 | C78: =IF(B78>='Environmental Factor Ranges'!$J$9,'Environmental Factor Ranges'!$K$9,IF(B78>='Environmental Factor Ranges'!$J$10,'Environmental Factor Ranges'!$K$10,IF(B78>='Environmental Factor Ranges'!$J$11,'Environmental Factor Ranges'!$K$11,IF(B78>='Environmental Factor Ranges'!$J$12,'Environmental Factor Ranges'!$K$12,IF(B78>='Environmental Factor Ranges'!$J$13,'Environmental Factor Ranges'!$K$13,IF(B78>='Environmental Factor Ranges'!$J$14,'Environmental Factor Ranges'!$K$14,IF(B78>='Environmental Factor Ranges'!$J$15,'Environmental Factor Ranges'!$K$15,IF(B78>='Environmental Factor Ranges'!$J$16,'Environmental Factor Ranges'!$K$16,IF(B78>='Environmental Factor Ranges'!$J$17,'Environmental Factor Ranges'!$K$17,IF(B78>='Environmental Factor Ranges'!$J$18,'Environmental Factor Ranges'!$K$18,IF(B78>='Environmental Factor Ranges'!$J$19,'Environmental Factor Ranges'!$K$19,IF(B78>='Environmental Factor Ranges'!$J$20,'Environmental Factor Ranges'!$K$20,IF(B78>='Environmental Factor Ranges'!$J$21,'Environmental Factor Ranges'!$K$21,IF(B78>='Environmental Factor Ranges'!$J$22,'Environmental Factor Ranges'!$K$22,IF(B78>='Environmental Factor Ranges'!$J$23,'Environmental Factor Ranges'!$K$23,IF(B78>='Environmental Factor Ranges'!$J$24,'Environmental Factor Ranges'!$K$24,'Environmental Factor Ranges'!$K$25)))))))))))))))) | E78: =$F$9 | F78: =IF(E78>='Environmental Factor Ranges'!$L$9,'Environmental Factor Ranges'!$F$9,IF(E78>='Environmental Factor Ranges'!$L$10,'Environmental Factor Ranges'!$F$10,IF(E78>='Environmental Factor Ranges'!$L$11,'Environmental Factor Ranges'!$F$11,IF(E78>='Environmental Factor Ranges'!$L$12,'Environmental Factor Ranges'!$F$12,IF(E78>='Environmental Factor Ranges'!$L$13,'Environmental Factor Ranges'!$F$13,IF(E78>='Environmental Factor Ranges'!$L$14,'Environmental Factor Ranges'!$F$14,IF(E78>='Environmental Factor Ranges'!$L$15,'Environmental Factor Ranges'!$F$15,IF(E78>='Environmental Factor Ranges'!$L$16,'Environmental Factor Ranges'!$F$16,IF(E78>='Environmental Factor Ranges'!$L$17,'Environmental Factor Ranges'!$F$17,IF(E78>='Environmental Factor Ranges'!$L$18,'Environmental Factor Ranges'!$F$18,IF(E78>='Environmental Factor Ranges'!$L$19,'Environmental Factor Ranges'!$F$19,IF(E78>='Environmental Factor Ranges'!$L$20,'Environmental Factor Ranges'!$F$20,'Environmental Factor Ranges'!$F$21))))))))))))
B79: ="Environmental Factor-"&B75
B80: =C78+F78
H81: Environmental Factor | I81: =B80
B83: ='Scale Calculation'!C18
B84: =$B$12 | E84: Economic Stress
B85: =B13 | C85: Score | E85: Actual | F85: Score
B86: ='Calc tab'!AI101 | C86: =IF(B86>='Environmental Factor Ranges'!$J$9,'Environmental Factor Ranges'!$K$9,IF(B86>='Environmental Factor Ranges'!$J$10,'Environmental Factor Ranges'!$K$10,IF(B86>='Environmental Factor Ranges'!$J$11,'Environmental Factor Ranges'!$K$11,IF(B86>='Environmental Factor Ranges'!$J$12,'Environmental Factor Ranges'!$K$12,IF(B86>='Environmental Factor Ranges'!$J$13,'Environmental Factor Ranges'!$K$13,IF(B86>='Environmental Factor Ranges'!$J$14,'Environmental Factor Ranges'!$K$14,IF(B86>='Environmental Factor Ranges'!$J$15,'Environmental Factor Ranges'!$K$15,IF(B86>='Environmental Factor Ranges'!$J$16,'Environmental Factor Ranges'!$K$16,IF(B86>='Environmental Factor Ranges'!$J$17,'Environmental Factor Ranges'!$K$17,IF(B86>='Environmental Factor Ranges'!$J$18,'Environmental Factor Ranges'!$K$18,IF(B86>='Environmental Factor Ranges'!$J$19,'Environmental Factor Ranges'!$K$19,IF(B86>='Environmental Factor Ranges'!$J$20,'Environmental Factor Ranges'!$K$20,IF(B86>='Environmental Factor Ranges'!$J$21,'Environmental Factor Ranges'!$K$21,IF(B86>='Environmental Factor Ranges'!$J$22,'Environmental Factor Ranges'!$K$22,IF(B86>='Environmental Factor Ranges'!$J$23,'Environmental Factor Ranges'!$K$23,IF(B86>='Environmental Factor Ranges'!$J$24,'Environmental Factor Ranges'!$K$24,'Environmental Factor Ranges'!$K$25)))))))))))))))) | E86: =$F$9 | F86: =IF(E86>='Environmental Factor Ranges'!$L$9,'Environmental Factor Ranges'!$F$9,IF(E86>='Environmental Factor Ranges'!$L$10,'Environmental Factor Ranges'!$F$10,IF(E86>='Environmental Factor Ranges'!$L$11,'Environmental Factor Ranges'!$F$11,IF(E86>='Environmental Factor Ranges'!$L$12,'Environmental Factor Ranges'!$F$12,IF(E86>='Environmental Factor Ranges'!$L$13,'Environmental Factor Ranges'!$F$13,IF(E86>='Environmental Factor Ranges'!$L$14,'Environmental Factor Ranges'!$F$14,IF(E86>='Environmental Factor Ranges'!$L$15,'Environmental Factor Ranges'!$F$15,IF(E86>='Environmental Factor Ranges'!$L$16,'Environmental Factor Ranges'!$F$16,IF(E86>='Environmental Factor Ranges'!$L$17,'Environmental Factor Ranges'!$F$17,IF(E86>='Environmental Factor Ranges'!$L$18,'Environmental Factor Ranges'!$F$18,IF(E86>='Environmental Factor Ranges'!$L$19,'Environmental Factor Ranges'!$F$19,IF(E86>='Environmental Factor Ranges'!$L$20,'Environmental Factor Ranges'!$F$20,'Environmental Factor Ranges'!$F$21))))))))))))
B87: ="Environmental Factor-"&B83
B88: =C86+F86
H89: Environmental Factor | I89: =B88
B91: ='Scale Calculation'!C19
B92: =$B$12 | E92: Economic Stress
B93: =B13 | C93: Score | E93: Actual | F93: Score
B94: ='Calc tab'!AI102 | C94: =IF(B94>='Environmental Factor Ranges'!$J$9,'Environmental Factor Ranges'!$K$9,IF(B94>='Environmental Factor Ranges'!$J$10,'Environmental Factor Ranges'!$K$10,IF(B94>='Environmental Factor Ranges'!$J$11,'Environmental Factor Ranges'!$K$11,IF(B94>='Environmental Factor Ranges'!$J$12,'Environmental Factor Ranges'!$K$12,IF(B94>='Environmental Factor Ranges'!$J$13,'Environmental Factor Ranges'!$K$13,IF(B94>='Environmental Factor Ranges'!$J$14,'Environmental Factor Ranges'!$K$14,IF(B94>='Environmental Factor Ranges'!$J$15,'Environmental Factor Ranges'!$K$15,IF(B94>='Environmental Factor Ranges'!$J$16,'Environmental Factor Ranges'!$K$16,IF(B94>='Environmental Factor Ranges'!$J$17,'Environmental Factor Ranges'!$K$17,IF(B94>='Environmental Factor Ranges'!$J$18,'Environmental Factor Ranges'!$K$18,IF(B94>='Environmental Factor Ranges'!$J$19,'Environmental Factor Ranges'!$K$19,IF(B94>='Environmental Factor Ranges'!$J$20,'Environmental Factor Ranges'!$K$20,IF(B94>='Environmental Factor Ranges'!$J$21,'Environmental Factor Ranges'!$K$21,IF(B94>='Environmental Factor Ranges'!$J$22,'Environmental Factor Ranges'!$K$22,IF(B94>='Environmental Factor Ranges'!$J$23,'Environmental Factor Ranges'!$K$23,IF(B94>='Environmental Factor Ranges'!$J$24,'Environmental Factor Ranges'!$K$24,'Environmental Factor Ranges'!$K$25)))))))))))))))) | E94: =$F$9 | F94: =IF(E94>='Environmental Factor Ranges'!$L$9,'Environmental Factor Ranges'!$F$9,IF(E94>='Environmental Factor Ranges'!$L$10,'Environmental Factor Ranges'!$F$10,IF(E94>='Environmental Factor Ranges'!$L$11,'Environmental Factor Ranges'!$F$11,IF(E94>='Environmental Factor Ranges'!$L$12,'Environmental Factor Ranges'!$F$12,IF(E94>='Environmental Factor Ranges'!$L$13,'Environmental Factor Ranges'!$F$13,IF(E94>='Environmental Factor Ranges'!$L$14,'Environmental Factor Ranges'!$F$14,IF(E94>='Environmental Factor Ranges'!$L$15,'Environmental Factor Ranges'!$F$15,IF(E94>='Environmental Factor Ranges'!$L$16,'Environmental Factor Ranges'!$F$16,IF(E94>='Environmental Factor Ranges'!$L$17,'Environmental Factor Ranges'!$F$17,IF(E94>='Environmental Factor Ranges'!$L$18,'Environmental Factor Ranges'!$F$18,IF(E94>='Environmental Factor Ranges'!$L$19,'Environmental Factor Ranges'!$F$19,IF(E94>='Environmental Factor Ranges'!$L$20,'Environmental Factor Ranges'!$F$20,'Environmental Factor Ranges'!$F$21))))))))))))
B95: ="Environmental Factor-"&B91
B96: =C94+F94
H97: Environmental Factor | I97: =B96
B100: ='Scale Calculation'!#REF!
B101: Delinquency | E101: Economic Stress
B102: Actual | C102: Score | E102: Actual | F102: Score
C103: =IF(B103>='Environmental Factor Ranges'!#REF!,'Environmental Factor Ranges'!#REF!,IF(B103>='Environmental Factor Ranges'!#REF!,'Environmental Factor Ranges'!#REF!,IF(B103>='Environmental Factor Ranges'!#REF!,'Environmental Factor Ranges'!#REF!,IF(B103>='Environmental Factor Ranges'!#REF!,'Environmental Factor Ranges'!#REF!,IF(B103>='Environmental Factor Ranges'!#REF!,'Environmental Factor Ranges'!#REF!,IF(B103>='Environmental Factor Ranges'!#REF!,'Environmental Factor Ranges'!#REF!,IF(B103>='Environmental Factor Ranges'!#REF!,'Environmental Factor Ranges'!#REF!,IF(B103>='Environmental Factor Ranges'!#REF!,'Environmental Factor Ranges'!#REF!,IF(B103>='Environmental Factor Ranges'!#REF!,'Environmental Factor Ranges'!#REF!,IF(B103>='Environmental Factor Ranges'!#REF!,'Environmental Factor Ranges'!#REF!,IF(B103>='Environmental Factor Ranges'!#REF!,'Environmental Factor Ranges'!#REF!,IF(B103>='Environmental Factor Ranges'!#REF!,'Environmental Factor Ranges'!#REF!,'Environmental Factor Ranges'!#REF!)))))))))))) | E103: =$F$9 | F103: =IF(E103>='Environmental Factor Ranges'!$L$9,'Environmental Factor Ranges'!$F$9,IF(E103>='Environmental Factor Ranges'!$L$10,'Environmental Factor Ranges'!$F$10,IF(E103>='Environmental Factor Ranges'!$L$11,'Environmental Factor Ranges'!$F$11,IF(E103>='Environmental Factor Ranges'!$L$12,'Environmental Factor Ranges'!$F$12,IF(E103>='Environmental Factor Ranges'!$L$13,'Environmental Factor Ranges'!$F$13,IF(E103>='Environmental Factor Ranges'!$L$14,'Environmental Factor Ranges'!$F$14,IF(E103>='Environmental Factor Ranges'!$L$15,'Environmental Factor Ranges'!$F$15,IF(E103>='Environmental Factor Ranges'!$L$16,'Environmental Factor Ranges'!$F$16,IF(E103>='Environmental Factor Ranges'!$L$17,'Environmental Factor Ranges'!$F$17,IF(E103>='Environmental Factor Ranges'!$L$18,'Environmental Factor Ranges'!$F$18,IF(E103>='Environmental Factor Ranges'!$L$19,'Environmental Factor Ranges'!$F$19,IF(E103>='Environmental Factor Ranges'!$L$20,'Environmental Factor Ranges'!$F$20,'Environmental Factor Ranges'!$F$21))))))))))))
B104: ="Environmental Factor-"&B100
B105: =C103+F103
H106: Environmental Factor | I106: =B105
B108: ='Scale Calculation'!#REF!
B109: Delinquency | E109: Economic Stress
B110: Actual | C110: Score | E110: Actual | F110: Score
C111: =IF(B111>='Environmental Factor Ranges'!#REF!,'Environmental Factor Ranges'!#REF!,IF(B111>='Environmental Factor Ranges'!#REF!,'Environmental Factor Ranges'!#REF!,IF(B111>='Environmental Factor Ranges'!#REF!,'Environmental Factor Ranges'!#REF!,IF(B111>='Environmental Factor Ranges'!#REF!,'Environmental Factor Ranges'!#REF!,IF(B111>='Environmental Factor Ranges'!#REF!,'Environmental Factor Ranges'!#REF!,IF(B111>='Environmental Factor Ranges'!#REF!,'Environmental Factor Ranges'!#REF!,IF(B111>='Environmental Factor Ranges'!#REF!,'Environmental Factor Ranges'!#REF!,IF(B111>='Environmental Factor Ranges'!#REF!,'Environmental Factor Ranges'!#REF!,IF(B111>='Environmental Factor Ranges'!#REF!,'Environmental Factor Ranges'!#REF!,IF(B111>='Environmental Factor Ranges'!#REF!,'Environmental Factor Ranges'!#REF!,IF(B111>='Environmental Factor Ranges'!#REF!,'Environmental Factor Ranges'!#REF!,IF(B111>='Environmental Factor Ranges'!#REF!,'Environmental Factor Ranges'!#REF!,'Environmental Factor Ranges'!#REF!)))))))))))) | E111: =$F$9 | F111: =IF(E111>='Environmental Factor Ranges'!$L$9,'Environmental Factor Ranges'!$F$9,IF(E111>='Environmental Factor Ranges'!$L$10,'Environmental Factor Ranges'!$F$10,IF(E111>='Environmental Factor Ranges'!$L$11,'Environmental Factor Ranges'!$F$11,IF(E111>='Environmental Factor Ranges'!$L$12,'Environmental Factor Ranges'!$F$12,IF(E111>='Environmental Factor Ranges'!$L$13,'Environmental Factor Ranges'!$F$13,IF(E111>='Environmental Factor Ranges'!$L$14,'Environmental Factor Ranges'!$F$14,IF(E111>='Environmental Factor Ranges'!$L$15,'Environmental Factor Ranges'!$F$15,IF(E111>='Environmental Factor Ranges'!$L$16,'Environmental Factor Ranges'!$F$16,IF(E111>='Environmental Factor Ranges'!$L$17,'Environmental Factor Ranges'!$F$17,IF(E111>='Environmental Factor Ranges'!$L$18,'Environmental Factor Ranges'!$F$18,IF(E111>='Environmental Factor Ranges'!$L$19,'Environmental Factor Ranges'!$F$19,IF(E111>='Environmental Factor Ranges'!$L$20,'Environmental Factor Ranges'!$F$20,'Environmental Factor Ranges'!$F$21))))))))))))
B112: ="Environmental Factor-"&B108
B113: =C111+F111
H114: Environmental Factor | I114: =B113
B116: ='Scale Calculation'!#REF!
...

Sheet Environmental Factor Ranges
B2: ='Historical Data'!B2
B3: Environmental Factor Ranges
B4: ="For Period Ending "&TEXT('Historical Data'!AY8,"mm/dd/yyyy")
O5: TCT Risk Solutions conducts regular reviews of data to support its CECL methodology and calculations. These analytics include multiple regression analysis, Cluster Analysis, t-tests, MANOVA and Variance analysis.
B6: Environmental Factor Scale Table | O6: Based on the most recent analysis, we have identified changes that are indicated in the Economic Stress score employed as an Environmental Factor in our CECL methodology. The changes are as follows:
B7: Delinquency | E7: Economic Stress Score | J7: Delinquency | L7: Economic stress
C8: Range | D8: Score | E8: Range | F8: Score | J8: Minimums | K8: Score | L8: Minimums | M8: Score | P8: Range | R8: Score
C9: =IF(J9=0,"Not Risk Rated",">"&TEXT(J9,"#.00%")) | D9: =K9 | E9: =">"&TEXT(L9,"#.00%") | F9: =M9 | J9: 0.05 | K9: 0.2 | L9: 0.25 | M9: 0.1 | P9: >25% | R9: 0.1
C10: =TEXT(J10,"#.00%")&" to "&TEXT(J9-0.0001,"#.00%") | D10: =K10 | E10: =TEXT(L10,"#.00%")&" to "&TEXT(L9-0.0001,"#.00%") | F10: =M10 | J10: 0.04 | K10: 0.17 | L10: 0.24 | M10: 0.08 | O10: 0.24 | P10: 0.2499 | R10: 0.08
C11: =TEXT(J11,"#.00%")&" to "&TEXT(J10-0.0001,"#.00%") | D11: =K11 | E11: =TEXT(L11,"#.00%")&" to "&TEXT(L10-0.0001,"#.00%") | F11: =M11 | J11: 0.03 | K11: 0.12 | L11: 0.22 | M11: 0.07 | O11: 0.22 | P11: 0.2399 | R11: 0.07
C12: =TEXT(J12,"#.00%")&" to "&TEXT(J11-0.0001,"#.00%") | D12: =K12 | E12: =TEXT(L12,"#.00%")&" to "&TEXT(L11-0.0001,"#.00%") | F12: =M12 | J12: 0.025 | K12: 0.08 | L12: 0.2 | M12: 0.06 | O12: 0.2 | P12: 0.2199 | R12: 0.06
C13: =TEXT(J13,"#.00%")&" to "&TEXT(J12-0.0001,"#.00%") | D13: =K13 | E13: =TEXT(L13,"#.00%")&" to "&TEXT(L12-0.0001,"#.00%") | F13: =M13 | J13: 0.02 | K13: 0.04 | L13: 0.18 | M13: 0.05 | O13: 0.18 | P13: 0.1999 | R13: 0.05
C14: =TEXT(J14,"#.00%")&" to "&TEXT(J13-0.0001,"#.00%") | D14: =K14 | E14: =TEXT(L14,"#.00%")&" to "&TEXT(L13-0.0001,"#.00%") | F14: =M14 | J14: 0.015 | K14: 0.025 | L14: 0.16 | M14: 0.04 | O14: 0.16 | P14: 0.1799 | R14: 0.04
C15: =TEXT(J15,"#.00%")&" to "&TEXT(J14-0.0001,"#.00%") | D15: =K15 | E15: =TEXT(L15,"#.00%")&" to "&TEXT(L14-0.0001,"#.00%") | F15: =M15 | J15: 0.01 | K15: 0.015 | L15: 0.14 | M15: 0.035 | O15: 0.14 | P15: 0.1599 | R15: 0.035
C16: =TEXT(J16,"#.00%")&" to "&TEXT(J15-0.0001,"#.00%") | D16: =K16 | E16: =TEXT(L16,"#.00%")&" to "&TEXT(L15-0.0001,"#.00%") | F16: =M16 | J16: 0.005 | K16: 0.0075 | L16: 0.12 | M16: 0.03 | O16: 0.12 | P16: 0.1399 | R16: 0.03
C17: =TEXT(J17,"#.00%")&" to "&TEXT(J16-0.0001,"#.00%") | D17: =K17 | E17: =TEXT(L17,"#.00%")&" to "&TEXT(L16-0.0001,"#.00%") | F17: =M17 | J17: -0.0049 | K17: 0 | L17: 0.1 | M17: 0.02 | O17: 0.1 | P17: 0.1199 | R17: 0.02
C18: =TEXT(J18,"#.00%")&" to "&TEXT(J17-0.0001,"#.00%") | D18: =K18 | E18: =TEXT(L18,"#.00%")&" to "&TEXT(L17-0.0001,"#.00%") | F18: =M18 | J18: -0.0099 | K18: -0.0075 | L18: 0.08 | M18: 0.01 | O18: 0.08 | P18: 0.0999 | R18: 0.01
C19: =TEXT(J19,"#.00%")&" to "&TEXT(J18-0.0001,"#.00%") | D19: =K19 | E19: =TEXT(L19,"#.00%")&" to "&TEXT(L18-0.0001,"#.00%") | F19: =M19 | J19: -0.0149 | K19: -0.015 | L19: 0.06 | M19: 0 | O19: 0.06 | P19: 0.0799 | R19: 0
C20: =TEXT(J20,"#.00%")&" to "&TEXT(J19-0.0001,"#.00%") | D20: =K20 | E20: =TEXT(L20,"#.00%")&" to "&TEXT(L19-0.0001,"#.00%") | F20: =M20 | J20: -0.0199 | K20: -0.025 | L20: 0.04 | M20: 0 | O20: 0.04 | P20: 0.0599 | R20: 0
C21: =TEXT(J21,"#.00%")&" to "&TEXT(J20-0.0001,"#.00%") | D21: =K21 | E21: =TEXT(L21,"#.00%")&" to "&TEXT(L20-0.0001,"#.00%") | F21: =M21 | J21: -0.0249 | K21: -0.04 | L21: 0.02 | M21: -0.01 | O21: 0.02 | P21: 0.0399 | R21: -0.01
C22: =TEXT(J22,"#.00%")&" to "&TEXT(J21-0.0001,"#.00%") | D22: =K22 | E22: =TEXT(L22,"#.00%")&" to "&TEXT(L21-0.0001,"#.00%") | F22: =M22 | J22: -0.0299 | K22: -0.08 | L22: 0 | M22: -0.02 | O22: 0 | P22: 0.0199 | R22: -0.02
C23: =TEXT(J23,"#.00%")&" to "&TEXT(J22-0.0001,"#.00%") | D23: =K23 | J23: -0.0399 | K23: -0.12
C24: =TEXT(J24,"#.00%")&" to "&TEXT(J23-0.0001,"#.00%") | D24: =K24 | J24: -0.0499 | K24: -0.17 | O24: These changes will take affect as of September 30, 2025.
C25: =IF(J25=0,"Not Risk Rated","<"&TEXT(J25,"#.00%")) | D25: =K25 | J25: -0.05 | K25: -0.2
C29: Discussion of Environmental Factor
C31: The Environmental Factor combines two distinct data sets to calculate the likely variance between the historical loss rate and the anticipated loss rate. As these two data sets improve the likelihood of loss decreases and as they deteriorate the likelihood of loss increases, hence the need to adjust the pool provision. Statistical tests including regression, MANOVA and Pearson 'R (correlation) were employed to validate each Factor and to establish the ranges.
C33: GAAP states that “when estimating credit losses on each group of loans with similar risk characteristics, an institution should consider its historical loss experience on the group, adjusted for changes in trends, conditions, and other relevant factors that affect repayment of the loans as of the evaluation date.”
C35: As part of the SCALE methodology, the Environmental Factor, or Q&E, is used to adjust the pooled loan allowance to assure it is representative of current risk. Two measures, identified in the Comptrollers Handbook, (e.g., delinquency and economic stress factor) are correlated to the charge-off history of the credit union, to determine if an adjustment to the pool risk factors are indicated. The two measures are applied to minimize the potential for skewing that could result from a single measure. Using accepted statistical techniques, (e.g., regression, ANOVA and correlation) the extent of the relationship is measured, and the adjustment is applied to the Pooled allowance amount for each grade to arrive at the adjusted allowance amount.
C37: Delinquency:
C39: A running history of the Reported Delinquency is pulled and maintained by TCT. Using this delinquency database, a trend is created to indicate the directionality of credit union past due loans over the indicated Life of Loan period for each pool. This trend of the Life of Loans DQ rates are compared to the current period DQ rate to determine if the rate is improving or deteriorating. An improving rate indicates lower risk of loss while a deteriorating rate indicated a higher risk of loss.
C41: Economic Stress Score:
C43: Measures the relative impact of the local economy on the historical loss rate. Calculated using Unemployment Rate, Bankruptcy Percentage, Foreclosure Rates and Population statistics for the State in which the Credit Union is based. The sources of these figures are: The Bureau of Labor Statistics, Realty Trac, and Electronic Access to Federal Court Records.
B49: =Cover!B35 | G49: Confidential

Sheet  Impaired Loans ASC 310-10
A1: ='Historical Data'!B2
A2: Impaired Loans Loans Report
A3: Report for Period Ending | B3: ='Historical Data'!AY8
A4: Impairment Type | B4: Provision Percentage | L4: =A4 | N4: ="Sum of "&N27 | P4: ="Sum of "&P27 | Q4: ="Sum of "&Q27
A5: Delinquent Loans | B5: 0.25 | L5: =IF(A5=0,"",A5) | N5: =IF(A5=0,"",SUMIF($A$28:$A$412,L5,$N$28:$N$412)) | P5: =IF(A5=0,"",SUMIF($A$28:$A$412,L5,$P$28:$P$412)) | Q5: =IF(A5=0,"",SUMIF($A$28:$A$412,L5,$Q$28:$Q$412))
A6: Known Losses | B6: 1 | L6: =IF(A6=0,"",A6) | N6: =IF(A6=0,"",SUMIF($A$28:$A$412,L6,$N$28:$N$412)) | P6: =IF(A6=0,"",SUMIF($A$28:$A$412,L6,$P$28:$P$412)) | Q6: =IF(A6=0,"",SUMIF($A$28:$A$412,L6,$Q$28:$Q$412))
A7: Repossessions | B7: 1 | L7: =IF(A7=0,"",A7) | N7: =IF(A7=0,"",SUMIF($A$28:$A$412,L7,$N$28:$N$412)) | P7: =IF(A7=0,"",SUMIF($A$28:$A$412,L7,$P$28:$P$412)) | Q7: =IF(A7=0,"",SUMIF($A$28:$A$412,L7,$Q$28:$Q$412))
A8: Foreclosed Real Estate | B8: 1 | L8: =IF(A8=0,"",A8) | N8: =IF(A8=0,"",SUMIF($A$28:$A$412,L8,$N$28:$N$412)) | P8: =IF(A8=0,"",SUMIF($A$28:$A$412,L8,$P$28:$P$412)) | Q8: =IF(A8=0,"",SUMIF($A$28:$A$412,L8,$Q$28:$Q$412))
A9: Other Individually Identified Loans | B9: 1 | L9: =IF(A9=0,"",A9) | N9: =IF(A9=0,"",SUMIF($A$28:$A$412,L9,$N$28:$N$412)) | P9: =IF(A9=0,"",SUMIF($A$28:$A$412,L9,$P$28:$P$412)) | Q9: =IF(A9=0,"",SUMIF($A$28:$A$412,L9,$Q$28:$Q$412))
L10: =IF(A10=0,"",A10) | N10: =IF(A10=0,"",SUMIF($A$28:$A$412,L10,$N$28:$N$412)) | P10: =IF(A10=0,"",SUMIF($A$28:$A$412,L10,$P$28:$P$412)) | Q10: =IF(A10=0,"",SUMIF($A$28:$A$412,L10,$Q$28:$Q$412))
L11: =IF(A11=0,"",A11) | N11: =IF(A11=0,"",SUMIF($A$28:$A$412,L11,$N$28:$N$412)) | P11: =IF(A11=0,"",SUMIF($A$28:$A$412,L11,$P$28:$P$412)) | Q11: =IF(A11=0,"",SUMIF($A$28:$A$412,L11,$Q$28:$Q$412))
L12: =IF(A12=0,"",A12) | N12: =IF(A12=0,"",SUMIF($A$28:$A$412,L12,$N$28:$N$412)) | P12: =IF(A12=0,"",SUMIF($A$28:$A$412,L12,$P$28:$P$412)) | Q12: =IF(A12=0,"",SUMIF($A$28:$A$412,L12,$Q$28:$Q$412))
L13: =IF(A13=0,"",A13) | N13: =IF(A13=0,"",SUMIF($A$28:$A$412,L13,$N$28:$N$412)) | P13: =IF(A13=0,"",SUMIF($A$28:$A$412,L13,$P$28:$P$412)) | Q13: =IF(A13=0,"",SUMIF($A$28:$A$412,L13,$Q$28:$Q$412))
L14: =IF(A14=0,"",A14) | N14: =IF(A14=0,"",SUMIF($A$28:$A$412,L14,$N$28:$N$412)) | P14: =IF(A14=0,"",SUMIF($A$28:$A$412,L14,$P$28:$P$412)) | Q14: =IF(A14=0,"",SUMIF($A$28:$A$412,L14,$Q$28:$Q$412))
L15: =IF(A15=0,"",A15) | N15: =IF(A15=0,"",SUMIF($A$28:$A$412,L15,$N$28:$N$412)) | P15: =IF(A15=0,"",SUMIF($A$28:$A$412,L15,$P$28:$P$412)) | Q15: =IF(A15=0,"",SUMIF($A$28:$A$412,L15,$Q$28:$Q$412))
L16: =IF(A16=0,"",A16) | N16: =IF(A16=0,"",SUMIF($A$28:$A$412,L16,$N$28:$N$412)) | P16: =IF(A16=0,"",SUMIF($A$28:$A$412,L16,$P$28:$P$412)) | Q16: =IF(A16=0,"",SUMIF($A$28:$A$412,L16,$Q$28:$Q$412))
L17: =IF(A17=0,"",A17) | N17: =IF(A17=0,"",SUMIF($A$28:$A$412,L17,$N$28:$N$412)) | P17: =IF(A17=0,"",SUMIF($A$28:$A$412,L17,$P$28:$P$412)) | Q17: =IF(A17=0,"",SUMIF($A$28:$A$412,L17,$Q$28:$Q$412))
L18: =IF(A18=0,"",A18) | N18: =IF(A18=0,"",SUMIF($A$28:$A$412,L18,$N$28:$N$412)) | P18: =IF(A18=0,"",SUMIF($A$28:$A$412,L18,$P$28:$P$412)) | Q18: =IF(A18=0,"",SUMIF($A$28:$A$412,L18,$Q$28:$Q$412))
L19: =IF(A19=0,"",A19) | N19: =IF(A19=0,"",SUMIF($A$28:$A$412,L19,$N$28:$N$412)) | P19: =IF(A19=0,"",SUMIF($A$28:$A$412,L19,$P$28:$P$412)) | Q19: =IF(A19=0,"",SUMIF($A$28:$A$412,L19,$Q$28:$Q$412))
L20: =IF(A20=0,"",A20) | N20: =IF(A20=0,"",SUMIF($A$28:$A$412,L20,$N$28:$N$412)) | P20: =IF(A20=0,"",SUMIF($A$28:$A$412,L20,$P$28:$P$412)) | Q20: =IF(A20=0,"",SUMIF($A$28:$A$412,L20,$Q$28:$Q$412))
L21: =IF(A21=0,"",A21) | N21: =IF(A21=0,"",SUMIF($A$28:$A$412,L21,$N$28:$N$412)) | P21: =IF(A21=0,"",SUMIF($A$28:$A$412,L21,$P$28:$P$412)) | Q21: =IF(A21=0,"",SUMIF($A$28:$A$412,L21,$Q$28:$Q$412))
... L23: =IF(A23=0,"",A23) | N23: =IF(A23=0,"",SUMIF($A$28:$A$412,L23,$N$28:$N$412)) | P23: =IF(A23=0,"",SUMIF($A$28:$A$412,L23,$P$28:$P$412)) | Q23: =IF(A23=0,"",SUMIF($A$28:$A$412,L23,$Q$28:$Q$412))
L24: Total | N24: =SUM(N5:N10) | P24: =SUM(P5:P10) | Q24: =SUM(Q5:Q10)
A26: Data Entry | B26: Data Entry | C26: Data Entry | D26: Data Entry | E26: Data Entry | F26: Data Entry | G26: Data Entry | H26: Data Entry | I26: Data Entry | K26: Calculation | L26: Calculation | M26: Calculation | N26: Calculation | O26: Calculation | P26: Calculation | Q26: Calculation
A27: Impairment Type | B27: Member # | C27: Loan Suffix | D27: Loan Pool | E27: Current Balance | F27: Days Delinquent | G27: Balance at Other Lender (2nd Mortgage and HELOC's) | H27: Collateral Value (for unsecured loans, leave blank) | I27: ="Allowance Provided by "&A1&" (blank cell = Amount at risk calc.)" | J27: Notes: | K27: Member #-Suffix | L27: Total Loans | M27: LTV | N27: Loss Given Default (LGD) | O27: Percent of Amount at Risk applied to Provision | P27: Provision Amount | Q27: Bal Removed from Pools
K28: =B28&"-"&C28 | L28: =E28+G28 | M28: =IF(H28=0,"No Value",L28/H28) | N28: =IF(I28<>"",I28,IF(L28-H28<=0,0,IF(L28-H28>=E28,E28,L28-H28))) | O28: =IF(I28<>"",100%,IF(A28=$A$5,$B$5,IF(A28=$A$6,$B$6,IF(A28=$A$7,$B$7,IF(A28=$A$8,$B$8,IF(A28=$A$9,$B$9,0)))))) | P28: =N28*O28 | Q28: =E28
K29: =B29&"-"&C29 | L29: =E29+G29 | M29: =IF(H29=0,"No Value",L29/H29) | N29: =IF(I29<>"",I29,IF(L29-H29<=0,0,IF(L29-H29>=E29,E29,L29-H29))) | O29: =IF(I29<>"",100%,IF(A29=$A$5,$B$5,IF(A29=$A$6,$B$6,IF(A29=$A$7,$B$7,IF(A29=$A$8,$B$8,IF(A29=$A$9,$B$9,0)))))) | P29: =N29*O29 | Q29: =E29
K30: =B30&"-"&C30 | L30: =E30+G30 | M30: =IF(H30=0,"No Value",L30/H30) | N30: =IF(I30<>"",I30,IF(L30-H30<=0,0,IF(L30-H30>=E30,E30,L30-H30))) | O30: =IF(I30<>"",100%,IF(A30=$A$5,$B$5,IF(A30=$A$6,$B$6,IF(A30=$A$7,$B$7,IF(A30=$A$8,$B$8,IF(A30=$A$9,$B$9,0)))))) | P30: =N30*O30 | Q30: =E30
K31: =B31&"-"&C31 | L31: =E31+G31 | M31: =IF(H31=0,"No Value",L31/H31) | N31: =IF(I31<>"",I31,IF(L31-H31<=0,0,IF(L31-H31>=E31,E31,L31-H31))) | O31: =IF(I31<>"",100%,IF(A31=$A$5,$B$5,IF(A31=$A$6,$B$6,IF(A31=$A$7,$B$7,IF(A31=$A$8,$B$8,IF(A31=$A$9,$B$9,0)))))) | P31: =N31*O31 | Q31: =E31
K32: =B32&"-"&C32 | L32: =E32+G32 | M32: =IF(H32=0,"No Value",L32/H32) | N32: =IF(I32<>"",I32,IF(L32-H32<=0,0,IF(L32-H32>=E32,E32,L32-H32))) | O32: =IF(I32<>"",100%,IF(A32=$A$5,$B$5,IF(A32=$A$6,$B$6,IF(A32=$A$7,$B$7,IF(A32=$A$8,$B$8,IF(A32=$A$9,$B$9,0)))))) | P32: =N32*O32 | Q32: =E32
K33: =B33&"-"&C33 | L33: =E33+G33 | M33: =IF(H33=0,"No Value",L33/H33) | N33: =IF(I33<>"",I33,IF(L33-H33<=0,0,IF(L33-H33>=E33,E33,L33-H33))) | O33: =IF(I33<>"",100%,IF(A33=$A$5,$B$5,IF(A33=$A$6,$B$6,IF(A33=$A$7,$B$7,IF(A33=$A$8,$B$8,IF(A33=$A$9,$B$9,0)))))) | P33: =N33*O33 | Q33: =E33
K34: =B34&"-"&C34 | L34: =E34+G34 | M34: =IF(H34=0,"No Value",L34/H34) | N34: =IF(I34<>"",I34,IF(L34-H34<=0,0,IF(L34-H34>=E34,E34,L34-H34))) | O34: =IF(I34<>"",100%,IF(A34=$A$5,$B$5,IF(A34=$A$6,$B$6,IF(A34=$A$7,$B$7,IF(A34=$A$8,$B$8,IF(A34=$A$9,$B$9,0)))))) | P34: =N34*O34 | Q34: =E34
K35: =B35&"-"&C35 | L35: =E35+G35 | M35: =IF(H35=0,"No Value",L35/H35) | N35: =IF(I35<>"",I35,IF(L35-H35<=0,0,IF(L35-H35>=E35,E35,L35-H35))) | O35: =IF(I35<>"",100%,IF(A35=$A$5,$B$5,IF(A35=$A$6,$B$6,IF(A35=$A$7,$B$7,IF(A35=$A$8,$B$8,IF(A35=$A$9,$B$9,0)))))) | P35: =N35*O35 | Q35: =E35
K36: =B36&"-"&C36 | L36: =E36+G36 | M36: =IF(H36=0,"No Value",L36/H36) | N36: =IF(I36<>"",I36,IF(L36-H36<=0,0,IF(L36-H36>=E36,E36,L36-H36))) | O36: =IF(I36<>"",100%,IF(A36=$A$5,$B$5,IF(A36=$A$6,$B$6,IF(A36=$A$7,$B$7,IF(A36=$A$8,$B$8,IF(A36=$A$9,$B$9,0)))))) | P36: =N36*O36 | Q36: =E36
K37: =B37&"-"&C37 | L37: =E37+G37 | M37: =IF(H37=0,"No Value",L37/H37) | N37: =IF(I37<>"",I37,IF(L37-H37<=0,0,IF(L37-H37>=E37,E37,L37-H37))) | O37: =IF(I37<>"",100%,IF(A37=$A$5,$B$5,IF(A37=$A$6,$B$6,IF(A37=$A$7,$B$7,IF(A37=$A$8,$B$8,IF(A37=$A$9,$B$9,0)))))) | P37: =N37*O37 | Q37: =E37
K38: =B38&"-"&C38 | L38: =E38+G38 | M38: =IF(H38=0,"No Value",L38/H38) | N38: =IF(I38<>"",I38,IF(L38-H38<=0,0,IF(L38-H38>=E38,E38,L38-H38))) | O38: =IF(I38<>"",100%,IF(A38=$A$5,$B$5,IF(A38=$A$6,$B$6,IF(A38=$A$7,$B$7,IF(A38=$A$8,$B$8,IF(A38=$A$9,$B$9,0)))))) | P38: =N38*O38 | Q38: =E38
K39: =B39&"-"&C39 | L39: =E39+G39 | M39: =IF(H39=0,"No Value",L39/H39) | N39: =IF(I39<>"",I39,IF(L39-H39<=0,0,IF(L39-H39>=E39,E39,L39-H39))) | O39: =IF(I39<>"",100%,IF(A39=$A$5,$B$5,IF(A39=$A$6,$B$6,IF(A39=$A$7,$B$7,IF(A39=$A$8,$B$8,IF(A39=$A$9,$B$9,0)))))) | P39: =N39*O39 | Q39: =E39
... K412: =B412&"-"&C412 | L412: =E412+G412 | M412: =IF(H412=0,"No Value",L412/H412) | N412: =IF(I412<>"",I412,IF(L412-H412<=0,0,IF(L412-H412>=E412,E412,L412-H412))) | O412: =IF(I412<>"",100%,IF(A412=$A$5,$B$5,IF(A412=$A$6,$B$6,IF(A412=$A$7,$B$7,IF(A412=$A$8,$B$8,IF(A412=$A$9,$B$9,0)))))) | P412: =N412*O412 | Q412: =E412

Sheet Calc tab
A1: Month Description | B1: Current -87 | C1: Current -84 | D1: Current -81 | E1: Current -78 | F1: Current -75 | G1: Current -72 | H1: Current -69 | I1: Current -66 | J1: Current -63 | K1: Current -60 | L1: Current -57 | M1: Current -54 | N1: Current -51 | O1: Current -48 | P1: Current -45 | Q1: Current -42 | R1: Current -39 | S1: Current -36 | T1: Current -33 | U1: Current -30 | V1: Current -27 | W1: Current -24 | X1: Current -21 | Y1: Current -18 | Z1: Current -15 | AA1: Current -12 | AB1: Current -9 | AC1: Current -6 | AD1: Current -3 | AE1: Current -0
A2: Month # | B2: =IF(C2=3,12,IF(C2=6,3,IF(C2=9,6,IF(C2=12,9)))) | C2: =IF(D2=3,12,IF(D2=6,3,IF(D2=9,6,IF(D2=12,9)))) | D2: =IF(E2=3,12,IF(E2=6,3,IF(E2=9,6,IF(E2=12,9)))) | E2: =IF(F2=3,12,IF(F2=6,3,IF(F2=9,6,IF(F2=12,9)))) | F2: =IF(G2=3,12,IF(G2=6,3,IF(G2=9,6,IF(G2=12,9)))) | G2: =IF(H2=3,12,IF(H2=6,3,IF(H2=9,6,IF(H2=12,9)))) | H2: =IF(I2=3,12,IF(I2=6,3,IF(I2=9,6,IF(I2=12,9)))) | I2: =IF(J2=3,12,IF(J2=6,3,IF(J2=9,6,IF(J2=12,9)))) | ... AD2: =IF(AE2=3,12,IF(AE2=6,3,IF(AE2=9,6,IF(AE2=12,9)))) | AE2: =MONTH(AE6)
A3: Year # | B3: =IF(B2=12,C3-1,C3) | C3: =IF(C2=12,D3-1,D3) | D3: =IF(D2=12,E3-1,E3) | E3: =IF(E2=12,F3-1,F3) | F3: =IF(F2=12,G3-1,G3) | G3: =IF(G2=12,H3-1,H3) | H3: =IF(H2=12,I3-1,I3) | I3: =IF(I2=12,J3-1,J3) | ... AD3: =IF(AD2=12,AE3-1,AE3) | AE3: =YEAR(AE6)
A4: Day# | B4: =IF(B2=6,30,IF(B2=9,30,31)) | C4: =IF(C2=6,30,IF(C2=9,30,31)) | D4: =IF(D2=6,30,IF(D2=9,30,31)) | E4: =IF(E2=6,30,IF(E2=9,30,31)) | F4: =IF(F2=6,30,IF(F2=9,30,31)) | G4: =IF(G2=6,30,IF(G2=9,30,31)) | H4: =IF(H2=6,30,IF(H2=9,30,31)) | I4: =IF(I2=6,30,IF(I2=9,30,31)) | ... AE4: =IF(AE2=6,30,IF(AE2=9,30,31))
A5: Quarter Number | B5: 30 | C5: 29 | D5: 28 | E5: 27 | F5: 26 | G5: 25 | H5: 24 | I5: 23 | J5: 22 | K5: 21 | L5: 20 | M5: 19 | N5: 18 | O5: 17 | P5: 16 | Q5: 15 | R5: 14 | S5: 13 | T5: 12 | U5: 11 | V5: 10 | W5: 9 | X5: 8 | Y5: 7 | Z5: 6 | AA5: 5 | AB5: 4 | AC5: 3 | AD5: 2 | AE5: 1
A6: Loan Balances | B6: =DATE(B3,B2,B4) | C6: =DATE(C3,C2,C4) | D6: =DATE(D3,D2,D4) | E6: =DATE(E3,E2,E4) | F6: =DATE(F3,F2,F4) | G6: =DATE(G3,G2,G4) | H6: =DATE(H3,H2,H4) | I6: =DATE(I3,I2,I4) | ... AD6: =DATE(AD3,AD2,AD4) | AE6: ='Historical Data'!AY8 | AF6: ACL Lifetime Months | AG6: ACL Lifetime Quarters | AH6: Average Balance ACL Lifetime
A7: ='Scale Calculation'!C9 | B7: =IF(B$5>$AG7,"",HLOOKUP(B$6,'Historical Data'!161:174,2,FALSE)) | C7: =IF(C$5>$AG7,"",HLOOKUP(C$6,'Historical Data'!161:174,2,FALSE)) | D7: =IF(D$5>$AG7,"",HLOOKUP(D$6,'Historical Data'!161:174,2,FALSE)) | E7: =IF(E$5>$AG7,"",HLOOKUP(E$6,'Historical Data'!161:174,2,FALSE)) | F7: =IF(F$5>$AG7,"",HLOOKUP(F$6,'Historical Data'!161:174,2,FALSE)) | G7: =IF(G$5>$AG7,"",HLOOKUP(G$6,'Historical Data'!161:174,2,FALSE)) | H7: =IF(H$5>$AG7,"",HLOOKUP(H$6,'Historical Data'!161:174,2,FALSE)) | I7: =IF(I$5>$AG7,"",HLOOKUP(I$6,'Historical Data'!161:174,2,FALSE)) | ... AE7: =IF(AE$5>$AG7,"",HLOOKUP(AE$6,'Historical Data'!161:174,2,FALSE)) | AF7: ='Industry Data'!B3 | AG7: =ROUNDUP(AF7/3,0) | AH7: =SUMIF($B$5:$AE$5,AG7,B24:AE24)/AG7
A8: ='Scale Calculation'!C10 | B8: =IF(B$5>$AG8,"",HLOOKUP(B$6,'Historical Data'!161:174,3,FALSE)) | C8: =IF(C$5>$AG8,"",HLOOKUP(C$6,'Historical Data'!161:174,3,FALSE)) | D8: =IF(D$5>$AG8,"",HLOOKUP(D$6,'Historical Data'!161:174,3,FALSE)) | E8: =IF(E$5>$AG8,"",HLOOKUP(E$6,'Historical Data'!161:174,3,FALSE)) | F8: =IF(F$5>$AG8,"",HLOOKUP(F$6,'Historical Data'!161:174,3,FALSE)) | G8: =IF(G$5>$AG8,"",HLOOKUP(G$6,'Historical Data'!161:174,3,FALSE)) | H8: =IF(H$5>$AG8,"",HLOOKUP(H$6,'Historical Data'!161:174,3,FALSE)) | I8: =IF(I$5>$AG8,"",HLOOKUP(I$6,'Historical Data'!161:174,3,FALSE)) | ... AE8: =IF(AE$5>$AG8,"",HLOOKUP(AE$6,'Historical Data'!161:174,3,FALSE)) | AF8: ='Industry Data'!B4 | AG8: =ROUNDUP(AF8/3,0) | AH8: =SUMIF($B$5:$AE$5,AG8,B25:AE25)/AG8
A9: ='Scale Calculation'!C11 | B9: =IF(B$5>$AG9,"",HLOOKUP(B$6,'Historical Data'!161:174,4,FALSE)) | C9: =IF(C$5>$AG9,"",HLOOKUP(C$6,'Historical Data'!161:174,4,FALSE)) | D9: =IF(D$5>$AG9,"",HLOOKUP(D$6,'Historical Data'!161:174,4,FALSE)) | E9: =IF(E$5>$AG9,"",HLOOKUP(E$6,'Historical Data'!161:174,4,FALSE)) | F9: =IF(F$5>$AG9,"",HLOOKUP(F$6,'Historical Data'!161:174,4,FALSE)) | G9: =IF(G$5>$AG9,"",HLOOKUP(G$6,'Historical Data'!161:174,4,FALSE)) | H9: =IF(H$5>$AG9,"",HLOOKUP(H$6,'Historical Data'!161:174,4,FALSE)) | I9: =IF(I$5>$AG9,"",HLOOKUP(I$6,'Historical Data'!161:174,4,FALSE)) | ... AE9: =IF(AE$5>$AG9,"",HLOOKUP(AE$6,'Historical Data'!161:174,4,FALSE)) | AF9: ='Industry Data'!B5 | AG9: =ROUNDUP(AF9/3,0) | AH9: =SUMIF($B$5:$AE$5,AG9,B26:AE26)/AG9
A10: ='Scale Calculation'!C12 | B10: =IF(B$5>$AG10,"",HLOOKUP(B$6,'Historical Data'!161:174,5,FALSE)) | C10: =IF(C$5>$AG10,"",HLOOKUP(C$6,'Historical Data'!161:174,5,FALSE)) | D10: =IF(D$5>$AG10,"",HLOOKUP(D$6,'Historical Data'!161:174,5,FALSE)) | E10: =IF(E$5>$AG10,"",HLOOKUP(E$6,'Historical Data'!161:174,5,FALSE)) | F10: =IF(F$5>$AG10,"",HLOOKUP(F$6,'Historical Data'!161:174,5,FALSE)) | G10: =IF(G$5>$AG10,"",HLOOKUP(G$6,'Historical Data'!161:174,5,FALSE)) | H10: =IF(H$5>$AG10,"",HLOOKUP(H$6,'Historical Data'!161:174,5,FALSE)) | I10: =IF(I$5>$AG10,"",HLOOKUP(I$6,'Historical Data'!161:174,5,FALSE)) | ... AE10: =IF(AE$5>$AG10,"",HLOOKUP(AE$6,'Historical Data'!161:174,5,FALSE)) | AF10: ='Industry Data'!B6 | AG10: =ROUNDUP(AF10/3,0) | AH10: =SUMIF($B$5:$AE$5,AG10,B27:AE27)/AG10
A11: ='Scale Calculation'!C13 | B11: =IF(B$5>$AG11,"",HLOOKUP(B$6,'Historical Data'!161:174,6,FALSE)) | C11: =IF(C$5>$AG11,"",HLOOKUP(C$6,'Historical Data'!161:174,6,FALSE)) | D11: =IF(D$5>$AG11,"",HLOOKUP(D$6,'Historical Data'!161:174,6,FALSE)) | E11: =IF(E$5>$AG11,"",HLOOKUP(E$6,'Historical Data'!161:174,6,FALSE)) | F11: =IF(F$5>$AG11,"",HLOOKUP(F$6,'Historical Data'!161:174,6,FALSE)) | G11: =IF(G$5>$AG11,"",HLOOKUP(G$6,'Historical Data'!161:174,6,FALSE)) | H11: =IF(H$5>$AG11,"",HLOOKUP(H$6,'Historical Data'!161:174,6,FALSE)) | I11: =IF(I$5>$AG11,"",HLOOKUP(I$6,'Historical Data'!161:174,6,FALSE)) | ... AE11: =IF(AE$5>$AG11,"",HLOOKUP(AE$6,'Historical Data'!161:174,6,FALSE)) | AF11: ='Industry Data'!B7 | AG11: =ROUNDUP(AF11/3,0) | AH11: =SUMIF($B$5:$AE$5,AG11,B28:AE28)/AG11
A12: ='Scale Calculation'!C14 | B12: =IF(B$5>$AG12,"",HLOOKUP(B$6,'Historical Data'!161:174,7,FALSE)) | C12: =IF(C$5>$AG12,"",HLOOKUP(C$6,'Historical Data'!161:174,7,FALSE)) | D12: =IF(D$5>$AG12,"",HLOOKUP(D$6,'Historical Data'!161:174,7,FALSE)) | E12: =IF(E$5>$AG12,"",HLOOKUP(E$6,'Historical Data'!161:174,7,FALSE)) | F12: =IF(F$5>$AG12,"",HLOOKUP(F$6,'Historical Data'!161:174,7,FALSE)) | G12: =IF(G$5>$AG12,"",HLOOKUP(G$6,'Historical Data'!161:174,7,FALSE)) | H12: =IF(H$5>$AG12,"",HLOOKUP(H$6,'Historical Data'!161:174,7,FALSE)) | I12: =IF(I$5>$AG12,"",HLOOKUP(I$6,'Historical Data'!161:174,7,FALSE)) | ... AE12: =IF(AE$5>$AG12,"",HLOOKUP(AE$6,'Historical Data'!161:174,7,FALSE)) | AF12: ='Industry Data'!B8 | AG12: =ROUNDUP(AF12/3,0) | AH12: =SUMIF($B$5:$AE$5,AG12,B29:AE29)/AG12
A13: ='Scale Calculation'!C15 | B13: =IF(B$5>$AG13,"",HLOOKUP(B$6,'Historical Data'!161:174,8,FALSE)) | C13: =IF(C$5>$AG13,"",HLOOKUP(C$6,'Historical Data'!161:174,8,FALSE)) | D13: =IF(D$5>$AG13,"",HLOOKUP(D$6,'Historical Data'!161:174,8,FALSE)) | E13: =IF(E$5>$AG13,"",HLOOKUP(E$6,'Historical Data'!161:174,8,FALSE)) | F13: =IF(F$5>$AG13,"",HLOOKUP(F$6,'Historical Data'!161:174,8,FALSE)) | G13: =IF(G$5>$AG13,"",HLOOKUP(G$6,'Historical Data'!161:174,8,FALSE)) | H13: =IF(H$5>$AG13,"",HLOOKUP(H$6,'Historical Data'!161:174,8,FALSE)) | I13: =IF(I$5>$AG13,"",HLOOKUP(I$6,'Historical Data'!161:174,8,FALSE)) | ... AE13: =IF(AE$5>$AG13,"",HLOOKUP(AE$6,'Historical Data'!161:174,8,FALSE)) | AF13: ='Industry Data'!B9 | AG13: =ROUNDUP(AF13/3,0) | AH13: =SUMIF($B$5:$AE$5,AG13,B30:AE30)/AG13
A14: ='Scale Calculation'!C16 | B14: =IF(B$5>$AG14,"",HLOOKUP(B$6,'Historical Data'!161:174,9,FALSE)) | C14: =IF(C$5>$AG14,"",HLOOKUP(C$6,'Historical Data'!161:174,9,FALSE)) | D14: =IF(D$5>$AG14,"",HLOOKUP(D$6,'Historical Data'!161:174,9,FALSE)) | E14: =IF(E$5>$AG14,"",HLOOKUP(E$6,'Historical Data'!161:174,9,FALSE)) | F14: =IF(F$5>$AG14,"",HLOOKUP(F$6,'Historical Data'!161:174,9,FALSE)) | G14: =IF(G$5>$AG14,"",HLOOKUP(G$6,'Historical Data'!161:174,9,FALSE)) | H14: =IF(H$5>$AG14,"",HLOOKUP(H$6,'Historical Data'!161:174,9,FALSE)) | I14: =IF(I$5>$AG14,"",HLOOKUP(I$6,'Historical Data'!161:174,9,FALSE)) | ... AE14: =IF(AE$5>$AG14,"",HLOOKUP(AE$6,'Historical Data'!161:174,9,FALSE)) | AF14: ='Industry Data'!B10 | AG14: =ROUNDUP(AF14/3,0) | AH14: =SUMIF($B$5:$AE$5,AG14,B31:AE31)/AG14
A15: ='Scale Calculation'!C17 | B15: =IF(B$5>$AG15,"",HLOOKUP(B$6,'Historical Data'!161:174,10,FALSE)) | C15: =IF(C$5>$AG15,"",HLOOKUP(C$6,'Historical Data'!161:174,10,FALSE)) | D15: =IF(D$5>$AG15,"",HLOOKUP(D$6,'Historical Data'!161:174,10,FALSE)) | E15: =IF(E$5>$AG15,"",HLOOKUP(E$6,'Historical Data'!161:174,10,FALSE)) | F15: =IF(F$5>$AG15,"",HLOOKUP(F$6,'Historical Data'!161:174,10,FALSE)) | G15: =IF(G$5>$AG15,"",HLOOKUP(G$6,'Historical Data'!161:174,10,FALSE)) | H15: =IF(H$5>$AG15,"",HLOOKUP(H$6,'Historical Data'!161:174,10,FALSE)) | I15: =IF(I$5>$AG15,"",HLOOKUP(I$6,'Historical Data'!161:174,10,FALSE)) | ... AE15: =IF(AE$5>$AG15,"",HLOOKUP(AE$6,'Historical Data'!161:174,10,FALSE)) | AF15: ='Industry Data'!B11 | AG15: =ROUNDUP(AF15/3,0) | AH15: =SUMIF($B$5:$AE$5,AG15,B32:AE32)/AG15
A16: ='Scale Calculation'!C18 | B16: =IF(B$5>$AG16,"",HLOOKUP(B$6,'Historical Data'!161:174,11,FALSE)) | C16: =IF(C$5>$AG16,"",HLOOKUP(C$6,'Historical Data'!161:174,11,FALSE)) | D16: =IF(D$5>$AG16,"",HLOOKUP(D$6,'Historical Data'!161:174,11,FALSE)) | E16: =IF(E$5>$AG16,"",HLOOKUP(E$6,'Historical Data'!161:174,11,FALSE)) | F16: =IF(F$5>$AG16,"",HLOOKUP(F$6,'Historical Data'!161:174,11,FALSE)) | G16: =IF(G$5>$AG16,"",HLOOKUP(G$6,'Historical Data'!161:174,11,FALSE)) | H16: =IF(H$5>$AG16,"",HLOOKUP(H$6,'Historical Data'!161:174,11,FALSE)) | I16: =IF(I$5>$AG16,"",HLOOKUP(I$6,'Historical Data'!161:174,11,FALSE)) | ... AE16: =IF(AE$5>$AG16,"",HLOOKUP(AE$6,'Historical Data'!161:174,11,FALSE)) | AF16: ='Industry Data'!B12 | AG16: =ROUNDUP(AF16/3,0) | AH16: =SUMIF($B$5:$AE$5,AG16,B33:AE33)/AG16
A17: ='Scale Calculation'!C19 | B17: =IF(B$5>$AG17,"",HLOOKUP(B$6,'Historical Data'!161:174,12,FALSE)) | C17: =IF(C$5>$AG17,"",HLOOKUP(C$6,'Historical Data'!161:174,12,FALSE)) | D17: =IF(D$5>$AG17,"",HLOOKUP(D$6,'Historical Data'!161:174,12,FALSE)) | E17: =IF(E$5>$AG17,"",HLOOKUP(E$6,'Historical Data'!161:174,12,FALSE)) | F17: =IF(F$5>$AG17,"",HLOOKUP(F$6,'Historical Data'!161:174,12,FALSE)) | G17: =IF(G$5>$AG17,"",HLOOKUP(G$6,'Historical Data'!161:174,12,FALSE)) | H17: =IF(H$5>$AG17,"",HLOOKUP(H$6,'Historical Data'!161:174,12,FALSE)) | I17: =IF(I$5>$AG17,"",HLOOKUP(I$6,'Historical Data'!161:174,12,FALSE)) | ... AE17: =IF(AE$5>$AG17,"",HLOOKUP(AE$6,'Historical Data'!161:174,12,FALSE)) | AF17: ='Industry Data'!B13 | AG17: =ROUNDUP(AF17/3,0) | AH17: =SUMIF($B$5:$AE$5,AG17,B34:AE34)/AG17
A18: ='Scale Calculation'!C20 | B18: =IF(B$5>$AG18,"",HLOOKUP(B$6,'Historical Data'!161:174,13,FALSE)) | C18: =IF(C$5>$AG18,"",HLOOKUP(C$6,'Historical Data'!161:174,13,FALSE)) | D18: =IF(D$5>$AG18,"",HLOOKUP(D$6,'Historical Data'!161:174,13,FALSE)) | E18: =IF(E$5>$AG18,"",HLOOKUP(E$6,'Historical Data'!161:174,13,FALSE)) | F18: =IF(F$5>$AG18,"",HLOOKUP(F$6,'Historical Data'!161:174,13,FALSE)) | G18: =IF(G$5>$AG18,"",HLOOKUP(G$6,'Historical Data'!161:174,13,FALSE)) | H18: =IF(H$5>$AG18,"",HLOOKUP(H$6,'Historical Data'!161:174,13,FALSE)) | I18: =IF(I$5>$AG18,"",HLOOKUP(I$6,'Historical Data'!161:174,13,FALSE)) | ... AE18: =IF(AE$5>$AG18,"",HLOOKUP(AE$6,'Historical Data'!161:174,13,FALSE)) | AF18: ='Industry Data'!B14 | AG18: =ROUNDUP(AF18/3,0) | AH18: =SUMIF($B$5:$AE$5,AG18,B35:AE35)/AG18
A19: ='Scale Calculation'!C21 | B19: =IF(B$5>$AG19,"",HLOOKUP(B$6,'Historical Data'!161:174,14,FALSE)) | C19: =IF(C$5>$AG19,"",HLOOKUP(C$6,'Historical Data'!161:174,14,FALSE)) | D19: =IF(D$5>$AG19,"",HLOOKUP(D$6,'Historical Data'!161:174,14,FALSE)) | E19: =IF(E$5>$AG19,"",HLOOKUP(E$6,'Historical Data'!161:174,14,FALSE)) | F19: =IF(F$5>$AG19,"",HLOOKUP(F$6,'Historical Data'!161:174,14,FALSE)) | G19: =IF(G$5>$AG19,"",HLOOKUP(G$6,'Historical Data'!161:174,14,FALSE)) | H19: =IF(H$5>$AG19,"",HLOOKUP(H$6,'Historical Data'!161:174,14,FALSE)) | I19: =IF(I$5>$AG19,"",HLOOKUP(I$6,'Historical Data'!161:174,14,FALSE)) | ... AE19: =IF(AE$5>$AG19,"",HLOOKUP(AE$6,'Historical Data'!161:174,14,FALSE)) | AF19: ='Industry Data'!B15 | AG19: =ROUNDUP(AF19/3,0) | AH19: =SUMIF($B$5:$AE$5,AG19,B36:AE36)/AG19
A20: Total Loans | B20: =SUM(B7:B19) | C20: =SUM(C7:C19) | D20: =SUM(D7:D19) | E20: =SUM(E7:E19) | F20: =SUM(F7:F19) | G20: =SUM(G7:G19) | H20: =SUM(H7:H19) | I20: =SUM(I7:I19) | ... AE20: =SUM(AE7:AE19) | AG20: =ROUNDUP(AF20/3,0)
A23: Cumlative Loan Balance Totals | B23: =B6 | C23: =C6 | D23: =D6 | E23: =E6 | F23: =F6 | G23: =G6 | H23: =H6 | I23: =I6 | ... AE23: =AE6
A24: =A7 | B24: =IFERROR(B7+C24,0) | C24: =IFERROR(C7+D24,0) | D24: =IFERROR(D7+E24,0) | E24: =IFERROR(E7+F24,0) | F24: =IFERROR(F7+G24,0) | G24: =IFERROR(G7+H24,0) | H24: =IFERROR(H7+I24,0) | I24: =IFERROR(I7+J24,0) | ... AE24: =IFERROR(AE7+AF24,0)
A25: =A8 | B25: =IFERROR(B8+C25,0) | C25: =IFERROR(C8+D25,0) | D25: =IFERROR(D8+E25,0) | E25: =IFERROR(E8+F25,0) | F25: =IFERROR(F8+G25,0) | G25: =IFERROR(G8+H25,0) | H25: =IFERROR(H8+I25,0) | I25: =IFERROR(I8+J25,0) | ... AE25: =IFERROR(AE8+AF25,0)
A26: =A9 | B26: =IFERROR(B9+C26,0) | C26: =IFERROR(C9+D26,0) | D26: =IFERROR(D9+E26,0) | E26: =IFERROR(E9+F26,0) | F26: =IFERROR(F9+G26,0) | G26: =IFERROR(G9+H26,0) | H26: =IFERROR(H9+I26,0) | I26: =IFERROR(I9+J26,0) | ... AE26: =IFERROR(AE9+AF26,0)
A27: =A10 | B27: =IFERROR(B10+C27,0) | C27: =IFERROR(C10+D27,0) | D27: =IFERROR(D10+E27,0) | E27: =IFERROR(E10+F27,0) | F27: =IFERROR(F10+G27,0) | G27: =IFERROR(G10+H27,0) | H27: =IFERROR(H10+I27,0) | I27: =IFERROR(I10+J27,0) | ... AE27: =IFERROR(AE10+AF27,0)
A28: =A11 | B28: =IFERROR(B11+C28,0) | C28: =IFERROR(C11+D28,0) | D28: =IFERROR(D11+E28,0) | E28: =IFERROR(E11+F28,0) | F28: =IFERROR(F11+G28,0) | G28: =IFERROR(G11+H28,0) | H28: =IFERROR(H11+I28,0) | I28: =IFERROR(I11+J28,0) | ... AE28: =IFERROR(AE11+AF28,0)
A29: =A12 | B29: =IFERROR(B12+C29,0) | C29: =IFERROR(C12+D29,0) | D29: =IFERROR(D12+E29,0) | E29: =IFERROR(E12+F29,0) | F29: =IFERROR(F12+G29,0) | G29: =IFERROR(G12+H29,0) | H29: =IFERROR(H12+I29,0) | I29: =IFERROR(I12+J29,0) | ... AE29: =IFERROR(AE12+AF29,0)
A30: =A13 | B30: =IFERROR(B13+C30,0) | C30: =IFERROR(C13+D30,0) | D30: =IFERROR(D13+E30,0) | E30: =IFERROR(E13+F30,0) | F30: =IFERROR(F13+G30,0) | G30: =IFERROR(G13+H30,0) | H30: =IFERROR(H13+I30,0) | I30: =IFERROR(I13+J30,0) | ... AE30: =IFERROR(AE13+AF30,0)
A31: =A14 | B31: =IFERROR(B14+C31,0) | C31: =IFERROR(C14+D31,0) | D31: =IFERROR(D14+E31,0) | E31: =IFERROR(E14+F31,0) | F31: =IFERROR(F14+G31,0) | G31: =IFERROR(G14+H31,0) | H31: =IFERROR(H14+I31,0) | I31: =IFERROR(I14+J31,0) | ... AE31: =IFERROR(AE14+AF31,0)
A32: =A15 | B32: =IFERROR(B15+C32,0) | C32: =IFERROR(C15+D32,0) | D32: =IFERROR(D15+E32,0) | E32: =IFERROR(E15+F32,0) | F32: =IFERROR(F15+G32,0) | G32: =IFERROR(G15+H32,0) | H32: =IFERROR(H15+I32,0) | I32: =IFERROR(I15+J32,0) | ... AE32: =IFERROR(AE15+AF32,0)
A33: =A16 | B33: =IFERROR(B16+C33,0) | C33: =IFERROR(C16+D33,0) | D33: =IFERROR(D16+E33,0) | E33: =IFERROR(E16+F33,0) | F33: =IFERROR(F16+G33,0) | G33: =IFERROR(G16+H33,0) | H33: =IFERROR(H16+I33,0) | I33: =IFERROR(I16+J33,0) | ... AE33: =IFERROR(AE16+AF33,0)
A34: =A17 | B34: =IFERROR(B17+C34,0) | C34: =IFERROR(C17+D34,0) | D34: =IFERROR(D17+E34,0) | E34: =IFERROR(E17+F34,0) | F34: =IFERROR(F17+G34,0) | G34: =IFERROR(G17+H34,0) | H34: =IFERROR(H17+I34,0) | I34: =IFERROR(I17+J34,0) | ... AE34: =IFERROR(AE17+AF34,0)
A35: =A18 | B35: =IFERROR(B18+C35,0) | C35: =IFERROR(C18+D35,0) | D35: =IFERROR(D18+E35,0) | E35: =IFERROR(E18+F35,0) | F35: =IFERROR(F18+G35,0) | G35: =IFERROR(G18+H35,0) | H35: =IFERROR(H18+I35,0) | I35: =IFERROR(I18+J35,0) | ... AE35: =IFERROR(AE18+AF35,0)
A36: =A19 | B36: =IFERROR(B19+C36,0) | C36: =IFERROR(C19+D36,0) | D36: =IFERROR(D19+E36,0) | E36: =IFERROR(E19+F36,0) | F36: =IFERROR(F19+G36,0) | G36: =IFERROR(G19+H36,0) | H36: =IFERROR(H19+I36,0) | I36: =IFERROR(I19+J36,0) | ... AE36: =IFERROR(AE19+AF36,0)
A37: Total Loans | B37: =SUM(B24:B36) | C37: =SUM(C24:C36) | D37: =SUM(D24:D36) | E37: =SUM(E24:E36) | F37: =SUM(F24:F36) | G37: =SUM(G24:G36) | H37: =SUM(H24:H36) | I37: =SUM(I24:I36) | ... AE37: =SUM(AE24:AE36)
A40: Net Charge offs | B40: =B6 | C40: =C6 | D40: =D6 | E40: =E6 | F40: =F6 | G40: =G6 | H40: =H6 | I40: =I6 | ... AE40: =AE6 | AF40: ACL Lifetime Months | AG40: ACL Lifetime Quarters | AH40: Total ACL Lifetime Net Charge off | AI40: ACL Loss Rate
A41: =A7 | B41: =IF(B7="","",B58) | C41: =IF(C7="","",C58) | D41: =IF(D7="","",D58) | E41: =IF(E7="","",E58) | F41: =IF(F7="","",F58) | G41: =IF(G7="","",G58) | H41: =IF(H7="","",H58) | I41: =IF(I7="","",I58) | ... AE41: =IF(AE7="","",AE58) | AF41: =AF58 | AG41: =AG58 | AH41: =AH58 | AI41: =AI58
A42: =A8 | B42: =IF(B8="","",B59) | C42: =IF(C8="","",C59) | D42: =IF(D8="","",D59) | E42: =IF(E8="","",E59) | F42: =IF(F8="","",F59) | G42: =IF(G8="","",G59) | H42: =IF(H8="","",H59) | I42: =IF(I8="","",I59) | ... AE42: =IF(AE8="","",AE59) | AF42: =AF59 | AG42: =AG59 | AH42: =AH59 | AI42: =AI59
A43: =A9 | B43: =IF(B9="","",B60) | C43: =IF(C9="","",C60) | D43: =IF(D9="","",D60) | E43: =IF(E9="","",E60) | F43: =IF(F9="","",F60) | G43: =IF(G9="","",G60) | H43: =IF(H9="","",H60) | I43: =IF(I9="","",I60) | ... AE43: =IF(AE9="","",AE60) | AF43: =AF60 | AG43: =AG60 | AH43: =AH60 | AI43: =AI60
A44: =A10 | B44: =IF(B10="","",B61) | C44: =IF(C10="","",C61) | D44: =IF(D10="","",D61) | E44: =IF(E10="","",E61) | F44: =IF(F10="","",F61) | G44: =IF(G10="","",G61) | H44: =IF(H10="","",H61) | I44: =IF(I10="","",I61) | ... AE44: =IF(AE10="","",AE61) | AF44: =AF61 | AG44: =AG61 | AH44: =AH61 | AI44: =AI61
A45: =A11 | B45: =IF(B11="","",B62) | C45: =IF(C11="","",C62) | D45: =IF(D11="","",D62) | E45: =IF(E11="","",E62) | F45: =IF(F11="","",F62) | G45: =IF(G11="","",G62) | H45: =IF(H11="","",H62) | I45: =IF(I11="","",I62) | ... AE45: =IF(AE11="","",AE62) | AF45: =AF62 | AG45: =AG62 | AH45: =AH62 | AI45: =AI62
A46: =A12 | B46: =IF(B12="","",B63) | C46: =IF(C12="","",C63) | D46: =IF(D12="","",D63) | E46: =IF(E12="","",E63) | F46: =IF(F12="","",F63) | G46: =IF(G12="","",G63) | H46: =IF(H12="","",H63) | I46: =IF(I12="","",I63) | ... AE46: =IF(AE12="","",AE63) | AF46: =AF63 | AG46: =AG63 | AH46: =AH63 | AI46: =AI63
A47: =A13 | B47: =IF(B13="","",B64) | C47: =IF(C13="","",C64) | D47: =IF(D13="","",D64) | E47: =IF(E13="","",E64) | F47: =IF(F13="","",F64) | G47: =IF(G13="","",G64) | H47: =IF(H13="","",H64) | I47: =IF(I13="","",I64) | ... AE47: =IF(AE13="","",AE64) | AF47: =AF64 | AG47: =AG64 | AH47: =AH64 | AI47: =AI64
A48: =A14 | B48: =IF(B14="","",B65) | C48: =IF(C14="","",C65) | D48: =IF(D14="","",D65) | E48: =IF(E14="","",E65) | F48: =IF(F14="","",F65) | G48: =IF(G14="","",G65) | H48: =IF(H14="","",H65) | I48: =IF(I14="","",I65) | ... AE48: =IF(AE14="","",AE65) | AF48: =AF65 | AG48: =AG65 | AH48: =AH65 | AI48: =AI65
A49: =A15 | B49: =IF(B15="","",B66) | C49: =IF(C15="","",C66) | D49: =IF(D15="","",D66) | E49: =IF(E15="","",E66) | F49: =IF(F15="","",F66) | G49: =IF(G15="","",G66) | H49: =IF(H15="","",H66) | I49: =IF(I15="","",I66) | ... AE49: =IF(AE15="","",AE66) | AF49: =AF66 | AG49: =AG66 | AH49: =AH66 | AI49: =AI66
A50: =A16 | B50: =IF(B16="","",B67) | C50: =IF(C16="","",C67) | D50: =IF(D16="","",D67) | E50: =IF(E16="","",E67) | F50: =IF(F16="","",F67) | G50: =IF(G16="","",G67) | H50: =IF(H16="","",H67) | I50: =IF(I16="","",I67) | ... AE50: =IF(AE16="","",AE67) | AF50: =AF67 | AG50: =AG67 | AH50: =AH67 | AI50: =AI67
A51: =A17 | B51: =IF(B17="","",B68) | C51: =IF(C17="","",C68) | D51: =IF(D17="","",D68) | E51: =IF(E17="","",E68) | F51: =IF(F17="","",F68) | G51: =IF(G17="","",G68) | H51: =IF(H17="","",H68) | I51: =IF(I17="","",I68) | ... AE51: =IF(AE17="","",AE68) | AF51: =AF68 | AG51: =AG68 | AH51: =AH68 | AI51: =AI68
A52: =A18 | B52: =IF(B18="","",B69) | C52: =IF(C18="","",C69) | D52: =IF(D18="","",D69) | E52: =IF(E18="","",E69) | F52: =IF(F18="","",F69) | G52: =IF(G18="","",G69) | H52: =IF(H18="","",H69) | I52: =IF(I18="","",I69) | ... AE52: =IF(AE18="","",AE69) | AF52: =AF69 | AG52: =AG69 | AH52: =AH69 | AI52: =AI69
A53: =A19 | B53: =IF(B19="","",B70) | C53: =IF(C19="","",C70) | D53: =IF(D19="","",D70) | E53: =IF(E19="","",E70) | F53: =IF(F19="","",F70) | G53: =IF(G19="","",G70) | H53: =IF(H19="","",H70) | I53: =IF(I19="","",I70) | ... AE53: =IF(AE19="","",AE70) | AF53: =AF70 | AG53: =AG70 | AH53: =AH70 | AI53: =AI70
A54: Total Charge Offs | B54: =IF(B20="","",B71) | C54: =IF(C20="","",C71) | D54: =IF(D20="","",D71) | E54: =IF(E20="","",E71) | F54: =IF(F20="","",F71) | G54: =IF(G20="","",G71) | H54: =IF(H20="","",H71) | I54: =IF(I20="","",I71) | ... AE54: =IF(AE20="","",AE71)
A57: Net Charge Offs | B57: =B6 | C57: =C6 | D57: =D6 | E57: =E6 | F57: =F6 | G57: =G6 | H57: =H6 | I57: =I6 | ... AE57: =AE6 | AF57: ACL Lifetime Months | AG57: ACL Lifetime Quarters | AH57: Total ACL Lifetime Net Charge off | AI57: ACL Loss Rate
A58: =A7 | C58: =IF(C$2=3,HLOOKUP(C$57,'Historical Data'!196:209,2,FALSE),(HLOOKUP(C$57,'Historical Data'!196:209,2,FALSE)-B58)) | D58: =HLOOKUP(D$57,'Historical Data'!213:226,2,FALSE) | E58: =HLOOKUP(E$57,'Historical Data'!213:226,2,FALSE) | F58: =HLOOKUP(F$57,'Historical Data'!213:226,2,FALSE) | G58: =HLOOKUP(G$57,'Historical Data'!213:226,2,FALSE) | H58: =HLOOKUP(H$57,'Historical Data'!213:226,2,FALSE) | I58: =HLOOKUP(I$57,'Historical Data'!213:226,2,FALSE) | J58: =HLOOKUP(J$57,'Historical Data'!213:226,2,FALSE) | K58: =HLOOKUP(K$57,'Historical Data'!213:226,2,FALSE) | ... AE58: =HLOOKUP(AE$57,'Historical Data'!213:226,2,FALSE) | AF58: =AF7 | AG58: =ROUNDUP(AF58/3,0) | AH58: =SUMIF($B$5:$AE$5,AG58,B75:AE75) | AI58: =IFERROR(IF(AH58/AH7<=0,0,AH58/AH7),0)
A59: =A8 | C59: =IF(C$2=3,HLOOKUP(C$57,'Historical Data'!196:209,3,FALSE),(HLOOKUP(C$57,'Historical Data'!196:209,3,FALSE)-B59)) | D59: =HLOOKUP(D$57,'Historical Data'!213:226,3,FALSE) | E59: =HLOOKUP(E$57,'Historical Data'!213:226,3,FALSE) | F59: =HLOOKUP(F$57,'Historical Data'!213:226,3,FALSE) | G59: =HLOOKUP(G$57,'Historical Data'!213:226,3,FALSE) | H59: =HLOOKUP(H$57,'Historical Data'!213:226,3,FALSE) | I59: =HLOOKUP(I$57,'Historical Data'!213:226,3,FALSE) | J59: =HLOOKUP(J$57,'Historical Data'!213:226,3,FALSE) | K59: =HLOOKUP(K$57,'Historical Data'!213:226,3,FALSE) | ... AE59: =HLOOKUP(AE$57,'Historical Data'!213:226,3,FALSE) | AF59: =AF8 | AG59: =ROUNDUP(AF59/3,0) | AH59: =SUMIF($B$5:$AE$5,AG59,B76:AE76) | AI59: =IFERROR(IF(AH59/AH8<=0,0,AH59/AH8),0)
A60: =A9 | C60: =IF(C$2=3,HLOOKUP(C$57,'Historical Data'!196:209,4,FALSE),(HLOOKUP(C$57,'Historical Data'!196:209,4,FALSE)-B60)) | D60: =HLOOKUP(D$57,'Historical Data'!213:226,4,FALSE) | E60: =HLOOKUP(E$57,'Historical Data'!213:226,4,FALSE) | F60: =HLOOKUP(F$57,'Historical Data'!213:226,4,FALSE) | G60: =HLOOKUP(G$57,'Historical Data'!213:226,4,FALSE) | H60: =HLOOKUP(H$57,'Historical Data'!213:226,4,FALSE) | I60: =HLOOKUP(I$57,'Historical Data'!213:226,4,FALSE) | J60: =HLOOKUP(J$57,'Historical Data'!213:226,4,FALSE) | K60: =HLOOKUP(K$57,'Historical Data'!213:226,4,FALSE) | ... AE60: =HLOOKUP(AE$57,'Historical Data'!213:226,4,FALSE) | AF60: =AF9 | AG60: =ROUNDUP(AF60/3,0) | AH60: =SUMIF($B$5:$AE$5,AG60,B77:AE77) | AI60: =IFERROR(IF(AH60/AH9<=0,0,AH60/AH9),0)
A61: =A10 | C61: =IF(C$2=3,HLOOKUP(C$57,'Historical Data'!196:209,5,FALSE),(HLOOKUP(C$57,'Historical Data'!196:209,5,FALSE)-B61)) | D61: =HLOOKUP(D$57,'Historical Data'!213:226,5,FALSE) | E61: =HLOOKUP(E$57,'Historical Data'!213:226,5,FALSE) | F61: =HLOOKUP(F$57,'Historical Data'!213:226,5,FALSE) | G61: =HLOOKUP(G$57,'Historical Data'!213:226,5,FALSE) | H61: =HLOOKUP(H$57,'Historical Data'!213:226,5,FALSE) | I61: =HLOOKUP(I$57,'Historical Data'!213:226,5,FALSE) | J61: =HLOOKUP(J$57,'Historical Data'!213:226,5,FALSE) | K61: =HLOOKUP(K$57,'Historical Data'!213:226,5,FALSE) | ... AE61: =HLOOKUP(AE$57,'Historical Data'!213:226,5,FALSE) | AF61: =AF10 | AG61: =ROUNDUP(AF61/3,0) | AH61: =SUMIF($B$5:$AE$5,AG61,B78:AE78) | AI61: =IFERROR(IF(AH61/AH10<=0,0,AH61/AH10),0)
A62: =A11 | C62: =IF(C$2=3,HLOOKUP(C$57,'Historical Data'!196:209,6,FALSE),(HLOOKUP(C$57,'Historical Data'!196:209,6,FALSE)-B62)) | D62: =HLOOKUP(D$57,'Historical Data'!213:226,6,FALSE) | E62: =HLOOKUP(E$57,'Historical Data'!213:226,6,FALSE) | F62: =HLOOKUP(F$57,'Historical Data'!213:226,6,FALSE) | G62: =HLOOKUP(G$57,'Historical Data'!213:226,6,FALSE) | H62: =HLOOKUP(H$57,'Historical Data'!213:226,6,FALSE) | I62: =HLOOKUP(I$57,'Historical Data'!213:226,6,FALSE) | J62: =HLOOKUP(J$57,'Historical Data'!213:226,6,FALSE) | K62: =HLOOKUP(K$57,'Historical Data'!213:226,6,FALSE) | ... AE62: =HLOOKUP(AE$57,'Historical Data'!213:226,6,FALSE) | AF62: =AF11 | AG62: =ROUNDUP(AF62/3,0) | AH62: =SUMIF($B$5:$AE$5,AG62,B79:AE79) | AI62: =IFERROR(IF(AH62/AH11<=0,0,AH62/AH11),0)
A63: =A12 | C63: =IF(C$2=3,HLOOKUP(C$57,'Historical Data'!196:209,7,FALSE),(HLOOKUP(C$57,'Historical Data'!196:209,7,FALSE)-B63)) | D63: =HLOOKUP(D$57,'Historical Data'!213:226,7,FALSE) | E63: =HLOOKUP(E$57,'Historical Data'!213:226,7,FALSE) | F63: =HLOOKUP(F$57,'Historical Data'!213:226,7,FALSE) | G63: =HLOOKUP(G$57,'Historical Data'!213:226,7,FALSE) | H63: =HLOOKUP(H$57,'Historical Data'!213:226,7,FALSE) | I63: =HLOOKUP(I$57,'Historical Data'!213:226,7,FALSE) | J63: =HLOOKUP(J$57,'Historical Data'!213:226,7,FALSE) | K63: =HLOOKUP(K$57,'Historical Data'!213:226,7,FALSE) | ... AE63: =HLOOKUP(AE$57,'Historical Data'!213:226,7,FALSE) | AF63: =AF12 | AG63: =ROUNDUP(AF63/3,0) | AH63: =SUMIF($B$5:$AE$5,AG63,B80:AE80) | AI63: =IFERROR(IF(AH63/AH12<=0,0,AH63/AH12),0)
A64: =A13 | C64: =IF(C$2=3,HLOOKUP(C$57,'Historical Data'!196:209,8,FALSE),(HLOOKUP(C$57,'Historical Data'!196:209,8,FALSE)-B64)) | D64: =HLOOKUP(D$57,'Historical Data'!213:226,8,FALSE) | E64: =HLOOKUP(E$57,'Historical Data'!213:226,8,FALSE) | F64: =HLOOKUP(F$57,'Historical Data'!213:226,8,FALSE) | G64: =HLOOKUP(G$57,'Historical Data'!213:226,8,FALSE) | H64: =HLOOKUP(H$57,'Historical Data'!213:226,8,FALSE) | I64: =HLOOKUP(I$57,'Historical Data'!213:226,8,FALSE) | J64: =HLOOKUP(J$57,'Historical Data'!213:226,8,FALSE) | K64: =HLOOKUP(K$57,'Historical Data'!213:226,8,FALSE) | ... AE64: =HLOOKUP(AE$57,'Historical Data'!213:226,8,FALSE) | AF64: =AF13 | AG64: =ROUNDUP(AF64/3,0) | AH64: =SUMIF($B$5:$AE$5,AG64,B81:AE81) | AI64: =IFERROR(IF(AH64/AH13<=0,0,AH64/AH13),0)
A65: =A14 | C65: =IF(C$2=3,HLOOKUP(C$57,'Historical Data'!196:209,9,FALSE),(HLOOKUP(C$57,'Historical Data'!196:209,9,FALSE)-B65)) | D65: =HLOOKUP(D$57,'Historical Data'!213:226,9,FALSE) | E65: =HLOOKUP(E$57,'Historical Data'!213:226,9,FALSE) | F65: =HLOOKUP(F$57,'Historical Data'!213:226,9,FALSE) | G65: =HLOOKUP(G$57,'Historical Data'!213:226,9,FALSE) | H65: =HLOOKUP(H$57,'Historical Data'!213:226,9,FALSE) | I65: =HLOOKUP(I$57,'Historical Data'!213:226,9,FALSE) | J65: =HLOOKUP(J$57,'Historical Data'!213:226,9,FALSE) | K65: =HLOOKUP(K$57,'Historical Data'!213:226,9,FALSE) | ... AE65: =HLOOKUP(AE$57,'Historical Data'!213:226,9,FALSE) | AF65: =AF14 | AG65: =ROUNDUP(AF65/3,0) | AH65: =SUMIF($B$5:$AE$5,AG65,B82:AE82) | AI65: =IFERROR(IF(AH65/AH14<=0,0,AH65/AH14),0)
A66: =A15 | C66: =IF(C$2=3,HLOOKUP(C$57,'Historical Data'!196:209,10,FALSE),(HLOOKUP(C$57,'Historical Data'!196:209,10,FALSE)-B66)) | D66: =HLOOKUP(D$57,'Historical Data'!213:226,10,FALSE) | E66: =HLOOKUP(E$57,'Historical Data'!213:226,10,FALSE) | F66: =HLOOKUP(F$57,'Historical Data'!213:226,10,FALSE) | G66: =HLOOKUP(G$57,'Historical Data'!213:226,10,FALSE) | H66: =HLOOKUP(H$57,'Historical Data'!213:226,10,FALSE) | I66: =HLOOKUP(I$57,'Historical Data'!213:226,10,FALSE) | J66: =HLOOKUP(J$57,'Historical Data'!213:226,10,FALSE) | K66: =HLOOKUP(K$57,'Historical Data'!213:226,10,FALSE) | ... AE66: =HLOOKUP(AE$57,'Historical Data'!213:226,10,FALSE) | AF66: =AF15 | AG66: =ROUNDUP(AF66/3,0) | AH66: =SUMIF($B$5:$AE$5,AG66,B83:AE83) | AI66: =IFERROR(IF(AH66/AH15<=0,0,AH66/AH15),0)
A67: =A16 | C67: =IF(C$2=3,HLOOKUP(C$57,'Historical Data'!196:209,11,FALSE),(HLOOKUP(C$57,'Historical Data'!196:209,11,FALSE)-B67)) | D67: =HLOOKUP(D$57,'Historical Data'!213:226,11,FALSE) | E67: =HLOOKUP(E$57,'Historical Data'!213:226,11,FALSE) | F67: =HLOOKUP(F$57,'Historical Data'!213:226,11,FALSE) | G67: =HLOOKUP(G$57,'Historical Data'!213:226,11,FALSE) | H67: =HLOOKUP(H$57,'Historical Data'!213:226,11,FALSE) | I67: =HLOOKUP(I$57,'Historical Data'!213:226,11,FALSE) | J67: =HLOOKUP(J$57,'Historical Data'!213:226,11,FALSE) | K67: =HLOOKUP(K$57,'Historical Data'!213:226,11,FALSE) | ... AE67: =HLOOKUP(AE$57,'Historical Data'!213:226,11,FALSE) | AF67: =AF16 | AG67: =ROUNDUP(AF67/3,0) | AH67: =SUMIF($B$5:$AE$5,AG67,B84:AE84) | AI67: =IFERROR(IF(AH67/AH16<=0,0,AH67/AH16),0)
A68: =A17 | C68: =IF(C$2=3,HLOOKUP(C$57,'Historical Data'!196:209,12,FALSE),(HLOOKUP(C$57,'Historical Data'!196:209,12,FALSE)-B68)) | D68: =HLOOKUP(D$57,'Historical Data'!213:226,12,FALSE) | E68: =HLOOKUP(E$57,'Historical Data'!213:226,12,FALSE) | F68: =HLOOKUP(F$57,'Historical Data'!213:226,12,FALSE) | G68: =HLOOKUP(G$57,'Historical Data'!213:226,12,FALSE) | H68: =HLOOKUP(H$57,'Historical Data'!213:226,12,FALSE) | I68: =HLOOKUP(I$57,'Historical Data'!213:226,12,FALSE) | J68: =HLOOKUP(J$57,'Historical Data'!213:226,12,FALSE) | K68: =HLOOKUP(K$57,'Historical Data'!213:226,12,FALSE) | ... AE68: =HLOOKUP(AE$57,'Historical Data'!213:226,12,FALSE) | AF68: =AF17 | AG68: =ROUNDUP(AF68/3,0) | AH68: =SUMIF($B$5:$AE$5,AG68,B85:AE85) | AI68: =IFERROR(IF(AH68/AH17<=0,0,AH68/AH17),0)
A69: =A18 | C69: =IF(C$2=3,HLOOKUP(C$57,'Historical Data'!196:209,13,FALSE),(HLOOKUP(C$57,'Historical Data'!196:209,13,FALSE)-B69)) | D69: =HLOOKUP(D$57,'Historical Data'!213:226,13,FALSE) | E69: =HLOOKUP(E$57,'Historical Data'!213:226,13,FALSE) | F69: =HLOOKUP(F$57,'Historical Data'!213:226,13,FALSE) | G69: =HLOOKUP(G$57,'Historical Data'!213:226,13,FALSE) | H69: =HLOOKUP(H$57,'Historical Data'!213:226,13,FALSE) | I69: =HLOOKUP(I$57,'Historical Data'!213:226,13,FALSE) | J69: =HLOOKUP(J$57,'Historical Data'!213:226,13,FALSE) | K69: =HLOOKUP(K$57,'Historical Data'!213:226,13,FALSE) | ... AE69: =HLOOKUP(AE$57,'Historical Data'!213:226,13,FALSE) | AF69: =AF18 | AG69: =ROUNDUP(AF69/3,0) | AH69: =SUMIF($B$5:$AE$5,AG69,B86:AE86) | AI69: =IFERROR(IF(AH69/AH18<=0,0,AH69/AH18),0)
A70: =A19 | C70: =IF(C$2=3,HLOOKUP(C$57,'Historical Data'!196:209,14,FALSE),(HLOOKUP(C$57,'Historical Data'!196:209,14,FALSE)-B70)) | D70: =HLOOKUP(D$57,'Historical Data'!213:226,14,FALSE) | E70: =HLOOKUP(E$57,'Historical Data'!213:226,14,FALSE) | F70: =HLOOKUP(F$57,'Historical Data'!213:226,14,FALSE) | G70: =HLOOKUP(G$57,'Historical Data'!213:226,14,FALSE) | H70: =HLOOKUP(H$57,'Historical Data'!213:226,14,FALSE) | I70: =HLOOKUP(I$57,'Historical Data'!213:226,14,FALSE) | J70: =HLOOKUP(J$57,'Historical Data'!213:226,14,FALSE) | K70: =HLOOKUP(K$57,'Historical Data'!213:226,14,FALSE) | ... AE70: =HLOOKUP(AE$57,'Historical Data'!213:226,14,FALSE) | AF70: =AF19 | AG70: =ROUNDUP(AF70/3,0) | AH70: =SUMIF($B$5:$AE$5,AG70,B87:AE87) | AI70: =IFERROR(IF(AH70/AH19<=0,0,AH70/AH19),0)
A71: Total Loans | C71: =SUM(C58:C70) | D71: =SUM(D58:D70) | E71: =SUM(E58:E70) | F71: =SUM(F58:F70) | G71: =SUM(G58:G70) | H71: =SUM(H58:H70) | I71: =SUM(I58:I70) | J71: =SUM(J58:J70) | ... AE71: =SUM(AE58:AE70)
A74: Cumlative Net Charge Off Totals | B74: =B57 | C74: =C57 | D74: =D57 | E74: =E57 | F74: =F57 | G74: =G57 | H74: =H57 | I74: =I57 | ... AE74: =AE57
A75: =A58 | B75: =B58+C75 | C75: =C58+D75 | D75: =D58+E75 | E75: =E58+F75 | F75: =F58+G75 | G75: =G58+H75 | H75: =H58+I75 | I75: =I58+J75 | ... AD75: =AD58+AE75 | AE75: =AE58
A76: =A59 | B76: =B59+C76 | C76: =C59+D76 | D76: =D59+E76 | E76: =E59+F76 | F76: =F59+G76 | G76: =G59+H76 | H76: =H59+I76 | I76: =I59+J76 | ... AD76: =AD59+AE76 | AE76: =AE59
A77: =A60 | B77: =B60+C77 | C77: =C60+D77 | D77: =D60+E77 | E77: =E60+F77 | F77: =F60+G77 | G77: =G60+H77 | H77: =H60+I77 | I77: =I60+J77 | ... AD77: =AD60+AE77 | AE77: =AE60
A78: =A61 | B78: =B61+C78 | C78: =C61+D78 | D78: =D61+E78 | E78: =E61+F78 | F78: =F61+G78 | G78: =G61+H78 | H78: =H61+I78 | I78: =I61+J78 | ... AD78: =AD61+AE78 | AE78: =AE61
A79: =A62 | B79: =B62+C79 | C79: =C62+D79 | D79: =D62+E79 | E79: =E62+F79 | F79: =F62+G79 | G79: =G62+H79 | H79: =H62+I79 | I79: =I62+J79 | ... AD79: =AD62+AE79 | AE79: =AE62
A80: =A63 | B80: =B63+C80 | C80: =C63+D80 | D80: =D63+E80 | E80: =E63+F80 | F80: =F63+G80 | G80: =G63+H80 | H80: =H63+I80 | I80: =I63+J80 | ... AD80: =AD63+AE80 | AE80: =AE63
A81: =A64 | B81: =B64+C81 | C81: =C64+D81 | D81: =D64+E81 | E81: =E64+F81 | F81: =F64+G81 | G81: =G64+H81 | H81: =H64+I81 | I81: =I64+J81 | ... AD81: =AD64+AE81 | AE81: =AE64
A82: =A65 | B82: =B65+C82 | C82: =C65+D82 | D82: =D65+E82 | E82: =E65+F82 | F82: =F65+G82 | G82: =G65+H82 | H82: =H65+I82 | I82: =I65+J82 | ... AD82: =AD65+AE82 | AE82: =AE65
A83: =A66 | B83: =B66+C83 | C83: =C66+D83 | D83: =D66+E83 | E83: =E66+F83 | F83: =F66+G83 | G83: =G66+H83 | H83: =H66+I83 | I83: =I66+J83 | ... AD83: =AD66+AE83 | AE83: =AE66
A84: =A67 | B84: =B67+C84 | C84: =C67+D84 | D84: =D67+E84 | E84: =E67+F84 | F84: =F67+G84 | G84: =G67+H84 | H84: =H67+I84 | I84: =I67+J84 | ... AD84: =AD67+AE84 | AE84: =AE67
A85: =A68 | B85: =B68+C85 | C85: =C68+D85 | D85: =D68+E85 | E85: =E68+F85 | F85: =F68+G85 | G85: =G68+H85 | H85: =H68+I85 | I85: =I68+J85 | ... AD85: =AD68+AE85 | AE85: =AE68
A86: =A69 | B86: =B69+C86 | C86: =C69+D86 | D86: =D69+E86 | E86: =E69+F86 | F86: =F69+G86 | G86: =G69+H86 | H86: =H69+I86 | I86: =I69+J86 | ... AD86: =AD69+AE86 | AE86: =AE69
A87: =A70 | B87: =B70+C87 | C87: =C70+D87 | D87: =D70+E87 | E87: =E70+F87 | F87: =F70+G87 | G87: =G70+H87 | H87: =H70+I87 | I87: =I70+J87 | ... AD87: =AD70+AE87 | AE87: =AE70
A88: Total Loans | B88: =SUM(B75:B87) | C88: =SUM(C75:C87) | D88: =SUM(D75:D87) | E88: =SUM(E75:E87) | F88: =SUM(F75:F87) | G88: =SUM(G75:G87) | H88: =SUM(H75:H87) | I88: =SUM(I75:I87) | ... AE88: =SUM(AE75:AE87)
A91: Historical Dellinquency % | B91: =B74 | C91: =C74 | D91: =D74 | E91: =E74 | F91: =F74 | G91: =G74 | H91: =H74 | I91: =I74 | ... AE91: =AE74 | AF91: =AF6 | AG91: =AG6 | AH91: =AH6 | AI91: Current Variance
A92: =A75 | B92: =HLOOKUP(B$91,'Historical Data'!231:244,2,FALSE) | C92: =HLOOKUP(C$91,'Historical Data'!231:244,2,FALSE) | D92: =HLOOKUP(D$91,'Historical Data'!231:244,2,FALSE) | E92: =HLOOKUP(E$91,'Historical Data'!231:244,2,FALSE) | F92: =HLOOKUP(F$91,'Historical Data'!231:244,2,FALSE) | G92: =HLOOKUP(G$91,'Historical Data'!231:244,2,FALSE) | H92: =HLOOKUP(H$91,'Historical Data'!231:244,2,FALSE) | I92: =HLOOKUP(I$91,'Historical Data'!231:244,2,FALSE) | ... AE92: =HLOOKUP(AE$91,'Historical Data'!231:244,2,FALSE) | AF92: =AF7 | AG92: =ROUNDUP(AF92/3,0) | AH92: =SUMIF($B$5:$AE$5,AG92,B109:AE109)/AG92 | AI92: =AE92-AH92
A93: =A76 | B93: =HLOOKUP(B$91,'Historical Data'!231:244,3,FALSE) | C93: =HLOOKUP(C$91,'Historical Data'!231:244,3,FALSE) | D93: =HLOOKUP(D$91,'Historical Data'!231:244,3,FALSE) | E93: =HLOOKUP(E$91,'Historical Data'!231:244,3,FALSE) | F93: =HLOOKUP(F$91,'Historical Data'!231:244,3,FALSE) | G93: =HLOOKUP(G$91,'Historical Data'!231:244,3,FALSE) | H93: =HLOOKUP(H$91,'Historical Data'!231:244,3,FALSE) | I93: =HLOOKUP(I$91,'Historical Data'!231:244,3,FALSE) | ... AE93: =HLOOKUP(AE$91,'Historical Data'!231:244,3,FALSE) | AF93: =AF8 | AG93: =ROUNDUP(AF93/3,0) | AH93: =SUMIF($B$5:$AE$5,AG93,B110:AE110)/AG93 | AI93: =AE93-AH93
A94: =A77 | B94: =HLOOKUP(B$91,'Historical Data'!231:244,4,FALSE) | C94: =HLOOKUP(C$91,'Historical Data'!231:244,4,FALSE) | D94: =HLOOKUP(D$91,'Historical Data'!231:244,4,FALSE) | E94: =HLOOKUP(E$91,'Historical Data'!231:244,4,FALSE) | F94: =HLOOKUP(F$91,'Historical Data'!231:244,4,FALSE) | G94: =HLOOKUP(G$91,'Historical Data'!231:244,4,FALSE) | H94: =HLOOKUP(H$91,'Historical Data'!231:244,4,FALSE) | I94: =HLOOKUP(I$91,'Historical Data'!231:244,4,FALSE) | ... AE94: =HLOOKUP(AE$91,'Historical Data'!231:244,4,FALSE) | AF94: =AF9 | AG94: =ROUNDUP(AF94/3,0) | AH94: =SUMIF($B$5:$AE$5,AG94,B111:AE111)/AG94 | AI94: =AE94-AH94
A95: =A78 | B95: =HLOOKUP(B$91,'Historical Data'!231:244,5,FALSE) | C95: =HLOOKUP(C$91,'Historical Data'!231:244,5,FALSE) | D95: =HLOOKUP(D$91,'Historical Data'!231:244,5,FALSE) | E95: =HLOOKUP(E$91,'Historical Data'!231:244,5,FALSE) | F95: =HLOOKUP(F$91,'Historical Data'!231:244,5,FALSE) | G95: =HLOOKUP(G$91,'Historical Data'!231:244,5,FALSE) | H95: =HLOOKUP(H$91,'Historical Data'!231:244,5,FALSE) | I95: =HLOOKUP(I$91,'Historical Data'!231:244,5,FALSE) | ... AE95: =HLOOKUP(AE$91,'Historical Data'!231:244,5,FALSE) | AF95: =AF10 | AG95: =ROUNDUP(AF95/3,0) | AH95: =SUMIF($B$5:$AE$5,AG95,B113:AE113)/AG95 | AI95: =AE95-AH95
A96: =A79 | B96: =HLOOKUP(B$91,'Historical Data'!231:244,6,FALSE) | C96: =HLOOKUP(C$91,'Historical Data'!231:244,6,FALSE) | D96: =HLOOKUP(D$91,'Historical Data'!231:244,6,FALSE) | E96: =HLOOKUP(E$91,'Historical Data'!231:244,6,FALSE) | F96: =HLOOKUP(F$91,'Historical Data'!231:244,6,FALSE) | G96: =HLOOKUP(G$91,'Historical Data'!231:244,6,FALSE) | H96: =HLOOKUP(H$91,'Historical Data'!231:244,6,FALSE) | I96: =HLOOKUP(I$91,'Historical Data'!231:244,6,FALSE) | ... AE96: =HLOOKUP(AE$91,'Historical Data'!231:244,6,FALSE) | AF96: =AF11 | AG96: =ROUNDUP(AF96/3,0) | AH96: =SUMIF($B$5:$AE$5,AG96,B113:AE113)/AG96 | AI96: =AE96-AH96
A97: =A80 | B97: =HLOOKUP(B$91,'Historical Data'!231:244,7,FALSE) | C97: =HLOOKUP(C$91,'Historical Data'!231:244,7,FALSE) | D97: =HLOOKUP(D$91,'Historical Data'!231:244,7,FALSE) | E97: =HLOOKUP(E$91,'Historical Data'!231:244,7,FALSE) | F97: =HLOOKUP(F$91,'Historical Data'!231:244,7,FALSE) | G97: =HLOOKUP(G$91,'Historical Data'!231:244,7,FALSE) | H97: =HLOOKUP(H$91,'Historical Data'!231:244,7,FALSE) | I97: =HLOOKUP(I$91,'Historical Data'!231:244,7,FALSE) | ... AE97: =HLOOKUP(AE$91,'Historical Data'!231:244,7,FALSE) | AF97: =AF12 | AG97: =ROUNDUP(AF97/3,0) | AH97: =SUMIF($B$5:$AE$5,AG97,B114:AE114)/AG97 | AI97: =AE97-AH97
A98: =A81 | B98: =HLOOKUP(B$91,'Historical Data'!231:244,8,FALSE) | C98: =HLOOKUP(C$91,'Historical Data'!231:244,8,FALSE) | D98: =HLOOKUP(D$91,'Historical Data'!231:244,8,FALSE) | E98: =HLOOKUP(E$91,'Historical Data'!231:244,8,FALSE) | F98: =HLOOKUP(F$91,'Historical Data'!231:244,8,FALSE) | G98: =HLOOKUP(G$91,'Historical Data'!231:244,8,FALSE) | H98: =HLOOKUP(H$91,'Historical Data'!231:244,8,FALSE) | I98: =HLOOKUP(I$91,'Historical Data'!231:244,8,FALSE) | ... AE98: =HLOOKUP(AE$91,'Historical Data'!231:244,8,FALSE) | AF98: =AF13 | AG98: =ROUNDUP(AF98/3,0) | AH98: =SUMIF($B$5:$AE$5,AG98,B115:AE115)/AG98 | AI98: =AE98-AH98
A99: =A82 | B99: =HLOOKUP(B$91,'Historical Data'!231:244,9,FALSE) | C99: =HLOOKUP(C$91,'Historical Data'!231:244,9,FALSE) | D99: =HLOOKUP(D$91,'Historical Data'!231:244,9,FALSE) | E99: =HLOOKUP(E$91,'Historical Data'!231:244,9,FALSE) | F99: =HLOOKUP(F$91,'Historical Data'!231:244,9,FALSE) | G99: =HLOOKUP(G$91,'Historical Data'!231:244,9,FALSE) | H99: =HLOOKUP(H$91,'Historical Data'!231:244,9,FALSE) | I99: =HLOOKUP(I$91,'Historical Data'!231:244,9,FALSE) | ... AE99: =HLOOKUP(AE$91,'Historical Data'!231:244,9,FALSE) | AF99: =AF14 | AG99: =ROUNDUP(AF99/3,0) | AH99: =SUMIF($B$5:$AE$5,AG99,B115:AE115)/AG99 | AI99: =AE99-AH99
A100: =A83 | B100: =HLOOKUP(B$91,'Historical Data'!231:244,10,FALSE) | C100: =HLOOKUP(C$91,'Historical Data'!231:244,10,FALSE) | D100: =HLOOKUP(D$91,'Historical Data'!231:244,10,FALSE) | E100: =HLOOKUP(E$91,'Historical Data'!231:244,10,FALSE) | F100: =HLOOKUP(F$91,'Historical Data'!231:244,10,FALSE) | G100: =HLOOKUP(G$91,'Historical Data'!231:244,10,FALSE) | H100: =HLOOKUP(H$91,'Historical Data'!231:244,10,FALSE) | I100: =HLOOKUP(I$91,'Historical Data'!231:244,10,FALSE) | ... AE100: =HLOOKUP(AE$91,'Historical Data'!231:244,10,FALSE) | AF100: =AF15 | AG100: =ROUNDUP(AF100/3,0) | AH100: =SUMIF($B$5:$AE$5,AG100,B117:AE117)/AG100 | AI100: =AE100-AH100
A101: =A84 | B101: =HLOOKUP(B$91,'Historical Data'!231:244,11,FALSE) | C101: =HLOOKUP(C$91,'Historical Data'!231:244,11,FALSE) | D101: =HLOOKUP(D$91,'Historical Data'!231:244,11,FALSE) | E101: =HLOOKUP(E$91,'Historical Data'!231:244,11,FALSE) | F101: =HLOOKUP(F$91,'Historical Data'!231:244,11,FALSE) | G101: =HLOOKUP(G$91,'Historical Data'!231:244,11,FALSE) | H101: =HLOOKUP(H$91,'Historical Data'!231:244,11,FALSE) | I101: =HLOOKUP(I$91,'Historical Data'!231:244,11,FALSE) | ... AE101: =HLOOKUP(AE$91,'Historical Data'!231:244,11,FALSE) | AF101: =AF16 | AG101: =ROUNDUP(AF101/3,0) | AH101: =SUMIF($B$5:$AE$5,AG101,B118:AE118)/AG101 | AI101: =AE101-AH101
A102: =A85 | B102: =HLOOKUP(B$91,'Historical Data'!231:244,12,FALSE) | C102: =HLOOKUP(C$91,'Historical Data'!231:244,12,FALSE) | D102: =HLOOKUP(D$91,'Historical Data'!231:244,12,FALSE) | E102: =HLOOKUP(E$91,'Historical Data'!231:244,12,FALSE) | F102: =HLOOKUP(F$91,'Historical Data'!231:244,12,FALSE) | G102: =HLOOKUP(G$91,'Historical Data'!231:244,12,FALSE) | H102: =HLOOKUP(H$91,'Historical Data'!231:244,12,FALSE) | I102: =HLOOKUP(I$91,'Historical Data'!231:244,12,FALSE) | ... AE102: =HLOOKUP(AE$91,'Historical Data'!231:244,12,FALSE) | AF102: =AF17 | AG102: =ROUNDUP(AF102/3,0) | AH102: =SUMIF($B$5:$AE$5,AG102,B119:AE119)/AG102 | AI102: =AE102-AH102
A103: =A86 | B103: =HLOOKUP(B$91,'Historical Data'!231:244,13,FALSE) | C103: =HLOOKUP(C$91,'Historical Data'!231:244,13,FALSE) | D103: =HLOOKUP(D$91,'Historical Data'!231:244,13,FALSE) | E103: =HLOOKUP(E$91,'Historical Data'!231:244,13,FALSE) | F103: =HLOOKUP(F$91,'Historical Data'!231:244,13,FALSE) | G103: =HLOOKUP(G$91,'Historical Data'!231:244,13,FALSE) | H103: =HLOOKUP(H$91,'Historical Data'!231:244,13,FALSE) | I103: =HLOOKUP(I$91,'Historical Data'!231:244,13,FALSE) | ... AE103: =HLOOKUP(AE$91,'Historical Data'!231:244,13,FALSE) | AF103: =AF18 | AG103: =ROUNDUP(AF103/3,0) | AH103: =SUMIF($B$5:$AE$5,AG103,B124:AE124)/AG103 | AI103: =AE103-AH103
A104: =A87 | B104: =HLOOKUP(B$91,'Historical Data'!231:244,14,FALSE) | C104: =HLOOKUP(C$91,'Historical Data'!231:244,14,FALSE) | D104: =HLOOKUP(D$91,'Historical Data'!231:244,14,FALSE) | E104: =HLOOKUP(E$91,'Historical Data'!231:244,14,FALSE) | F104: =HLOOKUP(F$91,'Historical Data'!231:244,14,FALSE) | G104: =HLOOKUP(G$91,'Historical Data'!231:244,14,FALSE) | H104: =HLOOKUP(H$91,'Historical Data'!231:244,14,FALSE) | I104: =HLOOKUP(I$91,'Historical Data'!231:244,14,FALSE) | ... AE104: =HLOOKUP(AE$91,'Historical Data'!231:244,14,FALSE) | AF104: =AF19 | AG104: =ROUNDUP(AF104/3,0) | AH104: =SUMIF($B$5:$AE$5,AG104,B125:AE125)/AG104 | AI104: =AE104-AH104
A108: Cumlative Delinquencies | B108: =B91 | C108: =C91 | D108: =D91 | E108: =E91 | F108: =F91 | G108: =G91 | H108: =H91 | I108: =I91 | ... AE108: =AE91
A109: =A92 | B109: =B92+C109 | C109: =C92+D109 | D109: =D92+E109 | E109: =E92+F109 | F109: =F92+G109 | G109: =G92+H109 | H109: =H92+I109 | I109: =I92+J109 | ... AD109: =AD92+AE109 | AE109: =AE92
A110: =A93 | B110: =B93+C110 | C110: =C93+D110 | D110: =D93+E110 | E110: =E93+F110 | F110: =F93+G110 | G110: =G93+H110 | H110: =H93+I110 | I110: =I93+J110 | ... AD110: =AD93+AE110 | AE110: =AE93
A111: =A94 | B111: =B94+C111 | C111: =C94+D111 | D111: =D94+E111 | E111: =E94+F111 | F111: =F94+G111 | G111: =G94+H111 | H111: =H94+I111 | I111: =I94+J111 | ... AD111: =AD94+AE111 | AE111: =AE94
A112: =A95 | B112: =B95+C112 | C112: =C95+D112 | D112: =D95+E112 | E112: =E95+F112 | F112: =F95+G112 | G112: =G95+H112 | H112: =H95+I112 | I112: =I95+J112 | ... AD112: =AD95+AE112 | AE112: =AE95
A113: =A96 | B113: =B96+C113 | C113: =C96+D113 | D113: =D96+E113 | E113: =E96+F113 | F113: =F96+G113 | G113: =G96+H113 | H113: =H96+I113 | I113: =I96+J113 | ... AD113: =AD96+AE113 | AE113: =AE96
...

Sheet Cover-Vizo
A8: CECL Allowance Report
A9: Using SCALE Methodology
A10: =Cover!A13
A11: =Cover!A17
B12: The following analysis and all parts thereof (‘analysis’) are based upon information obtained by Vizo Financial Corporate Credit Union (Vizo Financial) from the credit union that is subject of this analysis and other sources that Vizo Financial believes to be reliable and utilized in models using methods and assumptions which Vizo Financial believes to be reasonable. However, actual performance compared to estimated performance of the subject credit union may be different and cannot be guaranteed. This analysis is for informational purposes only and is intended only for the use of the subject credit union. The analysis does not constitute either legal or tax advice. All reports are confidential.
B32: © 2025 TCT Risk Solutions

Sheet Executive Summary-Vizo
A1: CECL Allowances for Credit Losses (ACL) Calculation
A2: ="Prepared For "&'Cover-Vizo'!A10
A3: ="Quarter Ended "&TEXT('Cover-Vizo'!A11,"m/d/yyyy")
B7: Executive Summary
B9: Current ACL | C9: ='Calc tab'!AE6
B10: ='Scale Calculation-Vizo'!O27 | C10: ='Scale Calculation-Vizo'!S27
B11: ='Scale Calculation-Vizo'!O28 | C11: ='Scale Calculation-Vizo'!S28
B12: ='Scale Calculation-Vizo'!O29 | C12: ='Scale Calculation-Vizo'!S29
B13: ='Scale Calculation-Vizo'!O30 | C13: ='Scale Calculation-Vizo'!S30
B15: Prior ACL | C15: =OFFSET('Calc tab'!AE6,0,-1)
B16: Total Expected Losses on Loans | C16: =OFFSET('Historical Data'!AZ2,0,-1)
B17: Current ACL Balance | C17: =OFFSET('Historical Data'!AZ3,0,-1)
B18: Adjustment | C18: =OFFSET('Historical Data'!AZ4,0,-1)
B19: ACL/Total Loans | C19: =OFFSET('Historical Data'!AZ5,0,-1)
B21: Change
B22: Total Expected Losses on Loans | C22: =C10-C16
B23: Current ACL Balance | C23: =C11-C17
B24: Adjustment | C24: =C12-C18
B25: ACL/Total Loans | C25: =C13-C19

Sheet Scale Calculation-Vizo
A2: CECL Allowances for Credit Losses (ACL) Calculation
A3: ="Prepared For "&'Cover-Vizo'!A10
A4: ="Quarter Ended "&TEXT('Cover-Vizo'!A11,"m/d/yyyy")
A8: ='Scale Calculation'!C8 | C8: ='Scale Calculation'!E8 | D8: - | E8: ='Scale Calculation'!G8 | F8: = | G8: ='Scale Calculation'!I8 | I8: ='Scale Calculation'!K8 | J8: +/- | K8: ='Scale Calculation'!M8 | L8: = | M8: ='Scale Calculation'!O8 | O8: ='Scale Calculation'!Q8 | P8: +/- | Q8: ='Scale Calculation'!S8 | S8: ='Scale Calculation'!U8
A9: ='Scale Calculation'!C9 | C9: ='Calc tab'!AE7 | E9: =SUMIF(' Impaired Loans ASC 310-10'!$D$27:$D$412,A9,' Impaired Loans ASC 310-10'!$Q$27:$Q$412) | G9: =C9-E9 | I9: ='Calc tab'!AI58 | K9: ='Management Adjustment'!B4 | M9: =I9+K9 | O9: =G9*M9 | Q9: ='Env Factor by Pool-Vizo'!G13 | S9: =O9+(O9*Q9)
A10: ='Scale Calculation'!C10 | C10: ='Calc tab'!AE8 | E10: =SUMIF(' Impaired Loans ASC 310-10'!$D$27:$D$412,A10,' Impaired Loans ASC 310-10'!$Q$27:$Q$412) | G10: =C10-E10 | I10: ='Calc tab'!AI59 | K10: ='Management Adjustment'!B5 | M10: =I10+K10 | O10: ='Scale Calculation'!Q10 | Q10: ='Env Factor by Pool-Vizo'!G14 | S10: =O10+(O10*Q10)
A11: ='Scale Calculation'!C11 | C11: ='Calc tab'!AE9 | E11: =SUMIF(' Impaired Loans ASC 310-10'!$D$27:$D$412,A11,' Impaired Loans ASC 310-10'!$Q$27:$Q$412) | G11: =C11-E11 | I11: ='Calc tab'!AI60 | K11: ='Management Adjustment'!B6 | M11: =I11+K11 | O11: ='Scale Calculation'!Q11 | Q11: ='Env Factor by Pool-Vizo'!G15 | S11: =O11+(O11*Q11)
A12: ='Scale Calculation'!C12 | C12: ='Calc tab'!AE10 | E12: =SUMIF(' Impaired Loans ASC 310-10'!$D$27:$D$412,A12,' Impaired Loans ASC 310-10'!$Q$27:$Q$412) | G12: =C12-E12 | I12: ='Calc tab'!AI61 | K12: ='Management Adjustment'!B7 | M12: =I12+K12 | O12: ='Scale Calculation'!Q12 | Q12: ='Env Factor by Pool-Vizo'!G16 | S12: =O12+(O12*Q12)
A13: ='Scale Calculation'!C13 | C13: ='Calc tab'!AE11 | E13: =SUMIF(' Impaired Loans ASC 310-10'!$D$27:$D$412,A13,' Impaired Loans ASC 310-10'!$Q$27:$Q$412) | G13: =C13-E13 | I13: ='Calc tab'!AI62 | K13: ='Management Adjustment'!B8 | M13: =I13+K13 | O13: ='Scale Calculation'!Q13 | Q13: ='Env Factor by Pool-Vizo'!G17 | S13: =O13+(O13*Q13)
A14: ='Scale Calculation'!C14 | C14: ='Calc tab'!AE12 | E14: =SUMIF(' Impaired Loans ASC 310-10'!$D$27:$D$412,A14,' Impaired Loans ASC 310-10'!$Q$27:$Q$412) | G14: =C14-E14 | I14: ='Calc tab'!AI63 | K14: ='Management Adjustment'!B9 | M14: =I14+K14 | O14: ='Scale Calculation'!Q14 | Q14: ='Env Factor by Pool-Vizo'!G18 | S14: =O14+(O14*Q14)
A15: ='Scale Calculation'!C15 | C15: ='Calc tab'!AE13 | E15: =SUMIF(' Impaired Loans ASC 310-10'!$D$27:$D$412,A15,' Impaired Loans ASC 310-10'!$Q$27:$Q$412) | G15: =C15-E15 | I15: ='Calc tab'!AI64 | K15: ='Management Adjustment'!B10 | M15: =I15+K15 | O15: ='Scale Calculation'!Q15 | Q15: ='Env Factor by Pool-Vizo'!G19 | S15: =O15+(O15*Q15)
A16: ='Scale Calculation'!C16 | C16: ='Calc tab'!AE14 | E16: =SUMIF(' Impaired Loans ASC 310-10'!$D$27:$D$412,A16,' Impaired Loans ASC 310-10'!$Q$27:$Q$412) | G16: =C16-E16 | I16: ='Calc tab'!AI65 | K16: ='Management Adjustment'!B11 | M16: =I16+K16 | O16: ='Scale Calculation'!Q16 | Q16: ='Env Factor by Pool-Vizo'!G20 | S16: =O16+(O16*Q16)
A17: ='Scale Calculation'!C17 | C17: ='Calc tab'!AE15 | E17: =SUMIF(' Impaired Loans ASC 310-10'!$D$27:$D$412,A17,' Impaired Loans ASC 310-10'!$Q$27:$Q$412) | G17: =C17-E17 | I17: ='Calc tab'!AI66 | K17: ='Management Adjustment'!B12 | M17: =I17+K17 | O17: ='Scale Calculation'!Q17 | Q17: ='Env Factor by Pool-Vizo'!G21 | S17: =O17+(O17*Q17)
A18: ='Scale Calculation'!C18 | C18: ='Calc tab'!AE16 | E18: =SUMIF(' Impaired Loans ASC 310-10'!$D$27:$D$412,A18,' Impaired Loans ASC 310-10'!$Q$27:$Q$412) | G18: =C18-E18 | I18: ='Calc tab'!AI67 | K18: ='Management Adjustment'!B13 | M18: =I18+K18 | O18: ='Scale Calculation'!Q18 | Q18: ='Env Factor by Pool-Vizo'!G22 | S18: =O18+(O18*Q18)
A19: ='Scale Calculation'!C19 | C19: ='Calc tab'!AE17 | E19: =SUMIF(' Impaired Loans ASC 310-10'!$D$27:$D$412,A19,' Impaired Loans ASC 310-10'!$Q$27:$Q$412) | G19: =C19-E19 | I19: ='Calc tab'!AI68 | K19: ='Management Adjustment'!B14 | M19: =I19+K19 | O19: ='Scale Calculation'!Q19 | Q19: ='Env Factor by Pool-Vizo'!G23 | S19: =O19+(O19*Q19)
A20: ='Scale Calculation'!C20 | C20: ='Calc tab'!AE18 | E20: =SUMIF(' Impaired Loans ASC 310-10'!$D$27:$D$412,A20,' Impaired Loans ASC 310-10'!$Q$27:$Q$412) | G20: =C20-E20 | I20: ='Calc tab'!AI69 | K20: ='Management Adjustment'!B15 | M20: =I20+K20 | O20: ='Scale Calculation'!Q20 | Q20: ='Env Factor by Pool-Vizo'!G24 | S20: =O20+(O20*Q20)
A21: ='Scale Calculation'!C21 | C21: ='Calc tab'!AE19 | E21: =SUMIF(' Impaired Loans ASC 310-10'!$D$27:$D$412,A21,' Impaired Loans ASC 310-10'!$Q$27:$Q$412) | G21: =C21-E21 | I21: ='Calc tab'!AI70 | K21: ='Management Adjustment'!B16 | M21: =I21+K21 | O21: ='Scale Calculation'!Q21 | Q21: ='Env Factor by Pool-Vizo'!G25 | S21: =O21+(O21*Q21)
A23: ='Scale Calculation'!C23 | C23: =SUM(C9:C21) | G23: =SUM(G9:G21) | O23: =SUM(O9:$O$21) | S23: =SUM(S9:S21)
O25: Management Adjustment-Additional Environmental Factor | Q25: ='Historical Data'!AY159 | S25: =G23*Q25
O26: Expected Losses on Loans Assessed on Individual Basis | S26: =' Impaired Loans ASC 310-10'!P24
O27: Total Expected Losses on Loans | S27: =S23+S25+S26
O28: Current ACL Balance | S28: ='Historical Data'!AY177
O29: Adjustment | S29: =S27-S28
O30: ACL/Total Loans | S30: =IF(S27=0,0,S27/C23)
A32: Calculations:
A33: Loans Assessed on Pooled Basis = End of Period Loan Balance - Loans Assessed on Individual Basis
A34: Life of Loan Loss Rate = CECL ACL Lifetime Loss Rate +/- Management Adjustment
A35: Base CECL ACL = Net Loans Asses on Pooled Basis x Life of Loan Loss Rate
A36: Final CECL ACL = Base CECL ACL + (Base CECL ACL x Adjustment for Qualitative Factors)
A37: See Appendix for detailed descriptions.

Sheet  Impaired Loans-Vizo
A1: ="Prepared For "&'Cover-Vizo'!A10 | L1: =A1
A2: Impaired Loans Report Data Entry | L2: Impaired Loans Calculation
A4: =' Impaired Loans ASC 310-10'!A4 | B4: =' Impaired Loans ASC 310-10'!B4 | L4: =A4 | Q4: ="Sum of "&Q27 | R4: ="Sum of "&R27 | S4: ="Sum of "&S27
A5: =IF(' Impaired Loans ASC 310-10'!A5="","",' Impaired Loans ASC 310-10'!A5) | B5: =' Impaired Loans ASC 310-10'!B5 | L5: =IF(A5=0,"",A5) | Q5: =IF(A5=0,"",SUMIF($A$28:$A$412,L5,$Q$28:$Q$412)) | R5: =IF(A5=0,"",SUMIF($A$28:$A$412,L5,$R$28:$R$412)) | S5: =IF(A5=0,"",SUMIF($A$28:$A$412,L5,$S$28:$S$412))
A6: =IF(' Impaired Loans ASC 310-10'!A6="","",' Impaired Loans ASC 310-10'!A6) | B6: =' Impaired Loans ASC 310-10'!B6 | L6: =IF(A6=0,"",A6) | Q6: =IF(A6=0,"",SUMIF($A$28:$A$412,L6,$Q$28:$Q$412)) | R6: =IF(A6=0,"",SUMIF($A$28:$A$412,L6,$R$28:$R$412)) | S6: =IF(A6=0,"",SUMIF($A$28:$A$412,L6,$S$28:$S$412))
A7: =IF(' Impaired Loans ASC 310-10'!A7="","",' Impaired Loans ASC 310-10'!A7) | B7: =' Impaired Loans ASC 310-10'!B7 | L7: =IF(A7=0,"",A7) | Q7: =IF(A7=0,"",SUMIF($A$28:$A$412,L7,$Q$28:$Q$412)) | R7: =IF(A7=0,"",SUMIF($A$28:$A$412,L7,$R$28:$R$412)) | S7: =IF(A7=0,"",SUMIF($A$28:$A$412,L7,$S$28:$S$412))
A8: =IF(' Impaired Loans ASC 310-10'!A8="","",' Impaired Loans ASC 310-10'!A8) | B8: =' Impaired Loans ASC 310-10'!B8 | L8: =IF(A8=0,"",A8) | Q8: =IF(A8=0,"",SUMIF($A$28:$A$412,L8,$Q$28:$Q$412)) | R8: =IF(A8=0,"",SUMIF($A$28:$A$412,L8,$R$28:$R$412)) | S8: =IF(A8=0,"",SUMIF($A$28:$A$412,L8,$S$28:$S$412))
A9: =IF(' Impaired Loans ASC 310-10'!A9="","",' Impaired Loans ASC 310-10'!A9) | B9: =' Impaired Loans ASC 310-10'!B9 | L9: =IF(A9=0,"",A9) | Q9: =IF(A9=0,"",SUMIF($A$28:$A$412,L9,$Q$28:$Q$412)) | R9: =IF(A9=0,"",SUMIF($A$28:$A$412,L9,$R$28:$R$412)) | S9: =IF(A9=0,"",SUMIF($A$28:$A$412,L9,$S$28:$S$412))
A10: =IF(' Impaired Loans ASC 310-10'!A10="","",' Impaired Loans ASC 310-10'!A10) | B10: =' Impaired Loans ASC 310-10'!B10 | L10: =IF(A10=0,"",A10) | Q10: =IF(A10=0,"",SUMIF($A$28:$A$412,L10,$Q$28:$Q$412)) | R10: =IF(A10=0,"",SUMIF($A$28:$A$412,L10,$R$28:$R$412)) | S10: =IF(A10=0,"",SUMIF($A$28:$A$412,L10,$S$28:$S$412))
A11: =IF(' Impaired Loans ASC 310-10'!A11="","",' Impaired Loans ASC 310-10'!A11) | B11: =' Impaired Loans ASC 310-10'!B11 | L11: =IF(A11=0,"",A11) | Q11: =IF(A11=0,"",SUMIF($A$28:$A$412,L11,$Q$28:$Q$412)) | R11: =IF(A11=0,"",SUMIF($A$28:$A$412,L11,$R$28:$R$412)) | S11: =IF(A11=0,"",SUMIF($A$28:$A$412,L11,$S$28:$S$412))
A12: =IF(' Impaired Loans ASC 310-10'!A12="","",' Impaired Loans ASC 310-10'!A12) | B12: =' Impaired Loans ASC 310-10'!B12 | L12: =IF(A12=0,"",A12) | Q12: =IF(A12=0,"",SUMIF($A$28:$A$412,L12,$Q$28:$Q$412)) | R12: =IF(A12=0,"",SUMIF($A$28:$A$412,L12,$R$28:$R$412)) | S12: =IF(A12=0,"",SUMIF($A$28:$A$412,L12,$S$28:$S$412))
A13: =IF(' Impaired Loans ASC 310-10'!A13="","",' Impaired Loans ASC 310-10'!A13) | B13: =' Impaired Loans ASC 310-10'!B13 | L13: =IF(A13=0,"",A13) | Q13: =IF(A13=0,"",SUMIF($A$28:$A$412,L13,$Q$28:$Q$412)) | R13: =IF(A13=0,"",SUMIF($A$28:$A$412,L13,$R$28:$R$412)) | S13: =IF(A13=0,"",SUMIF($A$28:$A$412,L13,$S$28:$S$412))
A14: =IF(' Impaired Loans ASC 310-10'!A14="","",' Impaired Loans ASC 310-10'!A14) | B14: =' Impaired Loans ASC 310-10'!B14 | L14: =IF(A14=0,"",A14) | Q14: =IF(A14=0,"",SUMIF($A$28:$A$412,L14,$Q$28:$Q$412)) | R14: =IF(A14=0,"",SUMIF($A$28:$A$412,L14,$R$28:$R$412)) | S14: =IF(A14=0,"",SUMIF($A$28:$A$412,L14,$S$28:$S$412))
A15: =IF(' Impaired Loans ASC 310-10'!A15="","",' Impaired Loans ASC 310-10'!A15) | B15: =' Impaired Loans ASC 310-10'!B15 | L15: =IF(A15=0,"",A15) | Q15: =IF(A15=0,"",SUMIF($A$28:$A$412,L15,$Q$28:$Q$412)) | R15: =IF(A15=0,"",SUMIF($A$28:$A$412,L15,$R$28:$R$412)) | S15: =IF(A15=0,"",SUMIF($A$28:$A$412,L15,$S$28:$S$412))
A16: =IF(' Impaired Loans ASC 310-10'!A16="","",' Impaired Loans ASC 310-10'!A16) | B16: =' Impaired Loans ASC 310-10'!B16 | L16: =IF(A16=0,"",A16) | Q16: =IF(A16=0,"",SUMIF($A$28:$A$412,L16,$Q$28:$Q$412)) | R16: =IF(A16=0,"",SUMIF($A$28:$A$412,L16,$R$28:$R$412)) | S16: =IF(A16=0,"",SUMIF($A$28:$A$412,L16,$S$28:$S$412))
... A23: =IF(' Impaired Loans ASC 310-10'!A23="","",' Impaired Loans ASC 310-10'!A23) | B23: =' Impaired Loans ASC 310-10'!B23 | L23: =IF(A23=0,"",A23) | Q23: =IF(A23=0,"",SUMIF($A$28:$A$412,L23,$Q$28:$Q$412)) | R23: =IF(A23=0,"",SUMIF($A$28:$A$412,L23,$R$28:$R$412)) | S23: =IF(A23=0,"",SUMIF($A$28:$A$412,L23,$S$28:$S$412))
L24: Total | Q24: =SUM(Q5:Q10) | R24: =SUM(R5:R10) | S24: =SUM(S5:S10)
A27: =' Impaired Loans ASC 310-10'!A27 | B27: =' Impaired Loans ASC 310-10'!B27 | C27: =' Impaired Loans ASC 310-10'!C27 | D27: =' Impaired Loans ASC 310-10'!D27 | E27: =' Impaired Loans ASC 310-10'!E27 | F27: =' Impaired Loans ASC 310-10'!F27 | G27: =' Impaired Loans ASC 310-10'!G27 | H27: =' Impaired Loans ASC 310-10'!H27 | ... J27: =' Impaired Loans ASC 310-10'!J27 | L27: =A27 | M27: =' Impaired Loans ASC 310-10'!K27 | N27: =' Impaired Loans ASC 310-10'!L27 | O27: =' Impaired Loans ASC 310-10'!M27 | P27: =' Impaired Loans ASC 310-10'!O27 | Q27: =' Impaired Loans ASC 310-10'!N27 | R27: =' Impaired Loans ASC 310-10'!P27 | S27: =' Impaired Loans ASC 310-10'!Q27
A28: =IF(' Impaired Loans ASC 310-10'!A28="","",' Impaired Loans ASC 310-10'!A28) | B28: =IF(' Impaired Loans ASC 310-10'!B28="","",' Impaired Loans ASC 310-10'!B28) | C28: =IF(' Impaired Loans ASC 310-10'!C28="","",' Impaired Loans ASC 310-10'!C28) | D28: =IF(' Impaired Loans ASC 310-10'!D28="","",' Impaired Loans ASC 310-10'!D28) | E28: =IF(' Impaired Loans ASC 310-10'!E28="","",' Impaired Loans ASC 310-10'!E28) | F28: =IF(' Impaired Loans ASC 310-10'!F28="","",' Impaired Loans ASC 310-10'!F28) | G28: =IF(' Impaired Loans ASC 310-10'!G28="","",' Impaired Loans ASC 310-10'!G28) | H28: =IF(' Impaired Loans ASC 310-10'!H28="","",' Impaired Loans ASC 310-10'!H28) | ... J28: =IF(' Impaired Loans ASC 310-10'!J28="","",' Impaired Loans ASC 310-10'!J28) | L28: =A28 | M28: =IF(' Impaired Loans ASC 310-10'!A28="","",' Impaired Loans ASC 310-10'!K28) | N28: =IF(' Impaired Loans ASC 310-10'!A28="","",' Impaired Loans ASC 310-10'!L28) | O28: =IF(' Impaired Loans ASC 310-10'!A28="","",' Impaired Loans ASC 310-10'!M28) | P28: =IF(' Impaired Loans ASC 310-10'!A28="","",' Impaired Loans ASC 310-10'!O28) | Q28: =IF(' Impaired Loans ASC 310-10'!A28="","",' Impaired Loans ASC 310-10'!N28) | R28: =IF(' Impaired Loans ASC 310-10'!A28="","",' Impaired Loans ASC 310-10'!P28) | S28: =IF(' Impaired Loans ASC 310-10'!A28="","",' Impaired Loans ASC 310-10'!Q28)
A29: =IF(' Impaired Loans ASC 310-10'!A29="","",' Impaired Loans ASC 310-10'!A29) | B29: =IF(' Impaired Loans ASC 310-10'!B29="","",' Impaired Loans ASC 310-10'!B29) | C29: =IF(' Impaired Loans ASC 310-10'!C29="","",' Impaired Loans ASC 310-10'!C29) | D29: =IF(' Impaired Loans ASC 310-10'!D29="","",' Impaired Loans ASC 310-10'!D29) | E29: =IF(' Impaired Loans ASC 310-10'!E29="","",' Impaired Loans ASC 310-10'!E29) | F29: =IF(' Impaired Loans ASC 310-10'!F29="","",' Impaired Loans ASC 310-10'!F29) | G29: =IF(' Impaired Loans ASC 310-10'!G29="","",' Impaired Loans ASC 310-10'!G29) | H29: =IF(' Impaired Loans ASC 310-10'!H29="","",' Impaired Loans ASC 310-10'!H29) | ... J29: =IF(' Impaired Loans ASC 310-10'!J29="","",' Impaired Loans ASC 310-10'!J29) | L29: =A29 | M29: =IF(' Impaired Loans ASC 310-10'!A29="","",' Impaired Loans ASC 310-10'!K29) | N29: =IF(' Impaired Loans ASC 310-10'!A29="","",' Impaired Loans ASC 310-10'!L29) | O29: =IF(' Impaired Loans ASC 310-10'!A29="","",' Impaired Loans ASC 310-10'!M29) | P29: =IF(' Impaired Loans ASC 310-10'!A29="","",' Impaired Loans ASC 310-10'!O29) | Q29: =IF(' Impaired Loans ASC 310-10'!A29="","",' Impaired Loans ASC 310-10'!N29) | R29: =IF(' Impaired Loans ASC 310-10'!A29="","",' Impaired Loans ASC 310-10'!P29) | S29: =IF(' Impaired Loans ASC 310-10'!A29="","",' Impaired Loans ASC 310-10'!Q29)
A30: =IF(' Impaired Loans ASC 310-10'!A30="","",' Impaired Loans ASC 310-10'!A30) | B30: =IF(' Impaired Loans ASC 310-10'!B30="","",' Impaired Loans ASC 310-10'!B30) | C30: =IF(' Impaired Loans ASC 310-10'!C30="","",' Impaired Loans ASC 310-10'!C30) | D30: =IF(' Impaired Loans ASC 310-10'!D30="","",' Impaired Loans ASC 310-10'!D30) | E30: =IF(' Impaired Loans ASC 310-10'!E30="","",' Impaired Loans ASC 310-10'!E30) | F30: =IF(' Impaired Loans ASC 310-10'!F30="","",' Impaired Loans ASC 310-10'!F30) | G30: =IF(' Impaired Loans ASC 310-10'!G30="","",' Impaired Loans ASC 310-10'!G30) | H30: =IF(' Impaired Loans ASC 310-10'!H30="","",' Impaired Loans ASC 310-10'!H30) | ... J30: =IF(' Impaired Loans ASC 310-10'!J30="","",' Impaired Loans ASC 310-10'!J30) | L30: =A30 | M30: =IF(' Impaired Loans ASC 310-10'!A30="","",' Impaired Loans ASC 310-10'!K30) | N30: =IF(' Impaired Loans ASC 310-10'!A30="","",' Impaired Loans ASC 310-10'!L30) | O30: =IF(' Impaired Loans ASC 310-10'!A30="","",' Impaired Loans ASC 310-10'!M30) | P30: =IF(' Impaired Loans ASC 310-10'!A30="","",' Impaired Loans ASC 310-10'!O30) | Q30: =IF(' Impaired Loans ASC 310-10'!A30="","",' Impaired Loans ASC 310-10'!N30) | R30: =IF(' Impaired Loans ASC 310-10'!A30="","",' Impaired Loans ASC 310-10'!P30) | S30: =IF(' Impaired Loans ASC 310-10'!A30="","",' Impaired Loans ASC 310-10'!Q30)
A31: =IF(' Impaired Loans ASC 310-10'!A31="","",' Impaired Loans ASC 310-10'!A31) | B31: =IF(' Impaired Loans ASC 310-10'!B31="","",' Impaired Loans ASC 310-10'!B31) | C31: =IF(' Impaired Loans ASC 310-10'!C31="","",' Impaired Loans ASC 310-10'!C31) | D31: =IF(' Impaired Loans ASC 310-10'!D31="","",' Impaired Loans ASC 310-10'!D31) | E31: =IF(' Impaired Loans ASC 310-10'!E31="","",' Impaired Loans ASC 310-10'!E31) | F31: =IF(' Impaired Loans ASC 310-10'!F31="","",' Impaired Loans ASC 310-10'!F31) | G31: =IF(' Impaired Loans ASC 310-10'!G31="","",' Impaired Loans ASC 310-10'!G31) | H31: =IF(' Impaired Loans ASC 310-10'!H31="","",' Impaired Loans ASC 310-10'!H31) | ... J31: =IF(' Impaired Loans ASC 310-10'!J31="","",' Impaired Loans ASC 310-10'!J31) | L31: =A31 | M31: =IF(' Impaired Loans ASC 310-10'!A31="","",' Impaired Loans ASC 310-10'!K31) | N31: =IF(' Impaired Loans ASC 310-10'!A31="","",' Impaired Loans ASC 310-10'!L31) | O31: =IF(' Impaired Loans ASC 310-10'!A31="","",' Impaired Loans ASC 310-10'!M31) | P31: =IF(' Impaired Loans ASC 310-10'!A31="","",' Impaired Loans ASC 310-10'!O31) | Q31: =IF(' Impaired Loans ASC 310-10'!A31="","",' Impaired Loans ASC 310-10'!N31) | R31: =IF(' Impaired Loans ASC 310-10'!A31="","",' Impaired Loans ASC 310-10'!P31) | S31: =IF(' Impaired Loans ASC 310-10'!A31="","",' Impaired Loans ASC 310-10'!Q31)
A32: =IF(' Impaired Loans ASC 310-10'!A32="","",' Impaired Loans ASC 310-10'!A32) | B32: =IF(' Impaired Loans ASC 310-10'!B32="","",' Impaired Loans ASC 310-10'!B32) | C32: =IF(' Impaired Loans ASC 310-10'!C32="","",' Impaired Loans ASC 310-10'!C32) | D32: =IF(' Impaired Loans ASC 310-10'!D32="","",' Impaired Loans ASC 310-10'!D32) | E32: =IF(' Impaired Loans ASC 310-10'!E32="","",' Impaired Loans ASC 310-10'!E32) | F32: =IF(' Impaired Loans ASC 310-10'!F32="","",' Impaired Loans ASC 310-10'!F32) | G32: =IF(' Impaired Loans ASC 310-10'!G32="","",' Impaired Loans ASC 310-10'!G32) | H32: =IF(' Impaired Loans ASC 310-10'!H32="","",' Impaired Loans ASC 310-10'!H32) | ... J32: =IF(' Impaired Loans ASC 310-10'!J32="","",' Impaired Loans ASC 310-10'!J32) | L32: =A32 | M32: =IF(' Impaired Loans ASC 310-10'!A32="","",' Impaired Loans ASC 310-10'!K32) | N32: =IF(' Impaired Loans ASC 310-10'!A32="","",' Impaired Loans ASC 310-10'!L32) | O32: =IF(' Impaired Loans ASC 310-10'!A32="","",' Impaired Loans ASC 310-10'!M32) | P32: =IF(' Impaired Loans ASC 310-10'!A32="","",' Impaired Loans ASC 310-10'!O32) | Q32: =IF(' Impaired Loans ASC 310-10'!A32="","",' Impaired Loans ASC 310-10'!N32) | R32: =IF(' Impaired Loans ASC 310-10'!A32="","",' Impaired Loans ASC 310-10'!P32) | S32: =IF(' Impaired Loans ASC 310-10'!A32="","",' Impaired Loans ASC 310-10'!Q32)
A33: =IF(' Impaired Loans ASC 310-10'!A33="","",' Impaired Loans ASC 310-10'!A33) | B33: =IF(' Impaired Loans ASC 310-10'!B33="","",' Impaired Loans ASC 310-10'!B33) | C33: =IF(' Impaired Loans ASC 310-10'!C33="","",' Impaired Loans ASC 310-10'!C33) | D33: =IF(' Impaired Loans ASC 310-10'!D33="","",' Impaired Loans ASC 310-10'!D33) | E33: =IF(' Impaired Loans ASC 310-10'!E33="","",' Impaired Loans ASC 310-10'!E33) | F33: =IF(' Impaired Loans ASC 310-10'!F33="","",' Impaired Loans ASC 310-10'!F33) | G33: =IF(' Impaired Loans ASC 310-10'!G33="","",' Impaired Loans ASC 310-10'!G33) | H33: =IF(' Impaired Loans ASC 310-10'!H33="","",' Impaired Loans ASC 310-10'!H33) | ... J33: =IF(' Impaired Loans ASC 310-10'!J33="","",' Impaired Loans ASC 310-10'!J33) | L33: =A33 | M33: =IF(' Impaired Loans ASC 310-10'!A33="","",' Impaired Loans ASC 310-10'!K33) | N33: =IF(' Impaired Loans ASC 310-10'!A33="","",' Impaired Loans ASC 310-10'!L33) | O33: =IF(' Impaired Loans ASC 310-10'!A33="","",' Impaired Loans ASC 310-10'!M33) | P33: =IF(' Impaired Loans ASC 310-10'!A33="","",' Impaired Loans ASC 310-10'!O33) | Q33: =IF(' Impaired Loans ASC 310-10'!A33="","",' Impaired Loans ASC 310-10'!N33) | R33: =IF(' Impaired Loans ASC 310-10'!A33="","",' Impaired Loans ASC 310-10'!P33) | S33: =IF(' Impaired Loans ASC 310-10'!A33="","",' Impaired Loans ASC 310-10'!Q33)
A34: =IF(' Impaired Loans ASC 310-10'!A34="","",' Impaired Loans ASC 310-10'!A34) | B34: =IF(' Impaired Loans ASC 310-10'!B34="","",' Impaired Loans ASC 310-10'!B34) | C34: =IF(' Impaired Loans ASC 310-10'!C34="","",' Impaired Loans ASC 310-10'!C34) | D34: =IF(' Impaired Loans ASC 310-10'!D34="","",' Impaired Loans ASC 310-10'!D34) | E34: =IF(' Impaired Loans ASC 310-10'!E34="","",' Impaired Loans ASC 310-10'!E34) | F34: =IF(' Impaired Loans ASC 310-10'!F34="","",' Impaired Loans ASC 310-10'!F34) | G34: =IF(' Impaired Loans ASC 310-10'!G34="","",' Impaired Loans ASC 310-10'!G34) | H34: =IF(' Impaired Loans ASC 310-10'!H34="","",' Impaired Loans ASC 310-10'!H34) | ... J34: =IF(' Impaired Loans ASC 310-10'!J34="","",' Impaired Loans ASC 310-10'!J34) | L34: =A34 | M34: =IF(' Impaired Loans ASC 310-10'!A34="","",' Impaired Loans ASC 310-10'!K34) | N34: =IF(' Impaired Loans ASC 310-10'!A34="","",' Impaired Loans ASC 310-10'!L34) | O34: =IF(' Impaired Loans ASC 310-10'!A34="","",' Impaired Loans ASC 310-10'!M34) | P34: =IF(' Impaired Loans ASC 310-10'!A34="","",' Impaired Loans ASC 310-10'!O34) | Q34: =IF(' Impaired Loans ASC 310-10'!A34="","",' Impaired Loans ASC 310-10'!N34) | R34: =IF(' Impaired Loans ASC 310-10'!A34="","",' Impaired Loans ASC 310-10'!P34) | S34: =IF(' Impaired Loans ASC 310-10'!A34="","",' Impaired Loans ASC 310-10'!Q34)
A35: =IF(' Impaired Loans ASC 310-10'!A35="","",' Impaired Loans ASC 310-10'!A35) | B35: =IF(' Impaired Loans ASC 310-10'!B35="","",' Impaired Loans ASC 310-10'!B35) | C35: =IF(' Impaired Loans ASC 310-10'!C35="","",' Impaired Loans ASC 310-10'!C35) | D35: =IF(' Impaired Loans ASC 310-10'!D35="","",' Impaired Loans ASC 310-10'!D35) | E35: =IF(' Impaired Loans ASC 310-10'!E35="","",' Impaired Loans ASC 310-10'!E35) | F35: =IF(' Impaired Loans ASC 310-10'!F35="","",' Impaired Loans ASC 310-10'!F35) | G35: =IF(' Impaired Loans ASC 310-10'!G35="","",' Impaired Loans ASC 310-10'!G35) | H35: =IF(' Impaired Loans ASC 310-10'!H35="","",' Impaired Loans ASC 310-10'!H35) | ... J35: =IF(' Impaired Loans ASC 310-10'!J35="","",' Impaired Loans ASC 310-10'!J35) | L35: =A35 | M35: =IF(' Impaired Loans ASC 310-10'!A35="","",' Impaired Loans ASC 310-10'!K35) | N35: =IF(' Impaired Loans ASC 310-10'!A35="","",' Impaired Loans ASC 310-10'!L35) | O35: =IF(' Impaired Loans ASC 310-10'!A35="","",' Impaired Loans ASC 310-10'!M35) | P35: =IF(' Impaired Loans ASC 310-10'!A35="","",' Impaired Loans ASC 310-10'!O35) | Q35: =IF(' Impaired Loans ASC 310-10'!A35="","",' Impaired Loans ASC 310-10'!N35) | R35: =IF(' Impaired Loans ASC 310-10'!A35="","",' Impaired Loans ASC 310-10'!P35) | S35: =IF(' Impaired Loans ASC 310-10'!A35="","",' Impaired Loans ASC 310-10'!Q35)
A36: =IF(' Impaired Loans ASC 310-10'!A36="","",' Impaired Loans ASC 310-10'!A36) | B36: =IF(' Impaired Loans ASC 310-10'!B36="","",' Impaired Loans ASC 310-10'!B36) | C36: =IF(' Impaired Loans ASC 310-10'!C36="","",' Impaired Loans ASC 310-10'!C36) | D36: =IF(' Impaired Loans ASC 310-10'!D36="","",' Impaired Loans ASC 310-10'!D36) | E36: =IF(' Impaired Loans ASC 310-10'!E36="","",' Impaired Loans ASC 310-10'!E36) | F36: =IF(' Impaired Loans ASC 310-10'!F36="","",' Impaired Loans ASC 310-10'!F36) | G36: =IF(' Impaired Loans ASC 310-10'!G36="","",' Impaired Loans ASC 310-10'!G36) | H36: =IF(' Impaired Loans ASC 310-10'!H36="","",' Impaired Loans ASC 310-10'!H36) | ... J36: =IF(' Impaired Loans ASC 310-10'!J36="","",' Impaired Loans ASC 310-10'!J36) | L36: =A36 | M36: =IF(' Impaired Loans ASC 310-10'!A36="","",' Impaired Loans ASC 310-10'!K36) | N36: =IF(' Impaired Loans ASC 310-10'!A36="","",' Impaired Loans ASC 310-10'!L36) | O36: =IF(' Impaired Loans ASC 310-10'!A36="","",' Impaired Loans ASC 310-10'!M36) | P36: =IF(' Impaired Loans ASC 310-10'!A36="","",' Impaired Loans ASC 310-10'!O36) | Q36: =IF(' Impaired Loans ASC 310-10'!A36="","",' Impaired Loans ASC 310-10'!N36) | R36: =IF(' Impaired Loans ASC 310-10'!A36="","",' Impaired Loans ASC 310-10'!P36) | S36: =IF(' Impaired Loans ASC 310-10'!A36="","",' Impaired Loans ASC 310-10'!Q36)
A37: =IF(' Impaired Loans ASC 310-10'!A37="","",' Impaired Loans ASC 310-10'!A37) | B37: =IF(' Impaired Loans ASC 310-10'!B37="","",' Impaired Loans ASC 310-10'!B37) | C37: =IF(' Impaired Loans ASC 310-10'!C37="","",' Impaired Loans ASC 310-10'!C37) | D37: =IF(' Impaired Loans ASC 310-10'!D37="","",' Impaired Loans ASC 310-10'!D37) | E37: =IF(' Impaired Loans ASC 310-10'!E37="","",' Impaired Loans ASC 310-10'!E37) | F37: =IF(' Impaired Loans ASC 310-10'!F37="","",' Impaired Loans ASC 310-10'!F37) | G37: =IF(' Impaired Loans ASC 310-10'!G37="","",' Impaired Loans ASC 310-10'!G37) | H37: =IF(' Impaired Loans ASC 310-10'!H37="","",' Impaired Loans ASC 310-10'!H37) | ... J37: =IF(' Impaired Loans ASC 310-10'!J37="","",' Impaired Loans ASC 310-10'!J37) | L37: =A37 | M37: =IF(' Impaired Loans ASC 310-10'!A37="","",' Impaired Loans ASC 310-10'!K37) | N37: =IF(' Impaired Loans ASC 310-10'!A37="","",' Impaired Loans ASC 310-10'!L37) | O37: =IF(' Impaired Loans ASC 310-10'!A37="","",' Impaired Loans ASC 310-10'!M37) | P37: =IF(' Impaired Loans ASC 310-10'!A37="","",' Impaired Loans ASC 310-10'!O37) | Q37: =IF(' Impaired Loans ASC 310-10'!A37="","",' Impaired Loans ASC 310-10'!N37) | R37: =IF(' Impaired Loans ASC 310-10'!A37="","",' Impaired Loans ASC 310-10'!P37) | S37: =IF(' Impaired Loans ASC 310-10'!A37="","",' Impaired Loans ASC 310-10'!Q37)
A38: =IF(' Impaired Loans ASC 310-10'!A38="","",' Impaired Loans ASC 310-10'!A38) | B38: =IF(' Impaired Loans ASC 310-10'!B38="","",' Impaired Loans ASC 310-10'!B38) | C38: =IF(' Impaired Loans ASC 310-10'!C38="","",' Impaired Loans ASC 310-10'!C38) | D38: =IF(' Impaired Loans ASC 310-10'!D38="","",' Impaired Loans ASC 310-10'!D38) | E38: =IF(' Impaired Loans ASC 310-10'!E38="","",' Impaired Loans ASC 310-10'!E38) | F38: =IF(' Impaired Loans ASC 310-10'!F38="","",' Impaired Loans ASC 310-10'!F38) | G38: =IF(' Impaired Loans ASC 310-10'!G38="","",' Impaired Loans ASC 310-10'!G38) | H38: =IF(' Impaired Loans ASC 310-10'!H38="","",' Impaired Loans ASC 310-10'!H38) | ... J38: =IF(' Impaired Loans ASC 310-10'!J38="","",' Impaired Loans ASC 310-10'!J38) | L38: =A38 | M38: =IF(' Impaired Loans ASC 310-10'!A38="","",' Impaired Loans ASC 310-10'!K38) | N38: =IF(' Impaired Loans ASC 310-10'!A38="","",' Impaired Loans ASC 310-10'!L38) | O38: =IF(' Impaired Loans ASC 310-10'!A38="","",' Impaired Loans ASC 310-10'!M38) | P38: =IF(' Impaired Loans ASC 310-10'!A38="","",' Impaired Loans ASC 310-10'!O38) | Q38: =IF(' Impaired Loans ASC 310-10'!A38="","",' Impaired Loans ASC 310-10'!N38) | R38: =IF(' Impaired Loans ASC 310-10'!A38="","",' Impaired Loans ASC 310-10'!P38) | S38: =IF(' Impaired Loans ASC 310-10'!A38="","",' Impaired Loans ASC 310-10'!Q38)
A39: =IF(' Impaired Loans ASC 310-10'!A39="","",' Impaired Loans ASC 310-10'!A39) | B39: =IF(' Impaired Loans ASC 310-10'!B39="","",' Impaired Loans ASC 310-10'!B39) | C39: =IF(' Impaired Loans ASC 310-10'!C39="","",' Impaired Loans ASC 310-10'!C39) | D39: =IF(' Impaired Loans ASC 310-10'!D39="","",' Impaired Loans ASC 310-10'!D39) | E39: =IF(' Impaired Loans ASC 310-10'!E39="","",' Impaired Loans ASC 310-10'!E39) | F39: =IF(' Impaired Loans ASC 310-10'!F39="","",' Impaired Loans ASC 310-10'!F39) | G39: =IF(' Impaired Loans ASC 310-10'!G39="","",' Impaired Loans ASC 310-10'!G39) | H39: =IF(' Impaired Loans ASC 310-10'!H39="","",' Impaired Loans ASC 310-10'!H39) | ... J39: =IF(' Impaired Loans ASC 310-10'!J39="","",' Impaired Loans ASC 310-10'!J39) | L39: =A39 | M39: =IF(' Impaired Loans ASC 310-10'!A39="","",' Impaired Loans ASC 310-10'!K39) | N39: =IF(' Impaired Loans ASC 310-10'!A39="","",' Impaired Loans ASC 310-10'!L39) | O39: =IF(' Impaired Loans ASC 310-10'!A39="","",' Impaired Loans ASC 310-10'!M39) | P39: =IF(' Impaired Loans ASC 310-10'!A39="","",' Impaired Loans ASC 310-10'!O39) | Q39: =IF(' Impaired Loans ASC 310-10'!A39="","",' Impaired Loans ASC 310-10'!N39) | R39: =IF(' Impaired Loans ASC 310-10'!A39="","",' Impaired Loans ASC 310-10'!P39) | S39: =IF(' Impaired Loans ASC 310-10'!A39="","",' Impaired Loans ASC 310-10'!Q39)
... A43: =IF(' Impaired Loans ASC 310-10'!A43="","",' Impaired Loans ASC 310-10'!A43) | B43: =IF(' Impaired Loans ASC 310-10'!B43="","",' Impaired Loans ASC 310-10'!B43) | C43: =IF(' Impaired Loans ASC 310-10'!C43="","",' Impaired Loans ASC 310-10'!C43) | D43: =IF(' Impaired Loans ASC 310-10'!D43="","",' Impaired Loans ASC 310-10'!D43) | E43: =IF(' Impaired Loans ASC 310-10'!E43="","",' Impaired Loans ASC 310-10'!E43) | F43: =IF(' Impaired Loans ASC 310-10'!F43="","",' Impaired Loans ASC 310-10'!F43) | G43: =IF(' Impaired Loans ASC 310-10'!G43="","",' Impaired Loans ASC 310-10'!G43) | H43: =IF(' Impaired Loans ASC 310-10'!H43="","",' Impaired Loans ASC 310-10'!H43) | ... J43: =IF(' Impaired Loans ASC 310-10'!J43="","",' Impaired Loans ASC 310-10'!J43) | L43: =A43 | M43: =IF(' Impaired Loans ASC 310-10'!A43="","",' Impaired Loans ASC 310-10'!K43) | N43: =IF(' Impaired Loans ASC 310-10'!A43="","",' Impaired Loans ASC 310-10'!L43) | O43: =IF(' Impaired Loans ASC 310-10'!A43="","",' Impaired Loans ASC 310-10'!M43) | P43: =IF(' Impaired Loans ASC 310-10'!A43="","",' Impaired Loans ASC 310-10'!O43) | Q43: =IF(' Impaired Loans ASC 310-10'!A43="","",' Impaired Loans ASC 310-10'!N43) | R43: =IF(' Impaired Loans ASC 310-10'!A43="","",' Impaired Loans ASC 310-10'!P43) | S43: =IF(' Impaired Loans ASC 310-10'!A43="","",' Impaired Loans ASC 310-10'!Q43)
A44: =IF(' Impaired Loans ASC 310-10'!A44="","",' Impaired Loans ASC 310-10'!A44) | B44: =IF(' Impaired Loans ASC 310-10'!B44="","",' Impaired Loans ASC 310-10'!B44) | C44: =IF(' Impaired Loans ASC 310-10'!C44="","",' Impaired Loans ASC 310-10'!C44) | D44: =IF(' Impaired Loans ASC 310-10'!D44="","",' Impaired Loans ASC 310-10'!D44) | E44: =IF(' Impaired Loans ASC 310-10'!E44="","",' Impaired Loans ASC 310-10'!E44) | F44: =IF(' Impaired Loans ASC 310-10'!F44="","",' Impaired Loans ASC 310-10'!F44) | G44: =IF(' Impaired Loans ASC 310-10'!G44="","",' Impaired Loans ASC 310-10'!G44) | H44: =IF(' Impaired Loans ASC 310-10'!H44="","",' Impaired Loans ASC 310-10'!H44) | ... J44: =IF(' Impaired Loans ASC 310-10'!J44="","",' Impaired Loans ASC 310-10'!J44) | L44: =IFERROR(A44," ") | M44: =IF(' Impaired Loans ASC 310-10'!A44="","",' Impaired Loans ASC 310-10'!K44) | N44: =IF(' Impaired Loans ASC 310-10'!A44="","",' Impaired Loans ASC 310-10'!L44) | O44: =IF(' Impaired Loans ASC 310-10'!A44="","",' Impaired Loans ASC 310-10'!M44) | P44: =IF(' Impaired Loans ASC 310-10'!A44="","",' Impaired Loans ASC 310-10'!O44) | Q44: =IF(' Impaired Loans ASC 310-10'!A44="","",' Impaired Loans ASC 310-10'!N44) | R44: =IF(' Impaired Loans ASC 310-10'!A44="","",' Impaired Loans ASC 310-10'!P44) | S44: =IF(' Impaired Loans ASC 310-10'!A44="","",' Impaired Loans ASC 310-10'!Q44)
A45: =IF(' Impaired Loans ASC 310-10'!A45="","",' Impaired Loans ASC 310-10'!A45) | B45: =IF(' Impaired Loans ASC 310-10'!B45="","",' Impaired Loans ASC 310-10'!B45) | C45: =IF(' Impaired Loans ASC 310-10'!C45="","",' Impaired Loans ASC 310-10'!C45) | D45: =IF(' Impaired Loans ASC 310-10'!D45="","",' Impaired Loans ASC 310-10'!D45) | E45: =IF(' Impaired Loans ASC 310-10'!E45="","",' Impaired Loans ASC 310-10'!E45) | F45: =IF(' Impaired Loans ASC 310-10'!F45="","",' Impaired Loans ASC 310-10'!F45) | G45: =IF(' Impaired Loans ASC 310-10'!G45="","",' Impaired Loans ASC 310-10'!G45) | H45: =IF(' Impaired Loans ASC 310-10'!H45="","",' Impaired Loans ASC 310-10'!H45) | ... J45: =IF(' Impaired Loans ASC 310-10'!J45="","",' Impaired Loans ASC 310-10'!J45) | L45: =IFERROR(A45,"") | M45: =IF(' Impaired Loans ASC 310-10'!A45="","",' Impaired Loans ASC 310-10'!K45) | N45: =IF(' Impaired Loans ASC 310-10'!A45="","",' Impaired Loans ASC 310-10'!L45) | O45: =IF(' Impaired Loans ASC 310-10'!A45="","",' Impaired Loans ASC 310-10'!M45) | P45: =IF(' Impaired Loans ASC 310-10'!A45="","",' Impaired Loans ASC 310-10'!O45) | Q45: =IF(' Impaired Loans ASC 310-10'!A45="","",' Impaired Loans ASC 310-10'!N45) | R45: =IF(' Impaired Loans ASC 310-10'!A45="","",' Impaired Loans ASC 310-10'!P45) | S45: =IF(' Impaired Loans ASC 310-10'!A45="","",' Impaired Loans ASC 310-10'!Q45)
A46: =IF(' Impaired Loans ASC 310-10'!A46="","",' Impaired Loans ASC 310-10'!A46) | B46: =IF(' Impaired Loans ASC 310-10'!B46="","",' Impaired Loans ASC 310-10'!B46) | C46: =IF(' Impaired Loans ASC 310-10'!C46="","",' Impaired Loans ASC 310-10'!C46) | D46: =IF(' Impaired Loans ASC 310-10'!D46="","",' Impaired Loans ASC 310-10'!D46) | E46: =IF(' Impaired Loans ASC 310-10'!E46="","",' Impaired Loans ASC 310-10'!E46) | F46: =IF(' Impaired Loans ASC 310-10'!F46="","",' Impaired Loans ASC 310-10'!F46) | G46: =IF(' Impaired Loans ASC 310-10'!G46="","",' Impaired Loans ASC 310-10'!G46) | H46: =IF(' Impaired Loans ASC 310-10'!H46="","",' Impaired Loans ASC 310-10'!H46) | ... J46: =IF(' Impaired Loans ASC 310-10'!J46="","",' Impaired Loans ASC 310-10'!J46) | L46: =IFERROR(A46,"") | M46: =IF(' Impaired Loans ASC 310-10'!A46="","",' Impaired Loans ASC 310-10'!K46) | N46: =IF(' Impaired Loans ASC 310-10'!A46="","",' Impaired Loans ASC 310-10'!L46) | O46: =IF(' Impaired Loans ASC 310-10'!A46="","",' Impaired Loans ASC 310-10'!M46) | P46: =IF(' Impaired Loans ASC 310-10'!A46="","",' Impaired Loans ASC 310-10'!O46) | Q46: =IF(' Impaired Loans ASC 310-10'!A46="","",' Impaired Loans ASC 310-10'!N46) | R46: =IF(' Impaired Loans ASC 310-10'!A46="","",' Impaired Loans ASC 310-10'!P46) | S46: =IF(' Impaired Loans ASC 310-10'!A46="","",' Impaired Loans ASC 310-10'!Q46)
A47: =IF(' Impaired Loans ASC 310-10'!A47="","",' Impaired Loans ASC 310-10'!A47) | B47: =IF(' Impaired Loans ASC 310-10'!B47="","",' Impaired Loans ASC 310-10'!B47) | C47: =IF(' Impaired Loans ASC 310-10'!C47="","",' Impaired Loans ASC 310-10'!C47) | D47: =IF(' Impaired Loans ASC 310-10'!D47="","",' Impaired Loans ASC 310-10'!D47) | E47: =IF(' Impaired Loans ASC 310-10'!E47="","",' Impaired Loans ASC 310-10'!E47) | F47: =IF(' Impaired Loans ASC 310-10'!F47="","",' Impaired Loans ASC 310-10'!F47) | G47: =IF(' Impaired Loans ASC 310-10'!G47="","",' Impaired Loans ASC 310-10'!G47) | H47: =IF(' Impaired Loans ASC 310-10'!H47="","",' Impaired Loans ASC 310-10'!H47) | ... J47: =IF(' Impaired Loans ASC 310-10'!J47="","",' Impaired Loans ASC 310-10'!J47) | L47: =IFERROR(A47,"") | M47: =IF(' Impaired Loans ASC 310-10'!A47="","",' Impaired Loans ASC 310-10'!K47) | N47: =IF(' Impaired Loans ASC 310-10'!A47="","",' Impaired Loans ASC 310-10'!L47) | O47: =IF(' Impaired Loans ASC 310-10'!A47="","",' Impaired Loans ASC 310-10'!M47) | P47: =IF(' Impaired Loans ASC 310-10'!A47="","",' Impaired Loans ASC 310-10'!O47) | Q47: =IF(' Impaired Loans ASC 310-10'!A47="","",' Impaired Loans ASC 310-10'!N47) | R47: =IF(' Impaired Loans ASC 310-10'!A47="","",' Impaired Loans ASC 310-10'!P47) | S47: =IF(' Impaired Loans ASC 310-10'!A47="","",' Impaired Loans ASC 310-10'!Q47)
A48: =IF(' Impaired Loans ASC 310-10'!A48="","",' Impaired Loans ASC 310-10'!A48) | B48: =IF(' Impaired Loans ASC 310-10'!B48="","",' Impaired Loans ASC 310-10'!B48) | C48: =IF(' Impaired Loans ASC 310-10'!C48="","",' Impaired Loans ASC 310-10'!C48) | D48: =IF(' Impaired Loans ASC 310-10'!D48="","",' Impaired Loans ASC 310-10'!D48) | E48: =IF(' Impaired Loans ASC 310-10'!E48="","",' Impaired Loans ASC 310-10'!E48) | F48: =IF(' Impaired Loans ASC 310-10'!F48="","",' Impaired Loans ASC 310-10'!F48) | G48: =IF(' Impaired Loans ASC 310-10'!G48="","",' Impaired Loans ASC 310-10'!G48) | H48: =IF(' Impaired Loans ASC 310-10'!H48="","",' Impaired Loans ASC 310-10'!H48) | ... J48: =IF(' Impaired Loans ASC 310-10'!J48="","",' Impaired Loans ASC 310-10'!J48) | L48: =IFERROR(A48,"") | M48: =IF(' Impaired Loans ASC 310-10'!A48="","",' Impaired Loans ASC 310-10'!K48) | N48: =IF(' Impaired Loans ASC 310-10'!A48="","",' Impaired Loans ASC 310-10'!L48) | O48: =IF(' Impaired Loans ASC 310-10'!A48="","",' Impaired Loans ASC 310-10'!M48) | P48: =IF(' Impaired Loans ASC 310-10'!A48="","",' Impaired Loans ASC 310-10'!O48) | Q48: =IF(' Impaired Loans ASC 310-10'!A48="","",' Impaired Loans ASC 310-10'!N48) | R48: =IF(' Impaired Loans ASC 310-10'!A48="","",' Impaired Loans ASC 310-10'!P48) | S48: =IF(' Impaired Loans ASC 310-10'!A48="","",' Impaired Loans ASC 310-10'!Q48)
A49: =IF(' Impaired Loans ASC 310-10'!A49="","",' Impaired Loans ASC 310-10'!A49) | B49: =IF(' Impaired Loans ASC 310-10'!B49="","",' Impaired Loans ASC 310-10'!B49) | C49: =IF(' Impaired Loans ASC 310-10'!C49="","",' Impaired Loans ASC 310-10'!C49) | D49: =IF(' Impaired Loans ASC 310-10'!D49="","",' Impaired Loans ASC 310-10'!D49) | E49: =IF(' Impaired Loans ASC 310-10'!E49="","",' Impaired Loans ASC 310-10'!E49) | F49: =IF(' Impaired Loans ASC 310-10'!F49="","",' Impaired Loans ASC 310-10'!F49) | G49: =IF(' Impaired Loans ASC 310-10'!G49="","",' Impaired Loans ASC 310-10'!G49) | H49: =IF(' Impaired Loans ASC 310-10'!H49="","",' Impaired Loans ASC 310-10'!H49) | ... J49: =IF(' Impaired Loans ASC 310-10'!J49="","",' Impaired Loans ASC 310-10'!J49) | L49: =IFERROR(A49,"") | M49: =IF(' Impaired Loans ASC 310-10'!A49="","",' Impaired Loans ASC 310-10'!K49) | N49: =IF(' Impaired Loans ASC 310-10'!A49="","",' Impaired Loans ASC 310-10'!L49) | O49: =IF(' Impaired Loans ASC 310-10'!A49="","",' Impaired Loans ASC 310-10'!M49) | P49: =IF(' Impaired Loans ASC 310-10'!A49="","",' Impaired Loans ASC 310-10'!O49) | Q49: =IF(' Impaired Loans ASC 310-10'!A49="","",' Impaired Loans ASC 310-10'!N49) | R49: =IF(' Impaired Loans ASC 310-10'!A49="","",' Impaired Loans ASC 310-10'!P49) | S49: =IF(' Impaired Loans ASC 310-10'!A49="","",' Impaired Loans ASC 310-10'!Q49)
A50: =IF(' Impaired Loans ASC 310-10'!A50="","",' Impaired Loans ASC 310-10'!A50) | B50: =IF(' Impaired Loans ASC 310-10'!B50="","",' Impaired Loans ASC 310-10'!B50) | C50: =IF(' Impaired Loans ASC 310-10'!C50="","",' Impaired Loans ASC 310-10'!C50) | D50: =IF(' Impaired Loans ASC 310-10'!D50="","",' Impaired Loans ASC 310-10'!D50) | E50: =IF(' Impaired Loans ASC 310-10'!E50="","",' Impaired Loans ASC 310-10'!E50) | F50: =IF(' Impaired Loans ASC 310-10'!F50="","",' Impaired Loans ASC 310-10'!F50) | G50: =IF(' Impaired Loans ASC 310-10'!G50="","",' Impaired Loans ASC 310-10'!G50) | H50: =IF(' Impaired Loans ASC 310-10'!H50="","",' Impaired Loans ASC 310-10'!H50) | ... J50: =IF(' Impaired Loans ASC 310-10'!J50="","",' Impaired Loans ASC 310-10'!J50) | L50: =IFERROR(A50,"") | M50: =IF(' Impaired Loans ASC 310-10'!A50="","",' Impaired Loans ASC 310-10'!K50) | N50: =IF(' Impaired Loans ASC 310-10'!A50="","",' Impaired Loans ASC 310-10'!L50) | O50: =IF(' Impaired Loans ASC 310-10'!A50="","",' Impaired Loans ASC 310-10'!M50) | P50: =IF(' Impaired Loans ASC 310-10'!A50="","",' Impaired Loans ASC 310-10'!O50) | Q50: =IF(' Impaired Loans ASC 310-10'!A50="","",' Impaired Loans ASC 310-10'!N50) | R50: =IF(' Impaired Loans ASC 310-10'!A50="","",' Impaired Loans ASC 310-10'!P50) | S50: =IF(' Impaired Loans ASC 310-10'!A50="","",' Impaired Loans ASC 310-10'!Q50)
A51: =IF(' Impaired Loans ASC 310-10'!A51="","",' Impaired Loans ASC 310-10'!A51) | B51: =IF(' Impaired Loans ASC 310-10'!B51="","",' Impaired Loans ASC 310-10'!B51) | C51: =IF(' Impaired Loans ASC 310-10'!C51="","",' Impaired Loans ASC 310-10'!C51) | D51: =IF(' Impaired Loans ASC 310-10'!D51="","",' Impaired Loans ASC 310-10'!D51) | E51: =IF(' Impaired Loans ASC 310-10'!E51="","",' Impaired Loans ASC 310-10'!E51) | F51: =IF(' Impaired Loans ASC 310-10'!F51="","",' Impaired Loans ASC 310-10'!F51) | G51: =IF(' Impaired Loans ASC 310-10'!G51="","",' Impaired Loans ASC 310-10'!G51) | H51: =IF(' Impaired Loans ASC 310-10'!H51="","",' Impaired Loans ASC 310-10'!H51) | ... J51: =IF(' Impaired Loans ASC 310-10'!J51="","",' Impaired Loans ASC 310-10'!J51) | L51: =IFERROR(A51,"") | M51: =IF(' Impaired Loans ASC 310-10'!A51="","",' Impaired Loans ASC 310-10'!K51) | N51: =IF(' Impaired Loans ASC 310-10'!A51="","",' Impaired Loans ASC 310-10'!L51) | O51: =IF(' Impaired Loans ASC 310-10'!A51="","",' Impaired Loans ASC 310-10'!M51) | P51: =IF(' Impaired Loans ASC 310-10'!A51="","",' Impaired Loans ASC 310-10'!O51) | Q51: =IF(' Impaired Loans ASC 310-10'!A51="","",' Impaired Loans ASC 310-10'!N51) | R51: =IF(' Impaired Loans ASC 310-10'!A51="","",' Impaired Loans ASC 310-10'!P51) | S51: =IF(' Impaired Loans ASC 310-10'!A51="","",' Impaired Loans ASC 310-10'!Q51)
A52: =IF(' Impaired Loans ASC 310-10'!A52="","",' Impaired Loans ASC 310-10'!A52) | B52: =IF(' Impaired Loans ASC 310-10'!B52="","",' Impaired Loans ASC 310-10'!B52) | C52: =IF(' Impaired Loans ASC 310-10'!C52="","",' Impaired Loans ASC 310-10'!C52) | D52: =IF(' Impaired Loans ASC 310-10'!D52="","",' Impaired Loans ASC 310-10'!D52) | E52: =IF(' Impaired Loans ASC 310-10'!E52="","",' Impaired Loans ASC 310-10'!E52) | F52: =IF(' Impaired Loans ASC 310-10'!F52="","",' Impaired Loans ASC 310-10'!F52) | G52: =IF(' Impaired Loans ASC 310-10'!G52="","",' Impaired Loans ASC 310-10'!G52) | H52: =IF(' Impaired Loans ASC 310-10'!H52="","",' Impaired Loans ASC 310-10'!H52) | ... J52: =IF(' Impaired Loans ASC 310-10'!J52="","",' Impaired Loans ASC 310-10'!J52) | L52: =IFERROR(A52,"") | M52: =IF(' Impaired Loans ASC 310-10'!A52="","",' Impaired Loans ASC 310-10'!K52) | N52: =IF(' Impaired Loans ASC 310-10'!A52="","",' Impaired Loans ASC 310-10'!L52) | O52: =IF(' Impaired Loans ASC 310-10'!A52="","",' Impaired Loans ASC 310-10'!M52) | P52: =IF(' Impaired Loans ASC 310-10'!A52="","",' Impaired Loans ASC 310-10'!O52) | Q52: =IF(' Impaired Loans ASC 310-10'!A52="","",' Impaired Loans ASC 310-10'!N52) | R52: =IF(' Impaired Loans ASC 310-10'!A52="","",' Impaired Loans ASC 310-10'!P52) | S52: =IF(' Impaired Loans ASC 310-10'!A52="","",' Impaired Loans ASC 310-10'!Q52)
A53: =IF(' Impaired Loans ASC 310-10'!A53="","",' Impaired Loans ASC 310-10'!A53) | B53: =IF(' Impaired Loans ASC 310-10'!B53="","",' Impaired Loans ASC 310-10'!B53) | C53: =IF(' Impaired Loans ASC 310-10'!C53="","",' Impaired Loans ASC 310-10'!C53) | D53: =IF(' Impaired Loans ASC 310-10'!D53="","",' Impaired Loans ASC 310-10'!D53) | E53: =IF(' Impaired Loans ASC 310-10'!E53="","",' Impaired Loans ASC 310-10'!E53) | F53: =IF(' Impaired Loans ASC 310-10'!F53="","",' Impaired Loans ASC 310-10'!F53) | G53: =IF(' Impaired Loans ASC 310-10'!G53="","",' Impaired Loans ASC 310-10'!G53) | H53: =IF(' Impaired Loans ASC 310-10'!H53="","",' Impaired Loans ASC 310-10'!H53) | ... J53: =IF(' Impaired Loans ASC 310-10'!J53="","",' Impaired Loans ASC 310-10'!J53) | L53: =IFERROR(A53,"") | M53: =IF(' Impaired Loans ASC 310-10'!A53="","",' Impaired Loans ASC 310-10'!K53) | N53: =IF(' Impaired Loans ASC 310-10'!A53="","",' Impaired Loans ASC 310-10'!L53) | O53: =IF(' Impaired Loans ASC 310-10'!A53="","",' Impaired Loans ASC 310-10'!M53) | P53: =IF(' Impaired Loans ASC 310-10'!A53="","",' Impaired Loans ASC 310-10'!O53) | Q53: =IF(' Impaired Loans ASC 310-10'!A53="","",' Impaired Loans ASC 310-10'!N53) | R53: =IF(' Impaired Loans ASC 310-10'!A53="","",' Impaired Loans ASC 310-10'!P53) | S53: =IF(' Impaired Loans ASC 310-10'!A53="","",' Impaired Loans ASC 310-10'!Q53)
A54: =IF(' Impaired Loans ASC 310-10'!A54="","",' Impaired Loans ASC 310-10'!A54) | B54: =IF(' Impaired Loans ASC 310-10'!B54="","",' Impaired Loans ASC 310-10'!B54) | C54: =IF(' Impaired Loans ASC 310-10'!C54="","",' Impaired Loans ASC 310-10'!C54) | D54: =IF(' Impaired Loans ASC 310-10'!D54="","",' Impaired Loans ASC 310-10'!D54) | E54: =IF(' Impaired Loans ASC 310-10'!E54="","",' Impaired Loans ASC 310-10'!E54) | F54: =IF(' Impaired Loans ASC 310-10'!F54="","",' Impaired Loans ASC 310-10'!F54) | G54: =IF(' Impaired Loans ASC 310-10'!G54="","",' Impaired Loans ASC 310-10'!G54) | H54: =IF(' Impaired Loans ASC 310-10'!H54="","",' Impaired Loans ASC 310-10'!H54) | ... J54: =IF(' Impaired Loans ASC 310-10'!J54="","",' Impaired Loans ASC 310-10'!J54) | L54: =IFERROR(A54,"") | M54: =IF(' Impaired Loans ASC 310-10'!A54="","",' Impaired Loans ASC 310-10'!K54) | N54: =IF(' Impaired Loans ASC 310-10'!A54="","",' Impaired Loans ASC 310-10'!L54) | O54: =IF(' Impaired Loans ASC 310-10'!A54="","",' Impaired Loans ASC 310-10'!M54) | P54: =IF(' Impaired Loans ASC 310-10'!A54="","",' Impaired Loans ASC 310-10'!O54) | Q54: =IF(' Impaired Loans ASC 310-10'!A54="","",' Impaired Loans ASC 310-10'!N54) | R54: =IF(' Impaired Loans ASC 310-10'!A54="","",' Impaired Loans ASC 310-10'!P54) | S54: =IF(' Impaired Loans ASC 310-10'!A54="","",' Impaired Loans ASC 310-10'!Q54)
A55: =IF(' Impaired Loans ASC 310-10'!A55="","",' Impaired Loans ASC 310-10'!A55) | B55: =IF(' Impaired Loans ASC 310-10'!B55="","",' Impaired Loans ASC 310-10'!B55) | C55: =IF(' Impaired Loans ASC 310-10'!C55="","",' Impaired Loans ASC 310-10'!C55) | D55: =IF(' Impaired Loans ASC 310-10'!D55="","",' Impaired Loans ASC 310-10'!D55) | E55: =IF(' Impaired Loans ASC 310-10'!E55="","",' Impaired Loans ASC 310-10'!E55) | F55: =IF(' Impaired Loans ASC 310-10'!F55="","",' Impaired Loans ASC 310-10'!F55) | G55: =IF(' Impaired Loans ASC 310-10'!G55="","",' Impaired Loans ASC 310-10'!G55) | H55: =IF(' Impaired Loans ASC 310-10'!H55="","",' Impaired Loans ASC 310-10'!H55) | ... J55: =IF(' Impaired Loans ASC 310-10'!J55="","",' Impaired Loans ASC 310-10'!J55) | L55: =IFERROR(A55,"") | M55: =IF(' Impaired Loans ASC 310-10'!A55="","",' Impaired Loans ASC 310-10'!K55) | N55: =IF(' Impaired Loans ASC 310-10'!A55="","",' Impaired Loans ASC 310-10'!L55) | O55: =IF(' Impaired Loans ASC 310-10'!A55="","",' Impaired Loans ASC 310-10'!M55) | P55: =IF(' Impaired Loans ASC 310-10'!A55="","",' Impaired Loans ASC 310-10'!O55) | Q55: =IF(' Impaired Loans ASC 310-10'!A55="","",' Impaired Loans ASC 310-10'!N55) | R55: =IF(' Impaired Loans ASC 310-10'!A55="","",' Impaired Loans ASC 310-10'!P55) | S55: =IF(' Impaired Loans ASC 310-10'!A55="","",' Impaired Loans ASC 310-10'!Q55)
A56: =IF(' Impaired Loans ASC 310-10'!A56="","",' Impaired Loans ASC 310-10'!A56) | B56: =IF(' Impaired Loans ASC 310-10'!B56="","",' Impaired Loans ASC 310-10'!B56) | C56: =IF(' Impaired Loans ASC 310-10'!C56="","",' Impaired Loans ASC 310-10'!C56) | D56: =IF(' Impaired Loans ASC 310-10'!D56="","",' Impaired Loans ASC 310-10'!D56) | E56: =IF(' Impaired Loans ASC 310-10'!E56="","",' Impaired Loans ASC 310-10'!E56) | F56: =IF(' Impaired Loans ASC 310-10'!F56="","",' Impaired Loans ASC 310-10'!F56) | G56: =IF(' Impaired Loans ASC 310-10'!G56="","",' Impaired Loans ASC 310-10'!G56) | H56: =IF(' Impaired Loans ASC 310-10'!H56="","",' Impaired Loans ASC 310-10'!H56) | ... J56: =IF(' Impaired Loans ASC 310-10'!J56="","",' Impaired Loans ASC 310-10'!J56) | L56: =IFERROR(A56,"") | M56: =IF(' Impaired Loans ASC 310-10'!A56="","",' Impaired Loans ASC 310-10'!K56) | N56: =IF(' Impaired Loans ASC 310-10'!A56="","",' Impaired Loans ASC 310-10'!L56) | O56: =IF(' Impaired Loans ASC 310-10'!A56="","",' Impaired Loans ASC 310-10'!M56) | P56: =IF(' Impaired Loans ASC 310-10'!A56="","",' Impaired Loans ASC 310-10'!O56) | Q56: =IF(' Impaired Loans ASC 310-10'!A56="","",' Impaired Loans ASC 310-10'!N56) | R56: =IF(' Impaired Loans ASC 310-10'!A56="","",' Impaired Loans ASC 310-10'!P56) | S56: =IF(' Impaired Loans ASC 310-10'!A56="","",' Impaired Loans ASC 310-10'!Q56)
... A412: =IF(' Impaired Loans ASC 310-10'!A412="","",' Impaired Loans ASC 310-10'!A412) | B412: =IF(' Impaired Loans ASC 310-10'!B412="","",' Impaired Loans ASC 310-10'!B412) | C412: =IF(' Impaired Loans ASC 310-10'!C412="","",' Impaired Loans ASC 310-10'!C412) | D412: =IF(' Impaired Loans ASC 310-10'!D412="","",' Impaired Loans ASC 310-10'!D412) | E412: =IF(' Impaired Loans ASC 310-10'!E412="","",' Impaired Loans ASC 310-10'!E412) | F412: =IF(' Impaired Loans ASC 310-10'!F412="","",' Impaired Loans ASC 310-10'!F412) | G412: =IF(' Impaired Loans ASC 310-10'!G412="","",' Impaired Loans ASC 310-10'!G412) | H412: =IF(' Impaired Loans ASC 310-10'!H412="","",' Impaired Loans ASC 310-10'!H412) | ... J412: =IF(' Impaired Loans ASC 310-10'!J412="","",' Impaired Loans ASC 310-10'!J412) | L412: =IFERROR(A412,"") | M412: =IF(' Impaired Loans ASC 310-10'!A412="","",' Impaired Loans ASC 310-10'!K412) | N412: =IF(' Impaired Loans ASC 310-10'!A412="","",' Impaired Loans ASC 310-10'!L412) | O412: =IF(' Impaired Loans ASC 310-10'!A412="","",' Impaired Loans ASC 310-10'!M412) | P412: =IF(' Impaired Loans ASC 310-10'!A412="","",' Impaired Loans ASC 310-10'!O412) | Q412: =IF(' Impaired Loans ASC 310-10'!A412="","",' Impaired Loans ASC 310-10'!N412) | R412: =IF(' Impaired Loans ASC 310-10'!A412="","",' Impaired Loans ASC 310-10'!P412) | S412: =IF(' Impaired Loans ASC 310-10'!A412="","",' Impaired Loans ASC 310-10'!Q412)

Sheet Historical Summary
A2: CECL Allowances for Credit Losses (ACL) Calculation
A3: ="Prepared For "&'Cover-Vizo'!A10
A4: ="Quarter Ended "&TEXT('Cover-Vizo'!A11,"m/d/yyyy")
A6: ='New Report Calc-Vizo'!A10 | B6: ='New Report Calc-Vizo'!AE10 | C6: ='New Report Calc-Vizo'!AF10 | D6: ='New Report Calc-Vizo'!AH10
A7: ='New Report Calc-Vizo'!A11 | B7: ='New Report Calc-Vizo'!AE11 | C7: ='New Report Calc-Vizo'!AF11 | D7: ='New Report Calc-Vizo'!AH11
A8: ='New Report Calc-Vizo'!A12 | B8: ='New Report Calc-Vizo'!AE12 | C8: ='New Report Calc-Vizo'!AF12 | D8: ='New Report Calc-Vizo'!AH12
A9: ='New Report Calc-Vizo'!A13 | B9: ='New Report Calc-Vizo'!AE13 | C9: ='New Report Calc-Vizo'!AF13 | D9: ='New Report Calc-Vizo'!AH13
A10: ='New Report Calc-Vizo'!A14 | B10: ='New Report Calc-Vizo'!AE14 | C10: ='New Report Calc-Vizo'!AF14 | D10: ='New Report Calc-Vizo'!AH14
A11: ='New Report Calc-Vizo'!A15 | B11: ='New Report Calc-Vizo'!AE15 | C11: ='New Report Calc-Vizo'!AF15 | D11: ='New Report Calc-Vizo'!AH15
A12: ='New Report Calc-Vizo'!A16 | B12: ='New Report Calc-Vizo'!AE16 | C12: ='New Report Calc-Vizo'!AF16 | D12: ='New Report Calc-Vizo'!AH16
A13: ='New Report Calc-Vizo'!A17 | B13: ='New Report Calc-Vizo'!AE17 | C13: ='New Report Calc-Vizo'!AF17 | D13: ='New Report Calc-Vizo'!AH17
A14: ='New Report Calc-Vizo'!A18 | B14: ='New Report Calc-Vizo'!AE18 | C14: ='New Report Calc-Vizo'!AF18 | D14: ='New Report Calc-Vizo'!AH18
A15: ='New Report Calc-Vizo'!A19 | B15: ='New Report Calc-Vizo'!AE19 | C15: ='New Report Calc-Vizo'!AF19 | D15: ='New Report Calc-Vizo'!AH19
A16: ='New Report Calc-Vizo'!A20 | B16: ='New Report Calc-Vizo'!AE20 | C16: ='New Report Calc-Vizo'!AF20 | D16: ='New Report Calc-Vizo'!AH20
A17: ='New Report Calc-Vizo'!A21 | B17: ='New Report Calc-Vizo'!AE21 | C17: ='New Report Calc-Vizo'!AF21 | D17: ='New Report Calc-Vizo'!AH21
... A19: ='New Report Calc-Vizo'!A23 | B19: ='New Report Calc-Vizo'!AE23 | C19: ='New Report Calc-Vizo'!AF23 | D19: ='New Report Calc-Vizo'!AH23
A20: ='New Report Calc-Vizo'!A24 | B20: ='New Report Calc-Vizo'!AE24
A23: ='New Report Calc-Vizo'!A44 | B23: ='New Report Calc-Vizo'!AE44 | C23: ='New Report Calc-Vizo'!AF44 | D23: ='New Report Calc-Vizo'!AH44 | E23: ='New Report Calc-Vizo'!AI44
A24: ='New Report Calc-Vizo'!A45 | B24: ='New Report Calc-Vizo'!AE45 | C24: ='New Report Calc-Vizo'!AF45 | D24: ='New Report Calc-Vizo'!AH45 | E24: ='New Report Calc-Vizo'!AI45
A25: ='New Report Calc-Vizo'!A46 | B25: ='New Report Calc-Vizo'!AE46 | C25: ='New Report Calc-Vizo'!AF46 | D25: ='New Report Calc-Vizo'!AH46 | E25: ='New Report Calc-Vizo'!AI46
A26: ='New Report Calc-Vizo'!A47 | B26: ='New Report Calc-Vizo'!AE47 | C26: ='New Report Calc-Vizo'!AF47 | D26: ='New Report Calc-Vizo'!AH47 | E26: ='New Report Calc-Vizo'!AI47
A27: ='New Report Calc-Vizo'!A48 | B27: ='New Report Calc-Vizo'!AE48 | C27: ='New Report Calc-Vizo'!AF48 | D27: ='New Report Calc-Vizo'!AH48 | E27: ='New Report Calc-Vizo'!AI48
A28: ='New Report Calc-Vizo'!A49 | B28: ='New Report Calc-Vizo'!AE49 | C28: ='New Report Calc-Vizo'!AF49 | D28: ='New Report Calc-Vizo'!AH49 | E28: ='New Report Calc-Vizo'!AI49
A29: ='New Report Calc-Vizo'!A50 | B29: ='New Report Calc-Vizo'!AE50 | C29: ='New Report Calc-Vizo'!AF50 | D29: ='New Report Calc-Vizo'!AH50 | E29: ='New Report Calc-Vizo'!AI50
A30: ='New Report Calc-Vizo'!A51 | B30: ='New Report Calc-Vizo'!AE51 | C30: ='New Report Calc-Vizo'!AF51 | D30: ='New Report Calc-Vizo'!AH51 | E30: ='New Report Calc-Vizo'!AI51
A31: ='New Report Calc-Vizo'!A52 | B31: ='New Report Calc-Vizo'!AE52 | C31: ='New Report Calc-Vizo'!AF52 | D31: ='New Report Calc-Vizo'!AH52 | E31: ='New Report Calc-Vizo'!AI52
A32: ='New Report Calc-Vizo'!A53 | B32: ='New Report Calc-Vizo'!AE53 | C32: ='New Report Calc-Vizo'!AF53 | D32: ='New Report Calc-Vizo'!AH53 | E32: ='New Report Calc-Vizo'!AI53
A33: ='New Report Calc-Vizo'!A54 | B33: ='New Report Calc-Vizo'!AE54 | C33: ='New Report Calc-Vizo'!AF54 | D33: ='New Report Calc-Vizo'!AH54 | E33: ='New Report Calc-Vizo'!AI54
A34: ='New Report Calc-Vizo'!A55 | B34: ='New Report Calc-Vizo'!AE55 | C34: ='New Report Calc-Vizo'!AF55 | D34: ='New Report Calc-Vizo'!AH55 | E34: ='New Report Calc-Vizo'!AI55
... A36: ='New Report Calc-Vizo'!A57 | B36: ='New Report Calc-Vizo'!AE57 | C36: ='New Report Calc-Vizo'!AF57 | D36: ='New Report Calc-Vizo'!AH57 | E36: ='New Report Calc-Vizo'!AI57
A37: ='New Report Calc-Vizo'!A58 | B37: ='New Report Calc-Vizo'!AE58
A40: ='New Report Calc-Vizo'!A95 | B40: ='New Report Calc-Vizo'!AE95 | C40: ='New Report Calc-Vizo'!AF95 | D40: ='New Report Calc-Vizo'!AH95 | E40: ='New Report Calc-Vizo'!AI95
A41: ='New Report Calc-Vizo'!A96 | B41: ='New Report Calc-Vizo'!AE96 | C41: ='New Report Calc-Vizo'!AF96 | D41: ='New Report Calc-Vizo'!AH96 | E41: ='New Report Calc-Vizo'!AI96
A42: ='New Report Calc-Vizo'!A97 | B42: ='New Report Calc-Vizo'!AE97 | C42: ='New Report Calc-Vizo'!AF97 | D42: ='New Report Calc-Vizo'!AH97 | E42: ='New Report Calc-Vizo'!AI97
A43: ='New Report Calc-Vizo'!A98 | B43: ='New Report Calc-Vizo'!AE98 | C43: ='New Report Calc-Vizo'!AF98 | D43: ='New Report Calc-Vizo'!AH98 | E43: ='New Report Calc-Vizo'!AI98
A44: ='New Report Calc-Vizo'!A99 | B44: ='New Report Calc-Vizo'!AE99 | C44: ='New Report Calc-Vizo'!AF99 | D44: ='New Report Calc-Vizo'!AH99 | E44: ='New Report Calc-Vizo'!AI99
A45: ='New Report Calc-Vizo'!A100 | B45: ='New Report Calc-Vizo'!AE100 | C45: ='New Report Calc-Vizo'!AF100 | D45: ='New Report Calc-Vizo'!AH100 | E45: ='New Report Calc-Vizo'!AI100
A46: ='New Report Calc-Vizo'!A101 | B46: ='New Report Calc-Vizo'!AE101 | C46: ='New Report Calc-Vizo'!AF101 | D46: ='New Report Calc-Vizo'!AH101 | E46: ='New Report Calc-Vizo'!AI101
A47: ='New Report Calc-Vizo'!A102 | B47: ='New Report Calc-Vizo'!AE102 | C47: ='New Report Calc-Vizo'!AF102 | D47: ='New Report Calc-Vizo'!AH102 | E47: ='New Report Calc-Vizo'!AI102
A48: ='New Report Calc-Vizo'!A103 | B48: ='New Report Calc-Vizo'!AE103 | C48: ='New Report Calc-Vizo'!AF103 | D48: ='New Report Calc-Vizo'!AH103 | E48: ='New Report Calc-Vizo'!AI103
A49: ='New Report Calc-Vizo'!A104 | B49: ='New Report Calc-Vizo'!AE104 | C49: ='New Report Calc-Vizo'!AF104 | D49: ='New Report Calc-Vizo'!AH104 | E49: ='New Report Calc-Vizo'!AI104
A50: ='New Report Calc-Vizo'!A105 | B50: ='New Report Calc-Vizo'!AE105 | C50: ='New Report Calc-Vizo'!AF105 | D50: ='New Report Calc-Vizo'!AH105 | E50: ='New Report Calc-Vizo'!AI105
A51: ='New Report Calc-Vizo'!A106 | B51: ='New Report Calc-Vizo'!AE106 | C51: ='New Report Calc-Vizo'!AF106 | D51: ='New Report Calc-Vizo'!AH106 | E51: ='New Report Calc-Vizo'!AI106
... A53: ='New Report Calc-Vizo'!A108 | B53: ='New Report Calc-Vizo'!AE108 | C53: ='New Report Calc-Vizo'!AF108 | D53: ='New Report Calc-Vizo'!AH108 | E53: ='New Report Calc-Vizo'!AI108

Sheet Env Factor by Pool-Vizo
B1: ="Prepared For "&'Cover-Vizo'!A10
B2: Environmental Factor for PLL
B3: ="Quarter Ended "&TEXT('Cover-Vizo'!A11,"m/d/yyyy")
B5: Economic Stress Index Calculation
B6: State | C6: Unemployment Rate | D6: Foreclosures per Person | E6: Bankruptcies | F6: Population
B7: ='Env Factor by Pool'!B7 | C7: ='Env Factor by Pool'!C7 | D7: ='Env Factor by Pool'!D7 | E7: ='Env Factor by Pool'!E7 | F7: ='Env Factor by Pool'!F7 | M7: what do the *s mean?, either can add to narrative or possibly remove?
B8: County | C8: Unemployment Rate | D8: Foreclosure % | E8: Bankruptcy % | F8: Economic Stress Index | M8: If all use the same economic stress, stress score and stress index, do they need to be listed at the portfolio segment or just in the top section?
B9: ='Env Factor by Pool'!B9 | C9: =C7 | D9: ='Env Factor by Pool'!E9 | E9: ='Env Factor by Pool'!D9 | F9: =SUM(C9:E9)
B12: Portfolio Segment | C12: Delinquency Variance from Ave. | D12: Delinquency Score | E12: Economic Stress Actual | F12: Economic Stress Score | G12: Environmental Factor
B13: ='Scale Calculation-Vizo'!A9 | C13: ='New Report Calc-Vizo'!AI96 | D13: =IF(C13>='Env Factor by Pool-Vizo'!$H$34,'Env Factor by Pool-Vizo'!$I$34,IF(C13>='Env Factor by Pool-Vizo'!$H$35,'Env Factor by Pool-Vizo'!$I$35,IF(C13>='Env Factor by Pool-Vizo'!$H$36,'Env Factor by Pool-Vizo'!$I$36,IF(C13>='Env Factor by Pool-Vizo'!$H$37,'Env Factor by Pool-Vizo'!$I$37,IF(C13>='Env Factor by Pool-Vizo'!$H$38,'Env Factor by Pool-Vizo'!$I$38,IF(C13>='Env Factor by Pool-Vizo'!$H$39,'Env Factor by Pool-Vizo'!$I$39,IF(C13>='Env Factor by Pool-Vizo'!$H$40,'Env Factor by Pool-Vizo'!$I$40,IF(C13>='Env Factor by Pool-Vizo'!$H$41,'Env Factor by Pool-Vizo'!$I$41,IF(C13>='Env Factor by Pool-Vizo'!$H$42,'Env Factor by Pool-Vizo'!$I$42,IF(C13>='Env Factor by Pool-Vizo'!$H$43,'Env Factor by Pool-Vizo'!$I$43,IF(C13>='Env Factor by Pool-Vizo'!$H$44,'Env Factor by Pool-Vizo'!$I$44,IF(C13>='Env Factor by Pool-Vizo'!$H$45,'Env Factor by Pool-Vizo'!$I$45,IF(C13>='Env Factor by Pool-Vizo'!$H$46,'Env Factor by Pool-Vizo'!$I$46,IF(C13>='Env Factor by Pool-Vizo'!$H$47,'Env Factor by Pool-Vizo'!$I$47,IF(C13>='Env Factor by Pool-Vizo'!$H$48,'Env Factor by Pool-Vizo'!$I$48,IF(C13>='Env Factor by Pool-Vizo'!$H$49,'Env Factor by Pool-Vizo'!$I$49,'Env Factor by Pool-Vizo'!$I$50)))))))))))))))) | E13: =$F$9 | F13: =IF(E13>='Env Factor by Pool-Vizo'!$J$34,'Env Factor by Pool-Vizo'!$E$89,IF(E13>='Env Factor by Pool-Vizo'!$J$35,'Env Factor by Pool-Vizo'!$E$90,IF(E13>='Env Factor by Pool-Vizo'!$J$36,'Env Factor by Pool-Vizo'!$E$91,IF(E13>='Env Factor by Pool-Vizo'!$J$37,'Env Factor by Pool-Vizo'!$E$92,IF(E13>='Env Factor by Pool-Vizo'!$J$38,'Env Factor by Pool-Vizo'!$E$93,IF(E13>='Env Factor by Pool-Vizo'!$J$39,'Env Factor by Pool-Vizo'!$E$94,IF(E13>='Env Factor by Pool-Vizo'!$J$40,'Env Factor by Pool-Vizo'!$E$95,IF(E13>='Env Factor by Pool-Vizo'!$J$41,'Env Factor by Pool-Vizo'!$E$96,IF(E13>='Env Factor by Pool-Vizo'!$J$42,'Env Factor by Pool-Vizo'!$E$97,IF(E13>='Env Factor by Pool-Vizo'!$J$43,'Env Factor by Pool-Vizo'!$E$98,IF(E13>='Env Factor by Pool-Vizo'!$J$44,'Env Factor by Pool-Vizo'!$E$99,IF(E13>='Env Factor by Pool-Vizo'!$J$45,'Env Factor by Pool-Vizo'!$E$100,IF(E13>='Env Factor by Pool-Vizo'!$J$46,'Env Factor by Pool-Vizo'!$E$101,IF(E13>='Env Factor by Pool-Vizo'!$J$47,'Env Factor by Pool-Vizo'!$E$102,IF(E13>='Env Factor by Pool-Vizo'!$J$48,'Env Factor by Pool-Vizo'!$E$103,IF(E13>='Env Factor by Pool-Vizo'!$J$49,'Env Factor by Pool-Vizo'!$E$104,IF(E13>='Env Factor by Pool-Vizo'!$J$50,'Env Factor by Pool-Vizo'!$E$105,'Envir Factor Ranges-Vizo'!$E$23))))))))))))))))) | G13: =D13+F13 | H13: Environmental Factor | I13: =G13
B14: ='Scale Calculation-Vizo'!A10 | C14: ='New Report Calc-Vizo'!$AI$97 | D14: =IF(C14>='Env Factor by Pool-Vizo'!$H$34,'Env Factor by Pool-Vizo'!$I$34,IF(C14>='Env Factor by Pool-Vizo'!$H$35,'Env Factor by Pool-Vizo'!$I$35,IF(C14>='Env Factor by Pool-Vizo'!$H$36,'Env Factor by Pool-Vizo'!$I$36,IF(C14>='Env Factor by Pool-Vizo'!$H$37,'Env Factor by Pool-Vizo'!$I$37,IF(C14>='Env Factor by Pool-Vizo'!$H$38,'Env Factor by Pool-Vizo'!$I$38,IF(C14>='Env Factor by Pool-Vizo'!$H$39,'Env Factor by Pool-Vizo'!$I$39,IF(C14>='Env Factor by Pool-Vizo'!$H$40,'Env Factor by Pool-Vizo'!$I$40,IF(C14>='Env Factor by Pool-Vizo'!$H$41,'Env Factor by Pool-Vizo'!$I$41,IF(C14>='Env Factor by Pool-Vizo'!$H$42,'Env Factor by Pool-Vizo'!$I$42,IF(C14>='Env Factor by Pool-Vizo'!$H$43,'Env Factor by Pool-Vizo'!$I$43,IF(C14>='Env Factor by Pool-Vizo'!$H$44,'Env Factor by Pool-Vizo'!$I$44,IF(C14>='Env Factor by Pool-Vizo'!$H$45,'Env Factor by Pool-Vizo'!$I$45,IF(C14>='Env Factor by Pool-Vizo'!$H$46,'Env Factor by Pool-Vizo'!$I$46,IF(C14>='Env Factor by Pool-Vizo'!$H$47,'Env Factor by Pool-Vizo'!$I$47,IF(C14>='Env Factor by Pool-Vizo'!$H$48,'Env Factor by Pool-Vizo'!$I$48,IF(C14>='Env Factor by Pool-Vizo'!$H$49,'Env Factor by Pool-Vizo'!$I$49,'Env Factor by Pool-Vizo'!$I$50)))))))))))))))) | E14: =$F$9 | F14: =IF(E14>='Env Factor by Pool-Vizo'!$J$34,'Env Factor by Pool-Vizo'!$E$89,IF(E14>='Env Factor by Pool-Vizo'!$J$35,'Env Factor by Pool-Vizo'!$E$90,IF(E14>='Env Factor by Pool-Vizo'!$J$36,'Env Factor by Pool-Vizo'!$E$91,IF(E14>='Env Factor by Pool-Vizo'!$J$37,'Env Factor by Pool-Vizo'!$E$92,IF(E14>='Env Factor by Pool-Vizo'!$J$38,'Env Factor by Pool-Vizo'!$E$93,IF(E14>='Env Factor by Pool-Vizo'!$J$39,'Env Factor by Pool-Vizo'!$E$94,IF(E14>='Env Factor by Pool-Vizo'!$J$40,'Env Factor by Pool-Vizo'!$E$95,IF(E14>='Env Factor by Pool-Vizo'!$J$41,'Env Factor by Pool-Vizo'!$E$96,IF(E14>='Env Factor by Pool-Vizo'!$J$42,'Env Factor by Pool-Vizo'!$E$97,IF(E14>='Env Factor by Pool-Vizo'!$J$43,'Env Factor by Pool-Vizo'!$E$98,IF(E14>='Env Factor by Pool-Vizo'!$J$44,'Env Factor by Pool-Vizo'!$E$99,IF(E14>='Env Factor by Pool-Vizo'!$J$45,'Env Factor by Pool-Vizo'!$E$100,'Env Factor by Pool-Vizo'!$E$101)))))))))))) | G14: =D14+F14 | H14: Environmental Factor | I14: =G14
B15: ='Scale Calculation-Vizo'!A11 | C15: ='New Report Calc-Vizo'!$AI$98 | D15: =IF(C15>='Env Factor by Pool-Vizo'!$H$34,'Env Factor by Pool-Vizo'!$I$34,IF(C15>='Env Factor by Pool-Vizo'!$H$35,'Env Factor by Pool-Vizo'!$I$35,IF(C15>='Env Factor by Pool-Vizo'!$H$36,'Env Factor by Pool-Vizo'!$I$36,IF(C15>='Env Factor by Pool-Vizo'!$H$37,'Env Factor by Pool-Vizo'!$I$37,IF(C15>='Env Factor by Pool-Vizo'!$H$38,'Env Factor by Pool-Vizo'!$I$38,IF(C15>='Env Factor by Pool-Vizo'!$H$39,'Env Factor by Pool-Vizo'!$I$39,IF(C15>='Env Factor by Pool-Vizo'!$H$40,'Env Factor by Pool-Vizo'!$I$40,IF(C15>='Env Factor by Pool-Vizo'!$H$41,'Env Factor by Pool-Vizo'!$I$41,IF(C15>='Env Factor by Pool-Vizo'!$H$42,'Env Factor by Pool-Vizo'!$I$42,IF(C15>='Env Factor by Pool-Vizo'!$H$43,'Env Factor by Pool-Vizo'!$I$43,IF(C15>='Env Factor by Pool-Vizo'!$H$44,'Env Factor by Pool-Vizo'!$I$44,IF(C15>='Env Factor by Pool-Vizo'!$H$45,'Env Factor by Pool-Vizo'!$I$45,IF(C15>='Env Factor by Pool-Vizo'!$H$46,'Env Factor by Pool-Vizo'!$I$46,IF(C15>='Env Factor by Pool-Vizo'!$H$47,'Env Factor by Pool-Vizo'!$I$47,IF(C15>='Env Factor by Pool-Vizo'!$H$48,'Env Factor by Pool-Vizo'!$I$48,IF(C15>='Env Factor by Pool-Vizo'!$H$49,'Env Factor by Pool-Vizo'!$I$49,'Env Factor by Pool-Vizo'!$I$50)))))))))))))))) | E15: =$F$9 | F15: =IF(E15>='Env Factor by Pool-Vizo'!$J$34,'Env Factor by Pool-Vizo'!$E$89,IF(E15>='Env Factor by Pool-Vizo'!$J$35,'Env Factor by Pool-Vizo'!$E$90,IF(E15>='Env Factor by Pool-Vizo'!$J$36,'Env Factor by Pool-Vizo'!$E$91,IF(E15>='Env Factor by Pool-Vizo'!$J$37,'Env Factor by Pool-Vizo'!$E$92,IF(E15>='Env Factor by Pool-Vizo'!$J$38,'Env Factor by Pool-Vizo'!$E$93,IF(E15>='Env Factor by Pool-Vizo'!$J$39,'Env Factor by Pool-Vizo'!$E$94,IF(E15>='Env Factor by Pool-Vizo'!$J$40,'Env Factor by Pool-Vizo'!$E$95,IF(E15>='Env Factor by Pool-Vizo'!$J$41,'Env Factor by Pool-Vizo'!$E$96,IF(E15>='Env Factor by Pool-Vizo'!$J$42,'Env Factor by Pool-Vizo'!$E$97,IF(E15>='Env Factor by Pool-Vizo'!$J$43,'Env Factor by Pool-Vizo'!$E$98,IF(E15>='Env Factor by Pool-Vizo'!$J$44,'Env Factor by Pool-Vizo'!$E$99,IF(E15>='Env Factor by Pool-Vizo'!$J$45,'Env Factor by Pool-Vizo'!$E$100,'Env Factor by Pool-Vizo'!$E$101)))))))))))) | G15: =D15+F15 | H15: Environmental Factor | I15: =G15
B16: ='Scale Calculation-Vizo'!A12 | C16: ='New Report Calc-Vizo'!$AI$99 | D16: =IF(C16>='Env Factor by Pool-Vizo'!$H$34,'Env Factor by Pool-Vizo'!$I$34,IF(C16>='Env Factor by Pool-Vizo'!$H$35,'Env Factor by Pool-Vizo'!$I$35,IF(C16>='Env Factor by Pool-Vizo'!$H$36,'Env Factor by Pool-Vizo'!$I$36,IF(C16>='Env Factor by Pool-Vizo'!$H$37,'Env Factor by Pool-Vizo'!$I$37,IF(C16>='Env Factor by Pool-Vizo'!$H$38,'Env Factor by Pool-Vizo'!$I$38,IF(C16>='Env Factor by Pool-Vizo'!$H$39,'Env Factor by Pool-Vizo'!$I$39,IF(C16>='Env Factor by Pool-Vizo'!$H$40,'Env Factor by Pool-Vizo'!$I$40,IF(C16>='Env Factor by Pool-Vizo'!$H$41,'Env Factor by Pool-Vizo'!$I$41,IF(C16>='Env Factor by Pool-Vizo'!$H$42,'Env Factor by Pool-Vizo'!$I$42,IF(C16>='Env Factor by Pool-Vizo'!$H$43,'Env Factor by Pool-Vizo'!$I$43,IF(C16>='Env Factor by Pool-Vizo'!$H$44,'Env Factor by Pool-Vizo'!$I$44,IF(C16>='Env Factor by Pool-Vizo'!$H$45,'Env Factor by Pool-Vizo'!$I$45,IF(C16>='Env Factor by Pool-Vizo'!$H$46,'Env Factor by Pool-Vizo'!$I$46,IF(C16>='Env Factor by Pool-Vizo'!$H$47,'Env Factor by Pool-Vizo'!$I$47,IF(C16>='Env Factor by Pool-Vizo'!$H$48,'Env Factor by Pool-Vizo'!$I$48,IF(C16>='Env Factor by Pool-Vizo'!$H$49,'Env Factor by Pool-Vizo'!$I$49,'Env Factor by Pool-Vizo'!$I$50)))))))))))))))) | E16: =$F$9 | F16: =IF(E16>='Env Factor by Pool-Vizo'!$J$34,'Env Factor by Pool-Vizo'!$E$89,IF(E16>='Env Factor by Pool-Vizo'!$J$35,'Env Factor by Pool-Vizo'!$E$90,IF(E16>='Env Factor by Pool-Vizo'!$J$36,'Env Factor by Pool-Vizo'!$E$91,IF(E16>='Env Factor by Pool-Vizo'!$J$37,'Env Factor by Pool-Vizo'!$E$92,IF(E16>='Env Factor by Pool-Vizo'!$J$38,'Env Factor by Pool-Vizo'!$E$93,IF(E16>='Env Factor by Pool-Vizo'!$J$39,'Env Factor by Pool-Vizo'!$E$94,IF(E16>='Env Factor by Pool-Vizo'!$J$40,'Env Factor by Pool-Vizo'!$E$95,IF(E16>='Env Factor by Pool-Vizo'!$J$41,'Env Factor by Pool-Vizo'!$E$96,IF(E16>='Env Factor by Pool-Vizo'!$J$42,'Env Factor by Pool-Vizo'!$E$97,IF(E16>='Env Factor by Pool-Vizo'!$J$43,'Env Factor by Pool-Vizo'!$E$98,IF(E16>='Env Factor by Pool-Vizo'!$J$44,'Env Factor by Pool-Vizo'!$E$99,IF(E16>='Env Factor by Pool-Vizo'!$J$45,'Env Factor by Pool-Vizo'!$E$100,'Env Factor by Pool-Vizo'!$E$101)))))))))))) | G16: =D16+F16 | H16: Environmental Factor | I16: =G16
B17: ='Scale Calculation-Vizo'!A13 | C17: ='New Report Calc-Vizo'!$AI$100 | D17: =IF(C17>='Env Factor by Pool-Vizo'!$H$34,'Env Factor by Pool-Vizo'!$I$34,IF(C17>='Env Factor by Pool-Vizo'!$H$35,'Env Factor by Pool-Vizo'!$I$35,IF(C17>='Env Factor by Pool-Vizo'!$H$36,'Env Factor by Pool-Vizo'!$I$36,IF(C17>='Env Factor by Pool-Vizo'!$H$37,'Env Factor by Pool-Vizo'!$I$37,IF(C17>='Env Factor by Pool-Vizo'!$H$38,'Env Factor by Pool-Vizo'!$I$38,IF(C17>='Env Factor by Pool-Vizo'!$H$39,'Env Factor by Pool-Vizo'!$I$39,IF(C17>='Env Factor by Pool-Vizo'!$H$40,'Env Factor by Pool-Vizo'!$I$40,IF(C17>='Env Factor by Pool-Vizo'!$H$41,'Env Factor by Pool-Vizo'!$I$41,IF(C17>='Env Factor by Pool-Vizo'!$H$42,'Env Factor by Pool-Vizo'!$I$42,IF(C17>='Env Factor by Pool-Vizo'!$H$43,'Env Factor by Pool-Vizo'!$I$43,IF(C17>='Env Factor by Pool-Vizo'!$H$44,'Env Factor by Pool-Vizo'!$I$44,IF(C17>='Env Factor by Pool-Vizo'!$H$45,'Env Factor by Pool-Vizo'!$I$45,IF(C17>='Env Factor by Pool-Vizo'!$H$46,'Env Factor by Pool-Vizo'!$I$46,IF(C17>='Env Factor by Pool-Vizo'!$H$47,'Env Factor by Pool-Vizo'!$I$47,IF(C17>='Env Factor by Pool-Vizo'!$H$48,'Env Factor by Pool-Vizo'!$I$48,IF(C17>='Env Factor by Pool-Vizo'!$H$49,'Env Factor by Pool-Vizo'!$I$49,'Env Factor by Pool-Vizo'!$I$50)))))))))))))))) | E17: =$F$9 | F17: =IF(E17>='Env Factor by Pool-Vizo'!$J$34,'Env Factor by Pool-Vizo'!$E$89,IF(E17>='Env Factor by Pool-Vizo'!$J$35,'Env Factor by Pool-Vizo'!$E$90,IF(E17>='Env Factor by Pool-Vizo'!$J$36,'Env Factor by Pool-Vizo'!$E$91,IF(E17>='Env Factor by Pool-Vizo'!$J$37,'Env Factor by Pool-Vizo'!$E$92,IF(E17>='Env Factor by Pool-Vizo'!$J$38,'Env Factor by Pool-Vizo'!$E$93,IF(E17>='Env Factor by Pool-Vizo'!$J$39,'Env Factor by Pool-Vizo'!$E$94,IF(E17>='Env Factor by Pool-Vizo'!$J$40,'Env Factor by Pool-Vizo'!$E$95,IF(E17>='Env Factor by Pool-Vizo'!$J$41,'Env Factor by Pool-Vizo'!$E$96,IF(E17>='Env Factor by Pool-Vizo'!$J$42,'Env Factor by Pool-Vizo'!$E$97,IF(E17>='Env Factor by Pool-Vizo'!$J$43,'Env Factor by Pool-Vizo'!$E$98,IF(E17>='Env Factor by Pool-Vizo'!$J$44,'Env Factor by Pool-Vizo'!$E$99,IF(E17>='Env Factor by Pool-Vizo'!$J$45,'Env Factor by Pool-Vizo'!$E$100,'Env Factor by Pool-Vizo'!$E$101)))))))))))) | G17: =D17+F17 | H17: Environmental Factor | I17: =G17
B18: ='Scale Calculation-Vizo'!A14 | C18: ='New Report Calc-Vizo'!$AI$101 | D18: =IF(C18>='Env Factor by Pool-Vizo'!$H$34,'Env Factor by Pool-Vizo'!$I$34,IF(C18>='Env Factor by Pool-Vizo'!$H$35,'Env Factor by Pool-Vizo'!$I$35,IF(C18>='Env Factor by Pool-Vizo'!$H$36,'Env Factor by Pool-Vizo'!$I$36,IF(C18>='Env Factor by Pool-Vizo'!$H$37,'Env Factor by Pool-Vizo'!$I$37,IF(C18>='Env Factor by Pool-Vizo'!$H$38,'Env Factor by Pool-Vizo'!$I$38,IF(C18>='Env Factor by Pool-Vizo'!$H$39,'Env Factor by Pool-Vizo'!$I$39,IF(C18>='Env Factor by Pool-Vizo'!$H$40,'Env Factor by Pool-Vizo'!$I$40,IF(C18>='Env Factor by Pool-Vizo'!$H$41,'Env Factor by Pool-Vizo'!$I$41,IF(C18>='Env Factor by Pool-Vizo'!$H$42,'Env Factor by Pool-Vizo'!$I$42,IF(C18>='Env Factor by Pool-Vizo'!$H$43,'Env Factor by Pool-Vizo'!$I$43,IF(C18>='Env Factor by Pool-Vizo'!$H$44,'Env Factor by Pool-Vizo'!$I$44,IF(C18>='Env Factor by Pool-Vizo'!$H$45,'Env Factor by Pool-Vizo'!$I$45,IF(C18>='Env Factor by Pool-Vizo'!$H$46,'Env Factor by Pool-Vizo'!$I$46,IF(C18>='Env Factor by Pool-Vizo'!$H$47,'Env Factor by Pool-Vizo'!$I$47,IF(C18>='Env Factor by Pool-Vizo'!$H$48,'Env Factor by Pool-Vizo'!$I$48,IF(C18>='Env Factor by Pool-Vizo'!$H$49,'Env Factor by Pool-Vizo'!$I$49,'Env Factor by Pool-Vizo'!$I$50)))))))))))))))) | E18: =$F$9 | F18: =IF(E18>='Env Factor by Pool-Vizo'!$J$34,'Env Factor by Pool-Vizo'!$E$89,IF(E18>='Env Factor by Pool-Vizo'!$J$35,'Env Factor by Pool-Vizo'!$E$90,IF(E18>='Env Factor by Pool-Vizo'!$J$36,'Env Factor by Pool-Vizo'!$E$91,IF(E18>='Env Factor by Pool-Vizo'!$J$37,'Env Factor by Pool-Vizo'!$E$92,IF(E18>='Env Factor by Pool-Vizo'!$J$38,'Env Factor by Pool-Vizo'!$E$93,IF(E18>='Env Factor by Pool-Vizo'!$J$39,'Env Factor by Pool-Vizo'!$E$94,IF(E18>='Env Factor by Pool-Vizo'!$J$40,'Env Factor by Pool-Vizo'!$E$95,IF(E18>='Env Factor by Pool-Vizo'!$J$41,'Env Factor by Pool-Vizo'!$E$96,IF(E18>='Env Factor by Pool-Vizo'!$J$42,'Env Factor by Pool-Vizo'!$E$97,IF(E18>='Env Factor by Pool-Vizo'!$J$43,'Env Factor by Pool-Vizo'!$E$98,IF(E18>='Env Factor by Pool-Vizo'!$J$44,'Env Factor by Pool-Vizo'!$E$99,IF(E18>='Env Factor by Pool-Vizo'!$J$45,'Env Factor by Pool-Vizo'!$E$100,'Env Factor by Pool-Vizo'!$E$101)))))))))))) | G18: =D18+F18 | H18: Environmental Factor | I18: =G18
B19: ='Scale Calculation-Vizo'!A15 | C19: ='New Report Calc-Vizo'!$AI$102 | D19: =IF(C19>='Env Factor by Pool-Vizo'!$H$34,'Env Factor by Pool-Vizo'!$I$34,IF(C19>='Env Factor by Pool-Vizo'!$H$35,'Env Factor by Pool-Vizo'!$I$35,IF(C19>='Env Factor by Pool-Vizo'!$H$36,'Env Factor by Pool-Vizo'!$I$36,IF(C19>='Env Factor by Pool-Vizo'!$H$37,'Env Factor by Pool-Vizo'!$I$37,IF(C19>='Env Factor by Pool-Vizo'!$H$38,'Env Factor by Pool-Vizo'!$I$38,IF(C19>='Env Factor by Pool-Vizo'!$H$39,'Env Factor by Pool-Vizo'!$I$39,IF(C19>='Env Factor by Pool-Vizo'!$H$40,'Env Factor by Pool-Vizo'!$I$40,IF(C19>='Env Factor by Pool-Vizo'!$H$41,'Env Factor by Pool-Vizo'!$I$41,IF(C19>='Env Factor by Pool-Vizo'!$H$42,'Env Factor by Pool-Vizo'!$I$42,IF(C19>='Env Factor by Pool-Vizo'!$H$43,'Env Factor by Pool-Vizo'!$I$43,IF(C19>='Env Factor by Pool-Vizo'!$H$44,'Env Factor by Pool-Vizo'!$I$44,IF(C19>='Env Factor by Pool-Vizo'!$H$45,'Env Factor by Pool-Vizo'!$I$45,IF(C19>='Env Factor by Pool-Vizo'!$H$46,'Env Factor by Pool-Vizo'!$I$46,IF(C19>='Env Factor by Pool-Vizo'!$H$47,'Env Factor by Pool-Vizo'!$I$47,IF(C19>='Env Factor by Pool-Vizo'!$H$48,'Env Factor by Pool-Vizo'!$I$48,IF(C19>='Env Factor by Pool-Vizo'!$H$49,'Env Factor by Pool-Vizo'!$I$49,'Env Factor by Pool-Vizo'!$I$50)))))))))))))))) | E19: =$F$9 | F19: =IF(E19>='Env Factor by Pool-Vizo'!$J$34,'Env Factor by Pool-Vizo'!$E$89,IF(E19>='Env Factor by Pool-Vizo'!$J$35,'Env Factor by Pool-Vizo'!$E$90,IF(E19>='Env Factor by Pool-Vizo'!$J$36,'Env Factor by Pool-Vizo'!$E$91,IF(E19>='Env Factor by Pool-Vizo'!$J$37,'Env Factor by Pool-Vizo'!$E$92,IF(E19>='Env Factor by Pool-Vizo'!$J$38,'Env Factor by Pool-Vizo'!$E$93,IF(E19>='Env Factor by Pool-Vizo'!$J$39,'Env Factor by Pool-Vizo'!$E$94,IF(E19>='Env Factor by Pool-Vizo'!$J$40,'Env Factor by Pool-Vizo'!$E$95,IF(E19>='Env Factor by Pool-Vizo'!$J$41,'Env Factor by Pool-Vizo'!$E$96,IF(E19>='Env Factor by Pool-Vizo'!$J$42,'Env Factor by Pool-Vizo'!$E$97,IF(E19>='Env Factor by Pool-Vizo'!$J$43,'Env Factor by Pool-Vizo'!$E$98,IF(E19>='Env Factor by Pool-Vizo'!$J$44,'Env Factor by Pool-Vizo'!$E$99,IF(E19>='Env Factor by Pool-Vizo'!$J$45,'Env Factor by Pool-Vizo'!$E$100,'Env Factor by Pool-Vizo'!$E$101)))))))))))) | G19: =D19+F19 | H19: Environmental Factor | I19: =G19
B20: ='Scale Calculation-Vizo'!A16 | C20: ='New Report Calc-Vizo'!$AI$103 | D20: =IF(C20>='Env Factor by Pool-Vizo'!$H$34,'Env Factor by Pool-Vizo'!$I$34,IF(C20>='Env Factor by Pool-Vizo'!$H$35,'Env Factor by Pool-Vizo'!$I$35,IF(C20>='Env Factor by Pool-Vizo'!$H$36,'Env Factor by Pool-Vizo'!$I$36,IF(C20>='Env Factor by Pool-Vizo'!$H$37,'Env Factor by Pool-Vizo'!$I$37,IF(C20>='Env Factor by Pool-Vizo'!$H$38,'Env Factor by Pool-Vizo'!$I$38,IF(C20>='Env Factor by Pool-Vizo'!$H$39,'Env Factor by Pool-Vizo'!$I$39,IF(C20>='Env Factor by Pool-Vizo'!$H$40,'Env Factor by Pool-Vizo'!$I$40,IF(C20>='Env Factor by Pool-Vizo'!$H$41,'Env Factor by Pool-Vizo'!$I$41,IF(C20>='Env Factor by Pool-Vizo'!$H$42,'Env Factor by Pool-Vizo'!$I$42,IF(C20>='Env Factor by Pool-Vizo'!$H$43,'Env Factor by Pool-Vizo'!$I$43,IF(C20>='Env Factor by Pool-Vizo'!$H$44,'Env Factor by Pool-Vizo'!$I$44,IF(C20>='Env Factor by Pool-Vizo'!$H$45,'Env Factor by Pool-Vizo'!$I$45,IF(C20>='Env Factor by Pool-Vizo'!$H$46,'Env Factor by Pool-Vizo'!$I$46,IF(C20>='Env Factor by Pool-Vizo'!$H$47,'Env Factor by Pool-Vizo'!$I$47,IF(C20>='Env Factor by Pool-Vizo'!$H$48,'Env Factor by Pool-Vizo'!$I$48,IF(C20>='Env Factor by Pool-Vizo'!$H$49,'Env Factor by Pool-Vizo'!$I$49,'Env Factor by Pool-Vizo'!$I$50)))))))))))))))) | E20: =$F$9 | F20: =IF(E20>='Env Factor by Pool-Vizo'!$J$34,'Env Factor by Pool-Vizo'!$E$89,IF(E20>='Env Factor by Pool-Vizo'!$J$35,'Env Factor by Pool-Vizo'!$E$90,IF(E20>='Env Factor by Pool-Vizo'!$J$36,'Env Factor by Pool-Vizo'!$E$91,IF(E20>='Env Factor by Pool-Vizo'!$J$37,'Env Factor by Pool-Vizo'!$E$92,IF(E20>='Env Factor by Pool-Vizo'!$J$38,'Env Factor by Pool-Vizo'!$E$93,IF(E20>='Env Factor by Pool-Vizo'!$J$39,'Env Factor by Pool-Vizo'!$E$94,IF(E20>='Env Factor by Pool-Vizo'!$J$40,'Env Factor by Pool-Vizo'!$E$95,IF(E20>='Env Factor by Pool-Vizo'!$J$41,'Env Factor by Pool-Vizo'!$E$96,IF(E20>='Env Factor by Pool-Vizo'!$J$42,'Env Factor by Pool-Vizo'!$E$97,IF(E20>='Env Factor by Pool-Vizo'!$J$43,'Env Factor by Pool-Vizo'!$E$98,IF(E20>='Env Factor by Pool-Vizo'!$J$44,'Env Factor by Pool-Vizo'!$E$99,IF(E20>='Env Factor by Pool-Vizo'!$J$45,'Env Factor by Pool-Vizo'!$E$100,'Env Factor by Pool-Vizo'!$E$101)))))))))))) | G20: =D20+F20 | H20: Environmental Factor | I20: =G20
B21: ='Scale Calculation-Vizo'!A17 | C21: ='New Report Calc-Vizo'!$AI$104 | D21: =IF(C21>='Env Factor by Pool-Vizo'!$H$34,'Env Factor by Pool-Vizo'!$I$34,IF(C21>='Env Factor by Pool-Vizo'!$H$35,'Env Factor by Pool-Vizo'!$I$35,IF(C21>='Env Factor by Pool-Vizo'!$H$36,'Env Factor by Pool-Vizo'!$I$36,IF(C21>='Env Factor by Pool-Vizo'!$H$37,'Env Factor by Pool-Vizo'!$I$37,IF(C21>='Env Factor by Pool-Vizo'!$H$38,'Env Factor by Pool-Vizo'!$I$38,IF(C21>='Env Factor by Pool-Vizo'!$H$39,'Env Factor by Pool-Vizo'!$I$39,IF(C21>='Env Factor by Pool-Vizo'!$H$40,'Env Factor by Pool-Vizo'!$I$40,IF(C21>='Env Factor by Pool-Vizo'!$H$41,'Env Factor by Pool-Vizo'!$I$41,IF(C21>='Env Factor by Pool-Vizo'!$H$42,'Env Factor by Pool-Vizo'!$I$42,IF(C21>='Env Factor by Pool-Vizo'!$H$43,'Env Factor by Pool-Vizo'!$I$43,IF(C21>='Env Factor by Pool-Vizo'!$H$44,'Env Factor by Pool-Vizo'!$I$44,IF(C21>='Env Factor by Pool-Vizo'!$H$45,'Env Factor by Pool-Vizo'!$I$45,IF(C21>='Env Factor by Pool-Vizo'!$H$46,'Env Factor by Pool-Vizo'!$I$46,IF(C21>='Env Factor by Pool-Vizo'!$H$47,'Env Factor by Pool-Vizo'!$I$47,IF(C21>='Env Factor by Pool-Vizo'!$H$48,'Env Factor by Pool-Vizo'!$I$48,IF(C21>='Env Factor by Pool-Vizo'!$H$49,'Env Factor by Pool-Vizo'!$I$49,'Env Factor by Pool-Vizo'!$I$50)))))))))))))))) | E21: =$F$9 | F21: =IF(E21>='Env Factor by Pool-Vizo'!$J$34,'Env Factor by Pool-Vizo'!$E$89,IF(E21>='Env Factor by Pool-Vizo'!$J$35,'Env Factor by Pool-Vizo'!$E$90,IF(E21>='Env Factor by Pool-Vizo'!$J$36,'Env Factor by Pool-Vizo'!$E$91,IF(E21>='Env Factor by Pool-Vizo'!$J$37,'Env Factor by Pool-Vizo'!$E$92,IF(E21>='Env Factor by Pool-Vizo'!$J$38,'Env Factor by Pool-Vizo'!$E$93,IF(E21>='Env Factor by Pool-Vizo'!$J$39,'Env Factor by Pool-Vizo'!$E$94,IF(E21>='Env Factor by Pool-Vizo'!$J$40,'Env Factor by Pool-Vizo'!$E$95,IF(E21>='Env Factor by Pool-Vizo'!$J$41,'Env Factor by Pool-Vizo'!$E$96,IF(E21>='Env Factor by Pool-Vizo'!$J$42,'Env Factor by Pool-Vizo'!$E$97,IF(E21>='Env Factor by Pool-Vizo'!$J$43,'Env Factor by Pool-Vizo'!$E$98,IF(E21>='Env Factor by Pool-Vizo'!$J$44,'Env Factor by Pool-Vizo'!$E$99,IF(E21>='Env Factor by Pool-Vizo'!$J$45,'Env Factor by Pool-Vizo'!$E$100,'Env Factor by Pool-Vizo'!$E$101)))))))))))) | G21: =D21+F21 | H21: Environmental Factor | I21: =G21
B22: ='Scale Calculation-Vizo'!A18 | C22: ='New Report Calc-Vizo'!$AI$105 | D22: =IF(C22>='Env Factor by Pool-Vizo'!$H$34,'Env Factor by Pool-Vizo'!$I$34,IF(C22>='Env Factor by Pool-Vizo'!$H$35,'Env Factor by Pool-Vizo'!$I$35,IF(C22>='Env Factor by Pool-Vizo'!$H$36,'Env Factor by Pool-Vizo'!$I$36,IF(C22>='Env Factor by Pool-Vizo'!$H$37,'Env Factor by Pool-Vizo'!$I$37,IF(C22>='Env Factor by Pool-Vizo'!$H$38,'Env Factor by Pool-Vizo'!$I$38,IF(C22>='Env Factor by Pool-Vizo'!$H$39,'Env Factor by Pool-Vizo'!$I$39,IF(C22>='Env Factor by Pool-Vizo'!$H$40,'Env Factor by Pool-Vizo'!$I$40,IF(C22>='Env Factor by Pool-Vizo'!$H$41,'Env Factor by Pool-Vizo'!$I$41,IF(C22>='Env Factor by Pool-Vizo'!$H$42,'Env Factor by Pool-Vizo'!$I$42,IF(C22>='Env Factor by Pool-Vizo'!$H$43,'Env Factor by Pool-Vizo'!$I$43,IF(C22>='Env Factor by Pool-Vizo'!$H$44,'Env Factor by Pool-Vizo'!$I$44,IF(C22>='Env Factor by Pool-Vizo'!$H$45,'Env Factor by Pool-Vizo'!$I$45,IF(C22>='Env Factor by Pool-Vizo'!$H$46,'Env Factor by Pool-Vizo'!$I$46,IF(C22>='Env Factor by Pool-Vizo'!$H$47,'Env Factor by Pool-Vizo'!$I$47,IF(C22>='Env Factor by Pool-Vizo'!$H$48,'Env Factor by Pool-Vizo'!$I$48,IF(C22>='Env Factor by Pool-Vizo'!$H$49,'Env Factor by Pool-Vizo'!$I$49,'Env Factor by Pool-Vizo'!$I$50)))))))))))))))) | E22: =$F$9 | F22: =IF(E22>='Env Factor by Pool-Vizo'!$J$34,'Env Factor by Pool-Vizo'!$E$89,IF(E22>='Env Factor by Pool-Vizo'!$J$35,'Env Factor by Pool-Vizo'!$E$90,IF(E22>='Env Factor by Pool-Vizo'!$J$36,'Env Factor by Pool-Vizo'!$E$91,IF(E22>='Env Factor by Pool-Vizo'!$J$37,'Env Factor by Pool-Vizo'!$E$92,IF(E22>='Env Factor by Pool-Vizo'!$J$38,'Env Factor by Pool-Vizo'!$E$93,IF(E22>='Env Factor by Pool-Vizo'!$J$39,'Env Factor by Pool-Vizo'!$E$94,IF(E22>='Env Factor by Pool-Vizo'!$J$40,'Env Factor by Pool-Vizo'!$E$95,IF(E22>='Env Factor by Pool-Vizo'!$J$41,'Env Factor by Pool-Vizo'!$E$96,IF(E22>='Env Factor by Pool-Vizo'!$J$42,'Env Factor by Pool-Vizo'!$E$97,IF(E22>='Env Factor by Pool-Vizo'!$J$43,'Env Factor by Pool-Vizo'!$E$98,IF(E22>='Env Factor by Pool-Vizo'!$J$44,'Env Factor by Pool-Vizo'!$E$99,IF(E22>='Env Factor by Pool-Vizo'!$J$45,'Env Factor by Pool-Vizo'!$E$100,'Env Factor by Pool-Vizo'!$E$101)))))))))))) | G22: =D22+F22 | H22: Environmental Factor | I22: =G22
B23: ='Scale Calculation-Vizo'!A19 | C23: ='New Report Calc-Vizo'!$AI$106 | D23: =IF(C23>='Env Factor by Pool-Vizo'!$H$34,'Env Factor by Pool-Vizo'!$I$34,IF(C23>='Env Factor by Pool-Vizo'!$H$35,'Env Factor by Pool-Vizo'!$I$35,IF(C23>='Env Factor by Pool-Vizo'!$H$36,'Env Factor by Pool-Vizo'!$I$36,IF(C23>='Env Factor by Pool-Vizo'!$H$37,'Env Factor by Pool-Vizo'!$I$37,IF(C23>='Env Factor by Pool-Vizo'!$H$38,'Env Factor by Pool-Vizo'!$I$38,IF(C23>='Env Factor by Pool-Vizo'!$H$39,'Env Factor by Pool-Vizo'!$I$39,IF(C23>='Env Factor by Pool-Vizo'!$H$40,'Env Factor by Pool-Vizo'!$I$40,IF(C23>='Env Factor by Pool-Vizo'!$H$41,'Env Factor by Pool-Vizo'!$I$41,IF(C23>='Env Factor by Pool-Vizo'!$H$42,'Env Factor by Pool-Vizo'!$I$42,IF(C23>='Env Factor by Pool-Vizo'!$H$43,'Env Factor by Pool-Vizo'!$I$43,IF(C23>='Env Factor by Pool-Vizo'!$H$44,'Env Factor by Pool-Vizo'!$I$44,IF(C23>='Env Factor by Pool-Vizo'!$H$45,'Env Factor by Pool-Vizo'!$I$45,IF(C23>='Env Factor by Pool-Vizo'!$H$46,'Env Factor by Pool-Vizo'!$I$46,IF(C23>='Env Factor by Pool-Vizo'!$H$47,'Env Factor by Pool-Vizo'!$I$47,IF(C23>='Env Factor by Pool-Vizo'!$H$48,'Env Factor by Pool-Vizo'!$I$48,IF(C23>='Env Factor by Pool-Vizo'!$H$49,'Env Factor by Pool-Vizo'!$I$49,'Env Factor by Pool-Vizo'!$I$50)))))))))))))))) | E23: =$F$9 | F23: =IF(E23>='Env Factor by Pool-Vizo'!$J$34,'Env Factor by Pool-Vizo'!$E$89,IF(E23>='Env Factor by Pool-Vizo'!$J$35,'Env Factor by Pool-Vizo'!$E$90,IF(E23>='Env Factor by Pool-Vizo'!$J$36,'Env Factor by Pool-Vizo'!$E$91,IF(E23>='Env Factor by Pool-Vizo'!$J$37,'Env Factor by Pool-Vizo'!$E$92,IF(E23>='Env Factor by Pool-Vizo'!$J$38,'Env Factor by Pool-Vizo'!$E$93,IF(E23>='Env Factor by Pool-Vizo'!$J$39,'Env Factor by Pool-Vizo'!$E$94,IF(E23>='Env Factor by Pool-Vizo'!$J$40,'Env Factor by Pool-Vizo'!$E$95,IF(E23>='Env Factor by Pool-Vizo'!$J$41,'Env Factor by Pool-Vizo'!$E$96,IF(E23>='Env Factor by Pool-Vizo'!$J$42,'Env Factor by Pool-Vizo'!$E$97,IF(E23>='Env Factor by Pool-Vizo'!$J$43,'Env Factor by Pool-Vizo'!$E$98,IF(E23>='Env Factor by Pool-Vizo'!$J$44,'Env Factor by Pool-Vizo'!$E$99,IF(E23>='Env Factor by Pool-Vizo'!$J$45,'Env Factor by Pool-Vizo'!$E$100,'Env Factor by Pool-Vizo'!$E$101)))))))))))) | G23: =D23+F23 | H23: Environmental Factor | I23: =G23
B24: ='Scale Calculation-Vizo'!A20 | C24: ='New Report Calc-Vizo'!$AI$107 | D24: =IF(C24>='Env Factor by Pool-Vizo'!$H$34,'Env Factor by Pool-Vizo'!$I$34,IF(C24>='Env Factor by Pool-Vizo'!$H$35,'Env Factor by Pool-Vizo'!$I$35,IF(C24>='Env Factor by Pool-Vizo'!$H$36,'Env Factor by Pool-Vizo'!$I$36,IF(C24>='Env Factor by Pool-Vizo'!$H$37,'Env Factor by Pool-Vizo'!$I$37,IF(C24>='Env Factor by Pool-Vizo'!$H$38,'Env Factor by Pool-Vizo'!$I$38,IF(C24>='Env Factor by Pool-Vizo'!$H$39,'Env Factor by Pool-Vizo'!$I$39,IF(C24>='Env Factor by Pool-Vizo'!$H$40,'Env Factor by Pool-Vizo'!$I$40,IF(C24>='Env Factor by Pool-Vizo'!$H$41,'Env Factor by Pool-Vizo'!$I$41,IF(C24>='Env Factor by Pool-Vizo'!$H$42,'Env Factor by Pool-Vizo'!$I$42,IF(C24>='Env Factor by Pool-Vizo'!$H$43,'Env Factor by Pool-Vizo'!$I$43,IF(C24>='Env Factor by Pool-Vizo'!$H$44,'Env Factor by Pool-Vizo'!$I$44,IF(C24>='Env Factor by Pool-Vizo'!$H$45,'Env Factor by Pool-Vizo'!$I$45,IF(C24>='Env Factor by Pool-Vizo'!$H$46,'Env Factor by Pool-Vizo'!$I$46,IF(C24>='Env Factor by Pool-Vizo'!$H$47,'Env Factor by Pool-Vizo'!$I$47,IF(C24>='Env Factor by Pool-Vizo'!$H$48,'Env Factor by Pool-Vizo'!$I$48,IF(C24>='Env Factor by Pool-Vizo'!$H$49,'Env Factor by Pool-Vizo'!$I$49,'Env Factor by Pool-Vizo'!$I$50)))))))))))))))) | E24: =$F$9 | F24: =IF(E24>='Env Factor by Pool-Vizo'!$J$34,'Env Factor by Pool-Vizo'!$E$89,IF(E24>='Env Factor by Pool-Vizo'!$J$35,'Env Factor by Pool-Vizo'!$E$90,IF(E24>='Env Factor by Pool-Vizo'!$J$36,'Env Factor by Pool-Vizo'!$E$91,IF(E24>='Env Factor by Pool-Vizo'!$J$37,'Env Factor by Pool-Vizo'!$E$92,IF(E24>='Env Factor by Pool-Vizo'!$J$38,'Env Factor by Pool-Vizo'!$E$93,IF(E24>='Env Factor by Pool-Vizo'!$J$39,'Env Factor by Pool-Vizo'!$E$94,IF(E24>='Env Factor by Pool-Vizo'!$J$40,'Env Factor by Pool-Vizo'!$E$95,IF(E24>='Env Factor by Pool-Vizo'!$J$41,'Env Factor by Pool-Vizo'!$E$96,IF(E24>='Env Factor by Pool-Vizo'!$J$42,'Env Factor by Pool-Vizo'!$E$97,IF(E24>='Env Factor by Pool-Vizo'!$J$43,'Env Factor by Pool-Vizo'!$E$98,IF(E24>='Env Factor by Pool-Vizo'!$J$44,'Env Factor by Pool-Vizo'!$E$99,IF(E24>='Env Factor by Pool-Vizo'!$J$45,'Env Factor by Pool-Vizo'!$E$100,'Env Factor by Pool-Vizo'!$E$101)))))))))))) | G24: =D24+F24 | H24: Environmental Factor | I24: =G24
B25: ='Scale Calculation-Vizo'!A21 | C25: ='New Report Calc-Vizo'!$AI$108 | D25: =IF(C25>='Env Factor by Pool-Vizo'!$H$34,'Env Factor by Pool-Vizo'!$I$34,IF(C25>='Env Factor by Pool-Vizo'!$H$35,'Env Factor by Pool-Vizo'!$I$35,IF(C25>='Env Factor by Pool-Vizo'!$H$36,'Env Factor by Pool-Vizo'!$I$36,IF(C25>='Env Factor by Pool-Vizo'!$H$37,'Env Factor by Pool-Vizo'!$I$37,IF(C25>='Env Factor by Pool-Vizo'!$H$38,'Env Factor by Pool-Vizo'!$I$38,IF(C25>='Env Factor by Pool-Vizo'!$H$39,'Env Factor by Pool-Vizo'!$I$39,IF(C25>='Env Factor by Pool-Vizo'!$H$40,'Env Factor by Pool-Vizo'!$I$40,IF(C25>='Env Factor by Pool-Vizo'!$H$41,'Env Factor by Pool-Vizo'!$I$41,IF(C25>='Env Factor by Pool-Vizo'!$H$42,'Env Factor by Pool-Vizo'!$I$42,IF(C25>='Env Factor by Pool-Vizo'!$H$43,'Env Factor by Pool-Vizo'!$I$43,IF(C25>='Env Factor by Pool-Vizo'!$H$44,'Env Factor by Pool-Vizo'!$I$44,IF(C25>='Env Factor by Pool-Vizo'!$H$45,'Env Factor by Pool-Vizo'!$I$45,IF(C25>='Env Factor by Pool-Vizo'!$H$46,'Env Factor by Pool-Vizo'!$I$46,IF(C25>='Env Factor by Pool-Vizo'!$H$47,'Env Factor by Pool-Vizo'!$I$47,IF(C25>='Env Factor by Pool-Vizo'!$H$48,'Env Factor by Pool-Vizo'!$I$48,IF(C25>='Env Factor by Pool-Vizo'!$H$49,'Env Factor by Pool-Vizo'!$I$49,'Env Factor by Pool-Vizo'!$I$50)))))))))))))))) | E25: =$F$9 | F25: =IF(E25>='Env Factor by Pool-Vizo'!$J$34,'Env Factor by Pool-Vizo'!$E$89,IF(E25>='Env Factor by Pool-Vizo'!$J$35,'Env Factor by Pool-Vizo'!$E$90,IF(E25>='Env Factor by Pool-Vizo'!$J$36,'Env Factor by Pool-Vizo'!$E$91,IF(E25>='Env Factor by Pool-Vizo'!$J$37,'Env Factor by Pool-Vizo'!$E$92,IF(E25>='Env Factor by Pool-Vizo'!$J$38,'Env Factor by Pool-Vizo'!$E$93,IF(E25>='Env Factor by Pool-Vizo'!$J$39,'Env Factor by Pool-Vizo'!$E$94,IF(E25>='Env Factor by Pool-Vizo'!$J$40,'Env Factor by Pool-Vizo'!$E$95,IF(E25>='Env Factor by Pool-Vizo'!$J$41,'Env Factor by Pool-Vizo'!$E$96,IF(E25>='Env Factor by Pool-Vizo'!$J$42,'Env Factor by Pool-Vizo'!$E$97,IF(E25>='Env Factor by Pool-Vizo'!$J$43,'Env Factor by Pool-Vizo'!$E$98,IF(E25>='Env Factor by Pool-Vizo'!$J$44,'Env Factor by Pool-Vizo'!$E$99,IF(E25>='Env Factor by Pool-Vizo'!$J$45,'Env Factor by Pool-Vizo'!$E$100,'Env Factor by Pool-Vizo'!$E$101)))))))))))) | G25: =D25+F25 | H25: Environmental Factor | I25: =G25
C30: Environmental Factor Ranges
C31: ="Quarter Ended "&TEXT('Cover-Vizo'!A11,"m/d/yyyy")
C32: Delinquency | E32: Economic Stress | H32: Delinquency | J32: Economic stress
C33: Range | D33: Score | E33: Range | F33: Score | H33: Minimums | I33: Score | J33: Minimums | K33: Score
C34: =IF(H34=0,"Not Risk Rated",">"&TEXT(H34,"#.00%")) | D34: =I34 | E34: =">"&TEXT(J34,"#.00%") | F34: =K34 | H34: ='Environmental Factor Ranges'!J9 | I34: ='Environmental Factor Ranges'!K9 | J34: ='Environmental Factor Ranges'!L9 | K34: ='Environmental Factor Ranges'!M9
C35: =TEXT(H35,"#.00%")&" to "&TEXT(H34-0.0001,"#.00%") | D35: =I35 | E35: =TEXT(J35,"#.00%")&" to "&TEXT(J34-0.0001,"#.00%") | F35: =K35 | H35: ='Environmental Factor Ranges'!J10 | I35: ='Environmental Factor Ranges'!K10 | J35: ='Environmental Factor Ranges'!L10 | K35: ='Environmental Factor Ranges'!M10
C36: =TEXT(H36,"#.00%")&" to "&TEXT(H35-0.0001,"#.00%") | D36: =I36 | E36: =TEXT(J36,"#.00%")&" to "&TEXT(J35-0.0001,"#.00%") | F36: =K36 | H36: ='Environmental Factor Ranges'!J11 | I36: ='Environmental Factor Ranges'!K11 | J36: ='Environmental Factor Ranges'!L11 | K36: ='Environmental Factor Ranges'!M11
C37: =TEXT(H37,"#.00%")&" to "&TEXT(H36-0.0001,"#.00%") | D37: =I37 | E37: =TEXT(J37,"#.00%")&" to "&TEXT(J36-0.0001,"#.00%") | F37: =K37 | H37: ='Environmental Factor Ranges'!J12 | I37: ='Environmental Factor Ranges'!K12 | J37: ='Environmental Factor Ranges'!L12 | K37: ='Environmental Factor Ranges'!M12
C38: =TEXT(H38,"#.00%")&" to "&TEXT(H37-0.0001,"#.00%") | D38: =I38 | E38: =TEXT(J38,"#.00%")&" to "&TEXT(J37-0.0001,"#.00%") | F38: =K38 | H38: ='Environmental Factor Ranges'!J13 | I38: ='Environmental Factor Ranges'!K13 | J38: ='Environmental Factor Ranges'!L13 | K38: ='Environmental Factor Ranges'!M13
C39: =TEXT(H39,"#.00%")&" to "&TEXT(H38-0.0001,"#.00%") | D39: =I39 | E39: =TEXT(J39,"#.00%")&" to "&TEXT(J38-0.0001,"#.00%") | F39: =K39 | H39: ='Environmental Factor Ranges'!J14 | I39: ='Environmental Factor Ranges'!K14 | J39: ='Environmental Factor Ranges'!L14 | K39: ='Environmental Factor Ranges'!M14
C40: =TEXT(H40,"#.00%")&" to "&TEXT(H39-0.0001,"#.00%") | D40: =I40 | E40: =TEXT(J40,"#.00%")&" to "&TEXT(J39-0.0001,"#.00%") | F40: =K40 | H40: ='Environmental Factor Ranges'!J15 | I40: ='Environmental Factor Ranges'!K15 | J40: ='Environmental Factor Ranges'!L15 | K40: ='Environmental Factor Ranges'!M15
C41: =TEXT(H41,"#0.00%")&" to "&TEXT(H40-0.0001,"#0.00%") | D41: =I41 | E41: =TEXT(J41,"#.00%")&" to "&TEXT(J40-0.0001,"#.00%") | F41: =K41 | H41: ='Environmental Factor Ranges'!J16 | I41: ='Environmental Factor Ranges'!K16 | J41: ='Environmental Factor Ranges'!L16 | K41: ='Environmental Factor Ranges'!M16
C42: =TEXT(H42,"#0.00%")&" to "&TEXT(H41-0.0001,"#0.00%") | D42: =I42 | E42: =TEXT(J42,"#.00%")&" to "&TEXT(J41-0.0001,"#.00%") | F42: =K42 | H42: ='Environmental Factor Ranges'!J17 | I42: ='Environmental Factor Ranges'!K17 | J42: ='Environmental Factor Ranges'!L17 | K42: ='Environmental Factor Ranges'!M17
C43: =TEXT(H43,"#0.00%")&" to "&TEXT(H42-0.0001,"#0.00%") | D43: =I43 | E43: =TEXT(J43,"#.00%")&" to "&TEXT(J42-0.0001,"#.00%") | F43: =K43 | H43: ='Environmental Factor Ranges'!J18 | I43: ='Environmental Factor Ranges'!K18 | J43: ='Environmental Factor Ranges'!L18 | K43: ='Environmental Factor Ranges'!M18
C44: =TEXT(H44,"#.00%")&" to "&TEXT(H43-0.0001,"#.00%") | D44: =I44 | E44: =TEXT(J44,"#.00%")&" to "&TEXT(J43-0.0001,"#.00%") | F44: =K44 | H44: ='Environmental Factor Ranges'!J19 | I44: ='Environmental Factor Ranges'!K19 | J44: ='Environmental Factor Ranges'!L19 | K44: ='Environmental Factor Ranges'!M19
C45: =TEXT(H45,"#.00%")&" to "&TEXT(H44-0.0001,"#.00%") | D45: =I45 | E45: =TEXT(J45,"#.00%")&" to "&TEXT(J44-0.0001,"#.00%") | F45: =K45 | H45: ='Environmental Factor Ranges'!J20 | I45: ='Environmental Factor Ranges'!K20 | J45: ='Environmental Factor Ranges'!L20 | K45: ='Environmental Factor Ranges'!M20
C46: =TEXT(H46,"#.00%")&" to "&TEXT(H45-0.0001,"#.00%") | D46: =I46 | E46: =TEXT(J46,"#.00%")&" to "&TEXT(J45-0.0001,"#.00%") | F46: =K46 | H46: ='Environmental Factor Ranges'!J21 | I46: ='Environmental Factor Ranges'!K21 | J46: ='Environmental Factor Ranges'!L21 | K46: ='Environmental Factor Ranges'!M21
C47: =TEXT(H47,"#.00%")&" to "&TEXT(H46-0.0001,"#.00%") | D47: =I47 | E47: =TEXT(J47,"#.00%")&" to "&TEXT(J46-0.0001,"#.00%") | F47: =K47 | H47: ='Environmental Factor Ranges'!J22 | I47: ='Environmental Factor Ranges'!K22 | J47: ='Environmental Factor Ranges'!L22 | K47: ='Environmental Factor Ranges'!M22
C48: =TEXT(H48,"#.00%")&" to "&TEXT(H47-0.0001,"#.00%") | D48: =I48 | H48: ='Environmental Factor Ranges'!J23 | I48: ='Environmental Factor Ranges'!K23
C49: =TEXT(H49,"#.00%")&" to "&TEXT(H48-0.0001,"#.00%") | D49: =I49 | H49: ='Environmental Factor Ranges'!J24 | I49: ='Environmental Factor Ranges'!K24
C50: =IF(H50=0,"Not Risk Rated","<"&TEXT(H50,"#.00%")) | D50: =I50 | H50: ='Environmental Factor Ranges'!J25 | I50: ='Environmental Factor Ranges'!K25
B88: Delinquency Variance | C88: Delinquency Score | D88: Economic Stress Actual | E88: Economic Stress Score
B89: =IF('Env Factor by Pool-Vizo'!H34=0,"Not Risk Rated",">"&TEXT('Env Factor by Pool-Vizo'!H34,"#.00%")) | C89: ='Env Factor by Pool-Vizo'!I34 | D89: =">"&TEXT('Env Factor by Pool-Vizo'!J34,"#.00%") | E89: ='Env Factor by Pool-Vizo'!K34
B90: =TEXT('Env Factor by Pool-Vizo'!H35,"#.00%")&" to "&TEXT('Env Factor by Pool-Vizo'!H34-0.0001,"#.00%") | C90: ='Env Factor by Pool-Vizo'!I35 | D90: =TEXT('Env Factor by Pool-Vizo'!J35,"#.00%")&" to "&TEXT('Env Factor by Pool-Vizo'!J34-0.0001,"#.00%") | E90: ='Env Factor by Pool-Vizo'!K35
B91: =TEXT('Env Factor by Pool-Vizo'!H36,"#.00%")&" to "&TEXT('Env Factor by Pool-Vizo'!H35-0.0001,"#.00%") | C91: ='Env Factor by Pool-Vizo'!I36 | D91: =TEXT('Env Factor by Pool-Vizo'!J36,"#.00%")&" to "&TEXT('Env Factor by Pool-Vizo'!J35-0.0001,"#.00%") | E91: ='Env Factor by Pool-Vizo'!K36
B92: =TEXT('Env Factor by Pool-Vizo'!H37,"#.00%")&" to "&TEXT('Env Factor by Pool-Vizo'!H36-0.0001,"#.00%") | C92: ='Env Factor by Pool-Vizo'!I37 | D92: =TEXT('Env Factor by Pool-Vizo'!J37,"#.00%")&" to "&TEXT('Env Factor by Pool-Vizo'!J36-0.0001,"#.00%") | E92: ='Env Factor by Pool-Vizo'!K37
B93: =TEXT('Env Factor by Pool-Vizo'!H38,"#.00%")&" to "&TEXT('Env Factor by Pool-Vizo'!H37-0.0001,"#.00%") | C93: ='Env Factor by Pool-Vizo'!I38 | D93: =TEXT('Env Factor by Pool-Vizo'!J38,"#.00%")&" to "&TEXT('Env Factor by Pool-Vizo'!J37-0.0001,"#.00%") | E93: ='Env Factor by Pool-Vizo'!K38
B94: =TEXT('Env Factor by Pool-Vizo'!H39,"#.00%")&" to "&TEXT('Env Factor by Pool-Vizo'!H38-0.0001,"#.00%") | C94: ='Env Factor by Pool-Vizo'!I39 | D94: =TEXT('Env Factor by Pool-Vizo'!J39,"#.00%")&" to "&TEXT('Env Factor by Pool-Vizo'!J38-0.0001,"#.00%") | E94: ='Env Factor by Pool-Vizo'!K39
B95: =TEXT('Env Factor by Pool-Vizo'!H40,"#.00%")&" to "&TEXT('Env Factor by Pool-Vizo'!H39-0.0001,"#.00%") | C95: ='Env Factor by Pool-Vizo'!I40 | D95: =TEXT('Env Factor by Pool-Vizo'!J40,"#.00%")&" to "&TEXT('Env Factor by Pool-Vizo'!J39-0.0001,"#.00%") | E95: ='Env Factor by Pool-Vizo'!K40
B96: =TEXT('Env Factor by Pool-Vizo'!H41,"#0.00%")&" to "&TEXT('Env Factor by Pool-Vizo'!H40-0.0001,"#0.00%") | C96: ='Env Factor by Pool-Vizo'!I41 | D96: =TEXT('Env Factor by Pool-Vizo'!J41,"#.00%")&" to "&TEXT('Env Factor by Pool-Vizo'!J40-0.0001,"#.00%") | E96: ='Env Factor by Pool-Vizo'!K41
B97: =TEXT('Env Factor by Pool-Vizo'!H42,"#0.00%")&" to "&TEXT('Env Factor by Pool-Vizo'!H41-0.0001,"#0.00%") | C97: ='Env Factor by Pool-Vizo'!I42 | D97: =TEXT('Env Factor by Pool-Vizo'!J42,"#.00%")&" to "&TEXT('Env Factor by Pool-Vizo'!J41-0.0001,"#.00%") | E97: ='Env Factor by Pool-Vizo'!K42
B98: =TEXT('Env Factor by Pool-Vizo'!H43,"#0.00%")&" to "&TEXT('Env Factor by Pool-Vizo'!H42-0.0001,"#0.00%") | C98: ='Env Factor by Pool-Vizo'!I43 | D98: =TEXT('Env Factor by Pool-Vizo'!J43,"#.00%")&" to "&TEXT('Env Factor by Pool-Vizo'!J42-0.0001,"#.00%") | E98: ='Env Factor by Pool-Vizo'!K43
